Workbook
Name IQ_CH: 110000
Name IQ_CQ: 5000
Name IQ_CY: 10000
Name IQ_DAILY: 500000
Name IQ_FH: 100000
Name IQ_FQ: 500
Name IQ_FY: 1000
Name IQ_LTM: 2000
Name IQ_MONTH: 15000
Name IQ_NTM: 6000
Name IQ_WEEK: 50000
Name IQ_YTD: 3000

Sheet benchmark_tasks
A1: 1 | B1: 2 | C1: 3 | D1: 4 | E1: 5 | F1: 6 | G1: 7 | H1: 8 | I1: 9 | J1: 10 | K1: 11 | L1: 12 | M1: 13 | N1: 14 | O1: 15 | P1: 16 | Q1: 17 | R1: 18 | S1: 19 | T1: 20 | U1: 21 | V1: 22 | W1: 23 | X1: 24 | Y1: 25
A2: id | B2: question_id | C2: prompt | D2: answer_type | E2: task_type | F2: task_format | G2: gold_answer | H2: options | I2: grading_criteria | J2: numeric_tolerance | K2: acceptable_variants | L2: context | M2: attached_files | N2: regulatory_framework | O2: applicable_regulatory_year | P2: category | Q2: subcategory | R2: skills | S2: education_level | T2: notes | U2: source | V2: submitted_by | W2: is_public | X2: created_at | Y2: validated_by | Z2: validation_status | AA2: pdf_path | AB2: excel_path
A3: 1 | B3: 12008933_0001 | C3: Der Ablauf eines befristeten Arbeitsverhältnisses wird durch die Einberufung zum Präsenzdienst gehemmt. | D3: single_choice | E3: interpretation_of_law | F3: single_choice | G3: A | H3: {"a": "RICHTIG", "b": "FALSCH"} | I3: Exact match of choice_id (A/B); case-insensitive. No partial credit. | N3: austrian_tax_law | O3: 2026 | P3: tax | Q3: personalverrechnung | R3: Beispiel 9; Theorie; Befristung; Präsenzdienst | S3: professional_examinations | U3: batch_import | V3: batch_admin | W3: 1 | X3: 2026-04-29 13:25:24.933445 | Y3: Manuel Kaburek | Z3: approved
A4: 2 | B4: 12008933_0002 | C4: Fallen in ein Urlaubsjahr Zeiten eines Präsenz-, Zivil oder Ausbildungsdienstes, gebührt ein Urlaub nur in jenem aliquoten Ausmaß, das dem um den Präsenz-, Zivil- oder Ausbildungsdienst verkürzten Arbeitsjahr entspricht. | D4: single_choice | E4: interpretation_of_law | F4: single_choice | G4: A | H4: {"a": "RICHTIG", "b": "FALSCH"} | I4: Exact match of choice_id (A/B); case-insensitive. No partial credit. | N4: austrian_tax_law | O4: 2026 | P4: tax | Q4: personalverrechnung | R4: Beispiel 9; Theorie; Urlaub; Präsenzdienst | S4: professional_examinations | U4: batch_import | V4: batch_admin | W4: 1 | X4: 2026-04-29 13:25:24.933445 | Y4: Manuel Kaburek | Z4: approved
A5: 3 | B5: 12008933_0003 | C5: Der Wiederantritt nach dem Präsenz- bzw. Zivildienst muss innerhalb von 12 Werktagen nach der Entlassung aus dem Dienst erfolgen. | D5: single_choice | E5: interpretation_of_law | F5: single_choice | G5: A | H5: {"a": "RICHTIG", "b": "FALSCH"} | I5: Exact match of choice_id (A/B); case-insensitive. No partial credit. | N5: austrian_tax_law | O5: 2026 | P5: tax | Q5: personalverrechnung | R5: Beispiel 9; Theorie; Präsenzdienst; Wiederantritt | S5: professional_examinations | U5: batch_import | V5: batch_admin | W5: 1 | X5: 2026-04-29 13:25:24.933445 | Y5: Manuel Kaburek | Z5: approved
A6: 4 | B6: 12008933_0004 | C6: Die DG:innen-Seite hat Herrn H. nach Ende der Pflichtversicherung bei der ÖGK abzumelden. Die Abmeldung ist binnen 7 Tagen zu erstatten. Diese 7-Tage Frist ist entweder vom „Ende der Beschäftigung“ oder vom „Ende Entgelt“ zu berechnen. Sind diese beiden Termine nicht ident, ist jeweils vom späteren Termin auszugehen. | D6: single_choice | E6: interpretation_of_law | F6: single_choice | G6: A | H6: {"a": "RICHTIG", "b": "FALSCH"} | I6: Exact match of choice_id (A/B); case-insensitive. No partial credit. | N6: austrian_tax_law | O6: 2026 | P6: tax | Q6: personalverrechnung | R6: Beispiel 8; Theorie; Abmeldung ÖGK; 7-Tage-Frist | S6: professional_examinations | U6: batch_import | V6: batch_admin | W6: 1 | X6: 2026-04-29 13:31:49.379318 | Y6: Manuel Kaburek | Z6: approved
A7: 5 | B7: 12008933_0005 | C7: Für Zeiträume, für die eine Urlaubsersatzleistung oder eine Kündigungsentschädigung gebührt, ruht der Anspruch auf Arbeitslosengeld oder Notstandshilfe. | D7: single_choice | E7: interpretation_of_law | F7: single_choice | G7: A | H7: {"a": "RICHTIG", "b": "FALSCH"} | I7: Exact match of choice_id (A/B); case-insensitive. No partial credit. | N7: austrian_tax_law | O7: 2026 | P7: tax | Q7: personalverrechnung | R7: Beispiel 8; Theorie; UEL; Kündigungsentschädigung; Arbeitslosengeld | S7: professional_examinations | U7: batch_import | V7: batch_admin | W7: 1 | X7: 2026-04-29 13:31:49.387136 | Y7: Manuel Kaburek | Z7: approved
A8: 6 | B8: 12008933_0018 | C8: Frau J. ist seit 15.11.2017 als Teilzeitarbeiterin im Unternehmen beschäftigt.\nIhr Bruttostundenlohn beträgt seit Jänner dieses Jahres € 15,00.\nIhre Normalarbeitszeit beträgt lt. Vertrag 20 Stunden. (Montag bis Freitag jeweils von 8 Uhr bis 12 Uhr.)\nVon Jänner bis inkl. Oktober 2026 wurden insgesamt € 12.471,47 laufende Bruttobezüge abgerechnet.\n\nMEHRLEISTUNGSSTUNDEN\nDie Mitarbeiterin leistete im Abrechnungsmonat ausnahmsweise 4 TZ-Mehrarbeitsstunden.\nDie Leistung der Stunden erfolgten ausnahmsweise, es liegt keine Regelmäßigkeit vor.\n\nBitte beachten Sie die allgemeine Angabe bzgl. ALLER Sonderzahlungen auf Seite 2!\n\nSämtliche AUSZAHLUNGSBETRÄGE sind zu ermitteln. | D8: open_text | E8: calculation | F8: open_text | G8: 789.52 | H8: null | I8: Akzeptiere EUR-Betrag mit 2 Dezimalstellen; Dezimaltrennzeichen „,“ oder „.“ zulässig. | J8: 1 | M8: C:\Users\dhoellmu\OneDrive - WU Wien\Dokumente\AccountingBench\backend\uploads\Wichtige_Werte_ab_7.1.2026-1.pdf | N8: austrian_tax_law | O8: 2026 | P8: tax | Q8: personalverrechnung | R8: Beispiel 10; Teilzeit; Mehrarbeitsstunden; Sonderzahlungen; Auszahlungsbetrag | S8: professional_examinations | U8: batch_import | V8: batch_admin | W8: 1 | X8: 2026-04-29 13:31:49.441551 | Y8: Manuel Kaburek | Z8: approved
A9: 7 | B9: 12008933_0006 | C9: Eine Rückforderung von Ausbildungskosten ist, bei Vorliegen der sonstigen Voraussetzungen, bei einer einvernehmlichen Auflösung nicht möglich. | D9: single_choice | E9: interpretation_of_law | F9: single_choice | G9: A | H9: {"a": "RICHTIG", "b": "FALSCH"} | I9: Exact match of choice_id (A/B); case-insensitive. No partial credit. | N9: austrian_tax_law | O9: 2026 | P9: tax | Q9: personalverrechnung | R9: Beispiel 8; Theorie; Ausbildungskosten; einvernehmliche Auflösung | S9: professional_examinations | U9: batch_import | V9: batch_admin | W9: 1 | X9: 2026-04-29 13:31:49.400185 | Y9: Manuel Kaburek | Z9: approved
A10: 8 | B10: 12008933_0013 | C10: Entscheiden Sie, ob folgende Aussage richtig oder falsch ist: „Hat der Lehrling beim/bei der Lehrberechtigten die für den Lehrberuf festgesetzte Lehrzeit bis zur Hälfte zurückgelegt, so trifft den/die Lehrberechtigte:n die Weiterbeschäftigungspflicht nur im halben Ausmaß.“ | D10: single_choice | E10: interpretation_of_law | F10: single_choice | G10: A | H10: {"a": "RICHTIG", "b": "FALSCH"} | I10: Exact match of choice_id (A/B); case-insensitive. No partial credit. | N10: austrian_tax_law | O10: 2026 | P10: tax | Q10: personalverrechnung | R10: Lehrlingsrecht; Weiterbeschäftigungspflicht; BAG | S10: professional_examinations | U10: batch_import | V10: batch_admin | W10: 1 | X10: 2026-04-29 13:31:49.423189 | Y10: Manuel Kaburek | Z10: approved
A11: 9 | B11: 12008933_0016 | C11: Entscheiden Sie, ob die folgende Aussage RICHTIG oder FALSCH ist: „Für den Bereich der Lohnnebenkosten (DB, DZ, KommSt) werden wesentlich beteiligte Gesellschafter Geschäftsführer:innen in der Regel als DN:innen qualifiziert. Ihre Bezüge unterliegen daher der Lohnnebenkostenpflicht.“ | D11: single_choice | E11: interpretation_of_law | F11: single_choice | G11: A | H11: {"a": "RICHTIG", "b": "FALSCH"} | I11: Exact match of choice_id (A/B); case-insensitive. No partial credit. | N11: austrian_tax_law | O11: 2026 | P11: tax | Q11: personalverrechnung | R11: Lohnnebenkosten; Gesellschafter-Geschäftsführer; DB/DZ/KommSt | S11: professional_examinations | U11: batch_import | V11: batch_admin | W11: 1 | X11: 2026-04-29 13:31:49.480110 | Y11: Manuel Kaburek | Z11: approved
A12: 10 | B12: 12008933_0009 | C12: Der/die Betriebsrat:rätin muss | D12: single_choice | E12: interpretation_of_law | F12: single_choice | G12: B | H12: {"a": "vor der Entlassung zwingend verst\u00e4ndigt werden", "b": "vor der Entlassung nicht verst\u00e4ndigt werden (Besprechung binnen 3 Arbeitstagen)", "c": "Keine Antwort ist richtig."} | I12: Exact match of choice_id (A/B/C); case-insensitive. No partial credit. | N12: austrian_tax_law | O12: 2026 | P12: tax | Q12: personalverrechnung | R12: Beispiel 2; Theorie; Entlassung; Betriebsrat; Verständigungspflicht | S12: professional_examinations | U12: batch_import | V12: batch_admin | W12: 1 | X12: 2026-04-29 13:31:49.437383 | Y12: Manuel Kaburek | Z12: approved
A13: 11 | B13: 12008933_0015 | C13: Entscheiden Sie, ob die folgende Aussage RICHTIG oder FALSCH ist: „Für Fahrzeuge mit einem CO2-Emissionswert von 0 Gramm pro Kilometer ist kein Sachbezug anzusetzen. Dies gilt auch für Hybridfahrzeuge.“ | D13: single_choice | E13: interpretation_of_law | F13: single_choice | G13: B | H13: {"a": "RICHTIG", "b": "FALSCH"} | I13: Exact match of choice_id (A/B); case-insensitive. No partial credit. | N13: austrian_tax_law | O13: 2026 | P13: tax | Q13: personalverrechnung | R13: Sachbezug KFZ; CO2=0; Hybrid vs. Elektro | S13: professional_examinations | U13: batch_import | V13: batch_admin | W13: 1 | X13: 2026-04-29 13:31:49.706738 | Y13: Manuel Kaburek | Z13: approved
A14: 12 | B14: 12008933_0012 | C14: Entscheiden Sie, ob folgende Aussage richtig oder falsch ist: „Die Gründe, die den/die Lehrberechtigte:n zur vorzeitigen Auflösung des Lehrverhältnisses berechtigen, sind im KJBG geregelt.“ | D14: single_choice | E14: interpretation_of_law | F14: single_choice | G14: B | H14: {"a": "RICHTIG", "b": "FALSCH"} | I14: Exact match of choice_id (A/B); case-insensitive. No partial credit. | N14: austrian_tax_law | O14: 2026 | P14: tax | Q14: personalverrechnung | R14: Lehrlingsrecht; Auflösung; BAG vs. KJBG | S14: professional_examinations | U14: batch_import | V14: batch_admin | W14: 1 | X14: 2026-04-29 13:31:49.484320 | Y14: Manuel Kaburek | Z14: approved
A15: 13 | B15: 12008933_0010 | C15: Entscheiden Sie bitte, ob folgende Aussagen richtig oder falsch sind:\n2. Für Fahrzeuge mit einem CO2-Emissionswert von 0 Gramm pro Kilometer ist kein Sachbezug anzusetzen. Dies gilt auch für Hybridfahrzeuge. | D15: single_choice | E15: interpretation_of_law | F15: single_choice | G15: B | H15: {"a": "RICHTIG", "b": "FALSCH"} | I15: Exact match of choice_id (A/B); case-insensitive. No partial credit. | N15: austrian_tax_law | O15: 2026 | P15: tax | Q15: personalverrechnung | R15: Beispiel 1; Theorie; Sachbezug; CO2; Hybridfahrzeuge | S15: professional_examinations | U15: batch_import | V15: batch_admin | W15: 1 | X15: 2026-04-29 13:31:49.480110 | Y15: Manuel Kaburek | Z15: approved
A16: 14 | B16: 12008933_0019 | C16: Herr I. ist als Arbeiter im Unternehmen tätig. Sein Eintritt erfolgte am 01.12.2021.\nDer vereinbarte Bruttolohn beträgt seit Jahresbeginn monatlich € 3.000,00.\n\nPRÄSENZDIENST\nDem Personalbüro ist bekannt, dass der Mitarbeiter mit Beginn 01.03.2026 für 6 Monate seinen Präsenzdienst leistete.\nIm Zuge der Februarabrechnung wurden die aliquoten Sonderzahlungen ausbezahlt.\nHerr I. ist nach dem Präsenzdienst ab 01.09.2026 wieder im Dienst!\n\nBitte beachten Sie die allgemeine Angabe bzgl. ALLER Sonderzahlungen auf Seite 2!\n\nSämtliche AUSZAHLUNGSBETRÄGE sind zu ermitteln. | D16: open_text | E16: calculation | F16: open_text | G16: 2079.38 | H16: null | I16: Akzeptiere EUR-Betrag mit 2 Dezimalstellen; Dezimaltrennzeichen „,“ oder „.“ zulässig. | J16: 1 | M16: C:\Users\dhoellmu\OneDrive - WU Wien\Dokumente\AccountingBench\backend\uploads\Wichtige_Werte_ab_7.1.2026-1.pdf | N16: austrian_tax_law | O16: 2026 | P16: tax | Q16: personalverrechnung | R16: Beispiel 9; Präsenzdienst; Sonderzahlungen; Auszahlungsbetrag | S16: professional_examinations | U16: batch_import | V16: batch_admin | W16: 1 | X16: 2026-04-29 13:31:49.484320 | Y16: Manuel Kaburek | Z16: approved
A17: 15 | B17: 12008933_0007 | C17: Die Gründe, die den:die Lehrberechtigte:n zur vorzeitigen Auflösung des Lehrverhältnisses berechtigen sind im KJBG geregelt. | D17: single_choice | E17: interpretation_of_law | F17: single_choice | G17: B | H17: {"a": "RICHTIG", "b": "FALSCH"} | I17: Exact match of choice_id (A/B); case-insensitive. No partial credit. | N17: austrian_tax_law | O17: 2026 | P17: tax | Q17: personalverrechnung | R17: Beispiel 5; Theorie; Lehrlingsrecht; Auflösung; KJBG | S17: professional_examinations | U17: batch_import | V17: batch_admin | W17: 1 | X17: 2026-04-29 13:31:49.400185 | Y17: Manuel Kaburek | Z17: approved
A18: 16 | B18: 12008933_0008 | C18: Hat der Lehrling beim/der Lehrberechtigten die für den Lehrberuf festgesetzte Lehrzeit bis zur Hälfte zurückgelegt, so trifft den/die Lehrberechtigte:n die Weiterbeschäftigungspflicht nur im halben Ausmaß. | D18: single_choice | E18: interpretation_of_law | F18: single_choice | G18: A | H18: {"a": "RICHTIG", "b": "FALSCH"} | I18: Exact match of choice_id (A/B); case-insensitive. No partial credit. | N18: austrian_tax_law | O18: 2026 | P18: tax | Q18: personalverrechnung | R18: Beispiel 5; Theorie; Lehrlingsrecht; Weiterbeschäftigungspflicht | S18: professional_examinations | U18: batch_import | V18: batch_admin | W18: 1 | X18: 2026-04-29 13:31:49.400185 | Y18: Manuel Kaburek | Z18: approved
A19: 17 | B19: 12008933_0011 | C19: Entscheiden Sie bitte, ob folgende Aussagen richtig oder falsch sind:\n1. Für den Bereich der Lohnnebenkosten (DB, DZ, KommSt) werden wesentlich beteiligte Gesellschafter Geschäftsführer:innen in der Regel als DN:innen qualifiziert. Ihre Bezüge unterliegen daher der Lohnnebenkostenpflicht. | D19: single_choice | E19: interpretation_of_law | F19: single_choice | G19: A | H19: {"a": "RICHTIG", "b": "FALSCH"} | I19: Exact match of choice_id (A/B); case-insensitive. No partial credit. | N19: austrian_tax_law | O19: 2026 | P19: tax | Q19: personalverrechnung | R19: Beispiel 1; Theorie; Lohnnebenkosten; Gesellschafter-Geschäftsführer | S19: professional_examinations | U19: batch_import | V19: batch_admin | W19: 1 | X19: 2026-04-29 13:31:49.534703 | Y19: Manuel Kaburek | Z19: approved
A20: 18 | B20: 12008933_0014 | C20: Entscheiden Sie, welche Aussage korrekt ist: „Der/die Betriebsrat:rätin muss bei einer Entlassung …“ | D20: single_choice | E20: interpretation_of_law | F20: single_choice | G20: B | H20: {"a": "\u2026 vor der Entlassung zwingend verst\u00e4ndigt werden, ansonsten ist die Entlassung unwirksam.", "b": "\u2026 vor der Entlassung nicht verst\u00e4ndigt werden; die bereits ausgesprochene Entlassung ist unverz\u00fcglich mitzuteilen und auf Verlangen innerhalb von 3 Arbeitstagen zu besprechen.", "c": "Keine Antwort ist richtig."} | I20: Exact match of choice_id (A/B/C); case-insensitive. No partial credit. | N20: austrian_tax_law | O20: 2026 | P20: tax | Q20: personalverrechnung | R20: Entlassung; Betriebsrat; Verständigungspflicht | S20: professional_examinations | U20: batch_import | V20: batch_admin | W20: 1 | X20: 2026-04-29 13:31:49.423189 | Y20: Manuel Kaburek | Z20: approved
A21: 19 | B21: 12008933_0020 | C21: Im Zuge des Gesprächs am 03.11.2026 wird schriftlich festgehalten, dass der DN ab dem Folgetag bis Ende des Dienstverhältnisses Urlaub konsumiert und die restliche Dauer des Vertragsverhältnisses vom Dienst freigestellt wird.\nEin Wiedereintritt in diesem Kalenderjahr nicht zu erwarten.\nKeine Rückverrechnung der bereits ausbezahlten Sonderzahlung.\nDie Aliquotierung allfälliger Bezüge erfolgt gemäß KV, bei Ein- und Austritt nach effektiven Std.\nBitte beachten Sie die allgemeine Angabe bzgl. ALLER Sonderzahlungen auf Seite 2!\n\nSämtliche Beendigungsansprüche bis zum Auszahlungsbetrag sind zu berechnen. | D21: open_text | E21: calculation | F21: open_text | G21: 72380.00 | H21: null | I21: Akzeptiere EUR-Betrag mit 2 Dezimalstellen; Dezimaltrennzeichen „,“ oder „.“ zulässig. | J21: 1 | M21: C:\Users\dhoellmu\OneDrive - WU Wien\Dokumente\AccountingBench\backend\uploads\Wichtige_Werte_ab_7.1.2026-1.pdf | N21: austrian_tax_law | O21: 2026 | P21: tax | Q21: personalverrechnung | R21: Beispiel 8; Beendigung; Freistellung; Abfertigung ALT; Auszahlungsbetrag | S21: professional_examinations | U21: batch_import | V21: batch_admin | W21: 1 | X21: 2026-04-29 13:31:49.441551 | Y21: Manuel Kaburek | Z21: approved
A22: 20 | B22: 12008933_0022 | C22: Herr G. ist als Arbeiter im Unternehmen tätig. Sein Eintritt erfolgte am 15.08.2021.\nDer vereinbarte Bruttomonatslohn beträgt seit Jahresbeginn € 3.660,00.\nLt. Lohnkonto betragen die laufenden Bezüge im aktuellen Kalenderjahr bis einschließlich Nov € 40.471,88!\n\nMEHRLEISTUNGSSTUNDEN / FEIERTAGSARBEIT\nDer Mitarbeiter war am 01.11.2026 4,5 Stunden (7:30 Uhr – 12:00 Uhr) im Einsatz.\nDie Entlohnung für die Feiertagsarbeit erfolgt gemäß KV bzw. ARG.\nDie Leistung der Stunden erfolgte ausnahmsweise, es liegt keine Regelmäßigkeit vor.\n\nAuszug KV:\nFeiertagsentlohnung\nFür jede an einem gesetzlichen Feiertag innerhalb der für den entsprechenden Wochentag vereinbarten regelmäßigen Arbeitszeit erbrachte Arbeitsleistung gebührt neben dem Entgelt im Sinne des § 9 Abs. 2 ARG auch das auf die geleistete Arbeit entfallende Entgelt. (Teiler 1/143)\nÜberstunden\nDie Überstundengrundvergütung und Grundlage für die Berechnung des Überstundenzuschlages beträgt 1/143 des Monatslohnes (bei 38,5 Wochenstunden NAZ) ohne Zulagen und Zuschläge.\nÜberstunden an Feiertagen − das sind Arbeitsleistungen, die außerhalb der für den entsprechenden Wochentag vereinbarten normalen Arbeitszeit erbracht werden − sind ab der ersten Überstunde mit einem Zuschlag von 100 % zu entlohnen.\n\nNACHZAHLUNG\nIm Abrechnungsmonat gebührt eine unwillkürliche Nachzahlung in der Höhe von € 380,00.\nEs handelt sich dabei um einen laufenden Bezug aus der Abrechnungsperiode August des Vorjahres.\n(Die damalige SV-Bemessungsgrundlage betrug € 3.020,00 mit einem %-Satz von 18,07%)\n\nBitte beachten Sie eventuelle Feiertage im Abrechnungsmonat sowie die allgemeine Angabe bzgl. ALLER Sonderzahlungen auf Seite 2!\n\nSämtliche AUSZAHLUNGSBETRÄGE sind zu ermitteln. | D22: open_text | E22: calculation | F22: open_text | G22: 2853.12 | H22: null | I22: Akzeptiere EUR-Betrag mit 2 Dezimalstellen; Dezimaltrennzeichen „,“ oder „.“ zulässig. | J22: 1 | M22: C:\Users\dhoellmu\OneDrive - WU Wien\Dokumente\AccountingBench\backend\uploads\Wichtige_Werte_ab_7.1.2026-1.pdf | N22: austrian_tax_law | O22: 2026 | P22: tax | Q22: personalverrechnung | R22: Beispiel 7; Feiertagsarbeit; Überstunden; Nachzahlung; Auszahlungsbetrag | S22: professional_examinations | U22: batch_import | V22: batch_admin | W22: 1 | X22: 2026-04-29 14:03:42.998558 | Y22: Manuel Kaburek | Z22: approved
A23: 21 | B23: 12008933_0024 | C23: Lehrlingseinkommen € 1.750,00 von 01.01.2026 bis 22.11.2026.\nAb 23.11.2026 Arbeiterlohn € 2.800,00.\nLAP-Prämie € 200,00.\n\n@ Sonderzahlungen:\n€ 1.750 / 365 x 326 = aliquotes UG Lehrling\n€ 1.750 / 365 x 326 = aliquotes WG Lehrling\n€ 2.800 / 365 x 39 = aliquotes UG Arbeiter\n€ 2.800 / 365 x 39 = aliquotes WG Arbeiter\nbereits erhalten =\noffen =\n\nDie LAP-Prämie wird am Monatsende ausbezahlt.\n\nSämtliche AUSZAHLUNGSBETRÄGE sind zu ermitteln. | D23: open_text | E23: calculation | F23: open_text | G23: 1772.56 | H23: null | I23: Akzeptiere EUR-Betrag mit 2 Dezimalstellen; Dezimaltrennzeichen „,“ oder „.“ zulässig. | J23: 1 | M23: C:\Users\dhoellmu\OneDrive - WU Wien\Dokumente\AccountingBench\backend\uploads\Wichtige_Werte_ab_7.1.2026-1.pdf | N23: austrian_tax_law | O23: 2026 | P23: tax | Q23: personalverrechnung | R23: Beispiel 5; Lehrling; LAP-Prämie; Sonderzahlungen aliquot; Wechsel Arbeiter; Auszahlungsbetrag | S23: professional_examinations | U23: batch_import | V23: batch_admin | W23: 1 | X23: 2026-04-29 14:03:43.001523 | Y23: Manuel Kaburek | Z23: approved
A24: 22 | B24: 12008933_0025 | C24: Herr D. seit 01.01.1999 als Reisender im Unternehmen tätig.\nSein Bruttomonatsgehalt beträgt seit Jänner dieses Jahres € 6.000,00.\n\nMEHRLEISTUNGSSTUNDEN\nSeit Jahresbeginn werden monatlich folgende Mehrleistungsstunden PAUSCHAL abgerechnet:\n• KV-Mehrarbeitsstunden: Differenz auf 40 Stunden wöchentlich (50 % ZS lt. KV / Teiler 167) (gem.§ 68 (2) EStG)\n• Überstundenpauschale: 15 h (50 % ZS lt. KV / Teiler 143) (gem.§ 68 (2) EStG)\n\nSACHBEZÜGE\nDem DN wird seit Jänner 2021 ein Firmen-PKW zur Privatnutzung überlassen.\nDer aktuelle PKW wurde am 01.09.2023 um € 51.860,00 vom Unternehmen erworben (140 g/km).\nLt. Vertrag ist der Reisende zur Führung eines Fahrtenbuches verpflichtet.\nNachweislich wird der PKW nicht mehr als 6.000 km im Jahresdurchschnitt privat genutzt.\n\nREISEKOSTEN: Der Angestellte unternimmt im Abrechnungsmonat folgende Dienstreisen im Raum OÖ:\nReisetag von - bis aufgerundete Stunden Anspruch steuerfrei Differenz pflichtig\n11.11.2026 07.15 - 11.45 Uhr\n13.11.2026 07.00 - 19.45 Uhr\n18.11.2026 10.20 - 16.45 Uhr\nDurchgehende Dienstreise:\n26.11.2026 Beginn DR 07.10 Uhr bis\n27.11.2026 Ende DR 10.55 Uhr\nSumme\n\n• Herr D. legt eine Hotelrechnung in der Höhe von € 138,50 vor. Dieser Aufwand wird im Rahmen der Abrechnung ersetzt.\n• Weiters wird eine Bahnkarte gegen Vorlage eines Beleges in der Höhe von € 85,60 erstattet.\nIm KJ 2026 wurden bisher (inklusive Oktober) insgesamt € 289,94 steuerpflichtige Reisekosten ausbezahlt.\n\nDie Abrechnung der Reisekosten erfolgt gemäß KV bzw. EStG.\n\nSämtliche AUSZAHLUNGSBETRÄGE sind zu ermitteln. | D24: open_text | E24: calculation | F24: open_text | G24: 2368.67 | H24: null | I24: Akzeptiere EUR-Betrag mit 2 Dezimalstellen; Dezimaltrennzeichen „,“ oder „.“ zulässig. | J24: 1 | M24: C:\Users\dhoellmu\OneDrive - WU Wien\Dokumente\AccountingBench\backend\uploads\Wichtige_Werte_ab_7.1.2026-1.pdf | N24: austrian_tax_law | O24: 2026 | P24: tax | Q24: personalverrechnung | R24: Beispiel 4; laufende Abrechnung; Mehrleistungsstunden; Sachbezug PKW; Reisekosten; Auszahlungsbetrag | S24: professional_examinations | U24: batch_import | V24: batch_admin | W24: 1 | X24: 2026-04-29 14:03:43.001523 | Y24: Manuel Kaburek | Z24: approved
A25: 23 | B25: 12008933_0027 | C25: Herr C. ist seit 16.11.1999 als Angestellter im Unternehmen beschäftigt.\nLt. Dienstvertrag beträgt sein Bruttomonatsgehalt seit Jahresbeginn € 4.650,00.\nDem Betrieb wurde eine Erklärung gegenüber dem/der Arbeitgeber:in (Formular E 30) auf AV-/AEAB für seine 3 Kinder abgegeben. (Der Familienbonus Plus wird jeweils über die AN-Veranlagung beantragt.)\n\nMEHRLEISTUNGSSTUNDEN\nIm Abrechnungsmonat wurden tatsächlich\n• KV-Mehrarbeitsstunden: 3,0 Stunden (50 % ZS lt. KV / Teiler 167) (gem.§ 68 (2) EStG) sowie\n• Überstunden (ÜStd.): 2,0 Stunden (50 % ZS lt. KV / Teiler 143) (gem.§ 68 (2) EStG)\nDie Mehrstunden werden regelmäßig geleistet - folgende Arbeitszeitaufzeichnungen liegen vor:\nAbrechnungsmonat KV - MA-Stunden ÜStd. 50 % (§ 68 Abs. 2 EStG)\n08 / 2026 4,0 Stunden 11,00 Stunden\n09 / 2026 3,5 Stunden 9,00 Stunden\n10 / 2026 3,0 Stunden 10,00 Stunden\nDiese Mehrleistungsstunden wurden im jeweiligen Abrechnungsmonat gemäß KV entlohnt. Sie finden bei der Berechnung der Sonderzahlungen keine Berücksichtigung.\n\nDIENSTVERHINDERUNGEN\nAm 13.11.2026 teilt der Mitarbeiter dem Unternehmen VOR Dienstantritt mit, dass er aufgrund der Erkrankung seiner 5-jährigen Tochter bis inklusive 18.11.2026 nicht zur Arbeit kommen kann – eine entsprechende Bestätigung der notwendigen Pflegefreistellung wird bei Dienstantritt am 19.11.2026 dem Lohnbüro vorgelegt.\nBitte beachten Sie eventuelle Feiertage im Abrechnungsmonat sowie die allgemeine Angabe bzgl. ALLER Sonderzahlungen auf Seite 2!\n\nSämtliche AUSZAHLUNGSBETRÄGE sind zu ermitteln. | D25: open_text | E25: calculation | F25: open_text | G25: -276.98 | H25: null | I25: Akzeptiere EUR-Betrag mit Vorzeichen und 2 Dezimalstellen; Dezimaltrennzeichen „,“ oder „.“ zulässig. | J25: 1 | M25: C:\Users\dhoellmu\OneDrive - WU Wien\Dokumente\AccountingBench\backend\uploads\Wichtige_Werte_ab_7.1.2026-1.pdf | N25: austrian_tax_law | O25: 2026 | P25: tax | Q25: personalverrechnung | R25: Beispiel 3; laufende Abrechnung; Mehrleistungsstunden; §68 EStG; Pflegefreistellung; AV-/AEAB; Auszahlungsbetrag | S25: professional_examinations | U25: batch_import | V25: batch_admin | W25: 1 | X25: 2026-04-29 14:03:43.001523 | Y25: Manuel Kaburek | Z25: approved
A26: 24 | B26: 12008933_0023 | C26: Ferdinand F.\n\nDie offene UNTERHALTS-Forderung seiner Tochter aus erster Ehe beträgt zum Abrechnungstermin € 2.340,00. Laut Personalunterlagen besteht außerdem eine Unterhaltsverpflichtung für seine beiden minderjährigen Kinder, welche mit ihm und seiner Lebensgefährtin im gemeinsamen Haushalt leben.\n\nSämtliche AUSZAHLUNGSBETRÄGE sind zu ermitteln.\nDie Berechnung der LOHNPFÄNDUNG sowie der KOSTEN für die Berechnung der Pfändung im Abrechnungsmonat ist durchzuführen.\n\n(Abrechnung November 2026 lt. Angabe; Details zu Grundlohn/SZL/EZL gemäß Angabe.) | D26: open_text | E26: calculation | F26: open_text | G26: 1646.25 | H26: null | I26: Akzeptiere EUR-Betrag mit 2 Dezimalstellen; Dezimaltrennzeichen „,“ oder „.“ zulässig. | J26: 1 | M26: C:\Users\dhoellmu\OneDrive - WU Wien\Dokumente\AccountingBench\backend\uploads\Wichtige_Werte_ab_7.1.2026-1.pdf | N26: austrian_tax_law | O26: 2026 | P26: tax | Q26: personalverrechnung | R26: Beispiel 6; Lohnpfändung; Unterhaltsforderung; Pfändungsberechnung; Auszahlungsbetrag | S26: professional_examinations | U26: batch_import | V26: batch_admin | W26: 1 | X26: 2026-04-29 14:03:43.001523 | Y26: Manuel Kaburek | Z26: approved
A27: 25 | B27: 12008933_0026 | C27: Herr D. seit 01.01.1999 als Reisender im Unternehmen tätig.\nSein Bruttomonatsgehalt beträgt seit Jänner dieses Jahres € 6.000,00.\n\nSONDERZAHLUNGEN\nWie jedes Jahr erhielt der Mitarbeiter im Abrechnungsmonat Februar eine Jahresprovision i.d.H.v. € 8.000,00.\n(Diese Zahlung erfolgt regelmäßig, wiederkehrend, in größeren zeitlichen Abständen als der monatliche Beitragszeitraum.)\nBitte beachten Sie die allgemeine Angabe bzgl. ALLER Sonderzahlungen auf Seite 2!\n\nSämtliche AUSZAHLUNGSBETRÄGE sind zu ermitteln. | D27: open_text | E27: calculation | F27: open_text | G27: 5903.62 | H27: null | I27: Akzeptiere EUR-Betrag mit 2 Dezimalstellen; Dezimaltrennzeichen „,“ oder „.“ zulässig. | J27: 1 | M27: C:\Users\dhoellmu\OneDrive - WU Wien\Dokumente\AccountingBench\backend\uploads\Wichtige_Werte_ab_7.1.2026-1.pdf | N27: austrian_tax_law | O27: 2026 | P27: tax | Q27: personalverrechnung | R27: Beispiel 4; Sonderzahlungen; Jahresprovision; Jahressechstel; Auszahlungsbetrag | S27: professional_examinations | U27: batch_import | V27: batch_admin | W27: 1 | X27: 2026-04-29 14:03:43.001523 | Y27: Manuel Kaburek | Z27: approved
A28: 26 | B28: 12008933_0021 | C28: Herr G. ist als Arbeiter im Unternehmen tätig.\n\nSONDERZAHLUNG\nSonderzahlung (November 2026) gemäß Angabe.\nLt. Lösung: im J/6 keine Überschreitung.\n\nSämtliche AUSZAHLUNGSBETRÄGE sind zu ermitteln. | D28: open_text | E28: calculation | F28: open_text | G28: 2853.12 | H28: null | I28: Akzeptiere EUR-Betrag mit 2 Dezimalstellen; Dezimaltrennzeichen „,“ oder „.“ zulässig. | J28: 1 | M28: C:\Users\dhoellmu\OneDrive - WU Wien\Dokumente\AccountingBench\backend\uploads\Wichtige_Werte_ab_7.1.2026-1.pdf | N28: austrian_tax_law | O28: 2026 | P28: tax | Q28: personalverrechnung | R28: Beispiel 7; Sonderzahlung; Jahressechstel; Auszahlungsbetrag | S28: professional_examinations | U28: batch_import | V28: batch_admin | W28: 1 | X28: 2026-04-29 14:03:42.998558 | Y28: Manuel Kaburek | Z28: approved
A29: 27 | B29: 12008933_0030 | C29: Frau B. ist am 01.03.2008 als Bilanzbuchhalterin ins Unternehmen eingetreten.\nIhr Bruttomonatsgehalt beträgt seit Jänner dieses Jahres € 6.500,00.\nDem Personalbüro liegt eine Mitteilung zur Vorlage an den/die Arbeitgeber:in vor. Folglich ist ein monatlicher Freibetragsbescheid in der Höhe von € 65,00 zu berücksichtigen.\nWeiters ist bekannt, dass Frau B. nach ihrer HAK-Matura 6 Jahre in einem anderen Unternehmen beschäftigt war. Die entsprechenden Nachweise wurden der Lohnverrechnung beim Eintritt ausgehändigt.\n\nSONDERZAHLUNGEN / SONSTIGE BEZÜGE\nDie Dienstnehmerin erhielt wie jedes Jahr im März dieses Jahres ein BILANZGELD in der Höhe von einem Bruttomonatsgehalt. Es handelt sich dabei um eine regelmäßig wiederkehrende Sonderzahlung.\nBitte beachten Sie die allgemeine Angabe bzgl. ALLER Sonderzahlungen auf Seite 2!\n\nBEENDIGUNG\nDurch Zufall erfährt die Geschäftsleitung am 06.11.2026 am Ende des Arbeitstages, dass die Mitarbeiterin sich in ihrer Tätigkeit ohne Wissen oder Willen der DG-Seite von dritten Personen unberechtigte Vorteile zuwenden ließ. Der:die Dienstgeber:in spricht daraufhin unverzüglich die berechtigte Entlassung aus.\nDie Mitarbeiterin hat im aktuellen Urlaubsjahr (Arbeitsjahr) noch keinen Urlaub konsumiert. Lt. Aufzeichnungen besteht noch 4 AT Resturlaub aus vergangenen Perioden.\nAufgrund des vorliegenden Entlassungstatbestands ist mit keinem Wiedereintritt zu rechnen.\nEine allfällige Aliquotierung des Monatsgehalts bei Beendigung des Dienstverhältnisses ist anhand der tatsächlichen Kalendertage des jeweiligen Monats vorzunehmen. Für die Berechnung der Sonderzahlungen gilt ein Divisor von 365; der aliquote Anspruch ist entsprechend den tatsächlichen Kalendertagen zu ermitteln.\n\nAllfällige AUSZAHLUNGSBETRÄGE sind zu berechnen. | D29: open_text | E29: calculation | F29: open_text | G29: 2873.71 | H29: null | I29: Akzeptiere EUR-Betrag mit 2 Dezimalstellen; Dezimaltrennzeichen „,“ oder „.“ zulässig. | J29: 1 | M29: C:\Users\dhoellmu\OneDrive - WU Wien\Dokumente\AccountingBench\backend\uploads\Wichtige_Werte_ab_7.1.2026-1.pdf | N29: austrian_tax_law | O29: 2026 | P29: tax | Q29: personalverrechnung | R29: Beispiel 2; laufende Abrechnung; Entlassung; Urlaubsersatzleistung (lfd.); Freibetragsbescheid; Auszahlungsbetrag | S29: professional_examinations | U29: batch_import | V29: batch_admin | W29: 1 | X29: 2026-04-29 14:03:43.045822 | Y29: Manuel Kaburek | Z29: approved
A30: 28 | B30: 12008933_0029 | C30: Frau B. ist am 01.03.2008 als Bilanzbuchhalterin ins Unternehmen eingetreten.\nIhr Bruttomonatsgehalt beträgt seit Jänner dieses Jahres € 6.500,00.\n\nSONDERZAHLUNGEN\nDie Dienstnehmerin erhielt wie jedes Jahr im März dieses Jahres ein BILANZGELD in der Höhe von einem Bruttomonatsgehalt. Es handelt sich dabei um eine regelmäßig wiederkehrende Sonderzahlung.\nBitte beachten Sie die allgemeine Angabe bzgl. ALLER Sonderzahlungen auf Seite 2!\n\nBEENDIGUNG\nEine allfällige Aliquotierung des Monatsgehalts bei Beendigung des Dienstverhältnisses ist anhand der tatsächlichen Kalendertage des jeweiligen Monats vorzunehmen. Für die Berechnung der Sonderzahlungen gilt ein Divisor von 365; der aliquote Anspruch ist entsprechend den tatsächlichen Kalendertagen zu ermitteln.\n\nAUSZAHLUNGSBETRÄGE sind zu berechnen. | D30: open_text | E30: calculation | F30: open_text | G30: 5308.14 | H30: null | I30: Akzeptiere EUR-Betrag mit 2 Dezimalstellen; Dezimaltrennzeichen „,“ oder „.“ zulässig. | J30: 1 | M30: C:\Users\dhoellmu\OneDrive - WU Wien\Dokumente\AccountingBench\backend\uploads\Wichtige_Werte_ab_7.1.2026-1.pdf | N30: austrian_tax_law | O30: 2026 | P30: tax | Q30: personalverrechnung | R30: Beispiel 2; Sonderzahlungen aliquot; Jahressechstel; Entlassung; Auszahlungsbetrag | S30: professional_examinations | U30: batch_import | V30: batch_admin | W30: 1 | X30: 2026-04-29 14:03:43.008601 | Y30: Manuel Kaburek | Z30: approved
A31: 29 | B31: 12008933_0028 | C31: Herr C. ist seit 16.11.1999 als Angestellter im Unternehmen beschäftigt.\nLt. Dienstvertrag beträgt sein Bruttomonatsgehalt seit Jahresbeginn € 4.650,00.\nDem Betrieb wurde eine Erklärung gegenüber dem/der Arbeitgeber:in (Formular E 30) auf AV-/AEAB für seine 3 Kinder abgegeben. (Der Familienbonus Plus wird jeweils über die AN-Veranlagung beantragt.)\nLt. Lohnkonto wurden von 01/2026 bis inkl. 10/2026 insges. € 52.449,54 laufende Bruttobezüge verrechnet.\n\nSONDERZAHLUNGEN\n• Im September 2026 erfolgte die Auszahlung einer 1x-Prämie i.d.H.v. € 3.000,00. (Der Anspruch war absolut einmalig - es ist mit keiner Wiederkehr zu rechnen.)\n• Lt. Vereinbarung gebührt ein Jubiläumsgeld im Ausmaß des 1,5-fachen des Bruttomonatsgehaltes. (Diese Zahlung erfolgt regelmäßig, wiederkehrend, in größeren zeitlichen Abständen als der monatliche Beitragszeitraum.)\nBitte beachten Sie die allgemeine Angabe bzgl. ALLER Sonderzahlungen auf Seite 2!\n\nSämtliche AUSZAHLUNGSBETRÄGE sind zu ermitteln. | D31: open_text | E31: calculation | F31: open_text | G31: 9907.94 | H31: null | I31: Akzeptiere EUR-Betrag mit 2 Dezimalstellen; Dezimaltrennzeichen „,“ oder „.“ zulässig. | J31: 1 | M31: C:\Users\dhoellmu\OneDrive - WU Wien\Dokumente\AccountingBench\backend\uploads\Wichtige_Werte_ab_7.1.2026-1.pdf | N31: austrian_tax_law | O31: 2026 | P31: tax | Q31: personalverrechnung | R31: Beispiel 3; Sonderzahlungen; Jubiläumsgeld; 1x-Prämie; Jahressechstel; Auszahlungsbetrag | S31: professional_examinations | U31: batch_import | V31: batch_admin | W31: 1 | X31: 2026-04-29 14:03:43.001523 | Y31: Manuel Kaburek | Z31: approved
A32: 30 | B32: 12008933_0031 | C32: Herr A. ist seit 01.08.2002 als Handelsrechtlicher Geschäftsführer (GF) mit 15 % am Unternehmen beteiligt.\nEs liegt keine Sperrminorität vor.\nWeiters ist bekannt, dass der Mitarbeiter im Abrechnungsmonat seinen 64. Geburtstag feiert und im 1. Quartal des nachfolgenden Kalenderjahres die Anspruchsvoraussetzungen für eine Eigenpension erfüllen wird.\nSein Bruttomonatsgehalt beträgt seit Jänner dieses Jahres € 8.500,00.\n\nSACHBEZÜGE\na) Dem DN wird seit Beginn des Vertragsverhältnisses ein Firmen-PKW zur vollen Privatnutzung überlassen. Der aktuelle PKW wurde am 01.02. des Vorjahres um € 66.280,00 vom Unternehmen erworben. Das Elektrofahrzeug wird seitdem von Herrn A. genutzt. Laut Vereinbarung leistet der Angestellte für diese Nutzung monatlich einen Kostenbeitrag in der Höhe von € 200,00, welcher im Rahmen der Abrechnung einbehalten wird.\nb) Der Mitarbeiter nutzt seit Beginn des Vertragsverhältnisses einen Tiefgaragenparkplatz innerhalb der gebührenpflichtigen Zone. Die Abstellfläche ist angemietet. Die Miete in der Höhe von € 135,00 wird monatlich von der Buchhaltung an den Vermieter überwiesen.\n\nSämtliche AUSZAHLUNGSBETRÄGE sind zu ermitteln. | D32: open_text | E32: calculation | F32: open_text | G32: 2593.45 | H32: null | I32: Akzeptiere EUR-Betrag mit 2 Dezimalstellen; Dezimaltrennzeichen „,“ oder „.“ zulässig. | J32: 1 | M32: C:\Users\dhoellmu\OneDrive - WU Wien\Dokumente\AccountingBench\backend\uploads\Wichtige_Werte_ab_7.1.2026-1.pdf | N32: austrian_tax_law | O32: 2026 | P32: tax | Q32: personalverrechnung | R32: Beispiel 1; GF; Sachbezüge; Firmen-PKW; Elektrofahrzeug; Tiefgaragenparkplatz; Auszahlungsbetrag | S32: professional_examinations | U32: batch_import | V32: batch_admin | W32: 1 | X32: 2026-04-29 14:33:08.793394 | Y32: Manuel Kaburek | Z32: approved
A33: 31 | B33: 12008933_0032 | C33: Herr A. ist seit 01.08.2002 als Handelsrechtlicher Geschäftsführer (GF) mit 15 % am Unternehmen beteiligt.\nEs liegt keine Sperrminorität vor.\nWeiters ist bekannt, dass der Mitarbeiter im Abrechnungsmonat seinen 64. Geburtstag feiert und im 1. Quartal des nachfolgenden Kalenderjahres die Anspruchsvoraussetzungen für eine Eigenpension erfüllen wird.\nSein Bruttomonatsgehalt beträgt seit Jänner dieses Jahres € 8.500,00.\n\nSONDERZAHLUNGEN / SONSTIGE BEZÜGE\nIm Abrechnungsmonat gebührt dem GF eine Prämie in der Höhe von Brutto € 5.000,00.\nDie Zahlung erfolgt jährlich wiederkehrend, Regelmäßigkeit ist gegeben.\nBitte beachten Sie die allgemeine Angabe bzgl. ALLER Sonderzahlungen auf Seite 2!\n\nSämtliche AUSZAHLUNGSBETRÄGE sind zu ermitteln. | D33: open_text | E33: calculation | F33: open_text | G33: 12260.11 | H33: null | I33: Akzeptiere EUR-Betrag mit 2 Dezimalstellen; Dezimaltrennzeichen „,“ oder „.“ zulässig. | J33: 1 | M33: C:\Users\dhoellmu\OneDrive - WU Wien\Dokumente\AccountingBench\backend\uploads\Wichtige_Werte_ab_7.1.2026-1.pdf | N33: austrian_tax_law | O33: 2026 | P33: tax | Q33: personalverrechnung | R33: Beispiel 1; GF; 15 % Beteiligung; Sonderzahlungen; Prämie; Auszahlungsbetrag | S33: professional_examinations | U33: batch_import | V33: batch_admin | W33: 1 | X33: 2026-04-29 14:33:08.793394 | Y33: Manuel Kaburek | Z33: approved
A34: 32 | B34: 12008933_0033 | C34: Berechnen Sie für den Lehrling (LAP am 22.11.2026, Wechsel zum Arbeiter ab 23.11.2026) die Sonderzahlungen (UG/WR aliquot Lehrling und aliquot Arbeiter) sowie die LAP-Prämie EUR 200,00 in der Novemberabrechnung 2026 und geben Sie den Netto-/Auszahlungsbetrag an. Gegeben: Lehrlingseinkommen EUR 1.750,00 bis 22.11.2026; ab 23.11.2026 Arbeiterlohn EUR 2.800,00; Aliquotierung nach Kalendertagen (365); LAP-Prämie am Monatsende ausbezahlt; SV-Pflicht beachten. | D34: open_text | E34: calculation | F34: open_text | G34: 1772.56 | H34: null | I34: Akzeptiere EUR-Betrag mit 2 Dezimalstellen; Dezimaltrennzeichen „,“ oder „.“ zulässig. | J34: 1 | L34: Betrieb: FIT-GmbH, Abrechnung November 2026; Jahressechstel, SV-Sätze Lehrling/Arbeiter und BV berücksichtigen. | M34: C:\Users\dhoellmu\OneDrive - WU Wien\Dokumente\AccountingBench\backend\uploads\Wichtige_Werte_ab_7.1.2026-1.pdf | N34: austrian_tax_law | O34: 2026 | P34: tax | Q34: personalverrechnung | R34: Lehrling; LAP-Prämie; Beschäftigungswechsel; Sonderzahlungen aliquot; SV/LSt | S34: professional_examinations | U34: batch_import | V34: batch_admin | W34: 1 | X34: 2026-04-29 14:33:08.793394 | Y34: Manuel Kaburek | Z34: approved
A35: 33 | B35: 12008933_0034 | C35: Berechnen Sie für Demian D. die laufende Novemberabrechnung 2026 und geben Sie den Netto-/Auszahlungsbetrag an. Gegeben: Bruttomonatsgehalt EUR 6.000,00; pauschale Überstunden 15 Std. (50 % Zuschlag, Teiler 143) und KV-Mehrarbeitsstunden 6,5 Std. (50 % Zuschlag, Teiler 167); Firmen-PKW (Anschaffung 01.09.2023 um EUR 51.860,00, 140 g/km, Privatnutzung < 6.000 km/Jahr, Fahrtenbuch vorhanden); Reisekosten gem. KV (Details lt. Angabe), davon steuerfrei und steuerpflichtig zu unterscheiden; bisher 2026 bereits EUR 289,94 steuerpflichtige RK. | D35: open_text | E35: calculation | F35: open_text | G35: 2368.67 | H35: null | I35: Akzeptiere EUR-Betrag mit 2 Dezimalstellen; Dezimaltrennzeichen „,“ oder „.“ zulässig. | J35: 1 | L35: Betrieb: FIT-GmbH, Abrechnung November 2026; Sachbezug PKW, §68 EStG und SV/LSt berücksichtigen. | M35: C:\Users\dhoellmu\OneDrive - WU Wien\Dokumente\AccountingBench\backend\uploads\Wichtige_Werte_ab_7.1.2026-1.pdf | N35: austrian_tax_law | O35: 2026 | P35: tax | Q35: personalverrechnung | R35: Reisekosten; Sachbezug PKW; Überstundenpauschale; §68 EStG; laufende Abrechnung | S35: professional_examinations | U35: batch_import | V35: batch_admin | W35: 1 | X35: 2026-04-29 14:33:08.793394 | Y35: Manuel Kaburek | Z35: approved
A36: 34 | B36: 12008933_0035 | C36: Berechnen Sie für Demian D. (Eintritt 01.01.1999) die Sonderzahlung (Weihnachtsremuneration) in der Novemberabrechnung 2026 und geben Sie den Netto-/Auszahlungsbetrag an. Gegeben: Bruttomonatsgehalt EUR 6.000,00; Jahresprovision EUR 8.000,00 (regelmäßig wiederkehrend, Auszahlung im Februar); Urlaubsgeld EUR 6.000,00 bereits ausbezahlt; WR im November; laufende Bezüge inkl. RK-pflichtig bis 10/2026 zu berücksichtigen; Mehrleistungsstunden nicht in SZ einzubeziehen. | D36: open_text | E36: calculation | F36: open_text | G36: 5903.62 | H36: null | I36: Akzeptiere EUR-Betrag mit 2 Dezimalstellen; Dezimaltrennzeichen „,“ oder „.“ zulässig. | J36: 1 | L36: Betrieb: FIT-GmbH, Abrechnung November 2026; Jahressechstel und HBGL SZ beachten. | M36: C:\Users\dhoellmu\OneDrive - WU Wien\Dokumente\AccountingBench\backend\uploads\Wichtige_Werte_ab_7.1.2026-1.pdf | N36: austrian_tax_law | O36: 2026 | P36: tax | Q36: personalverrechnung | R36: Sonderzahlungen; Jahresprovision; Jahressechstel; HBGL; SV/LSt | S36: professional_examinations | U36: batch_import | V36: batch_admin | W36: 1 | X36: 2026-04-29 14:33:08.809508 | Y36: Manuel Kaburek | Z36: approved
A37: 35 | B37: 12008933_0036 | C37: Berechnen Sie für Klaus C. die laufende Novemberabrechnung 2026 und geben Sie den Netto-/Auszahlungsbetrag an. Gegeben: Bruttomonatsgehalt EUR 4.650,00; 3 KV-Mehrarbeitsstunden (50 % Zuschlag, Teiler 167) und 2 Überstunden (50 % Zuschlag, Teiler 143) im November; Mehrleistungsstunden regelmäßig geleistet; Pflegefreistellung 13.11.–18.11.2026 (Bestätigung vorgelegt); AV-/AEAB für 3 Kinder (Formular E30); Familienbonus Plus über AN-Veranlagung; Mehrleistungsstunden nicht in SZ einzubeziehen. | D37: open_text | E37: calculation | F37: open_text | G37: -276.98 | H37: null | I37: Akzeptiere EUR-Betrag mit Vorzeichen und 2 Dezimalstellen; Dezimaltrennzeichen „,“ oder „.“ zulässig. | J37: 1 | L37: Betrieb: FIT-GmbH, Abrechnung November 2026; Feiertage und § 68 Abs. 2 EStG berücksichtigen. | M37: C:\Users\dhoellmu\OneDrive - WU Wien\Dokumente\AccountingBench\backend\uploads\Wichtige_Werte_ab_7.1.2026-1.pdf | N37: austrian_tax_law | O37: 2026 | P37: tax | Q37: personalverrechnung | R37: Mehrleistungsstunden; Pflegefreistellung; §68 EStG; AVAB/AEAB; laufende Abrechnung | S37: professional_examinations | U37: batch_import | V37: batch_admin | W37: 1 | X37: 2026-04-29 14:48:17.255640 | Y37: Manuel Kaburek | Z37: approved
A38: 36 | B38: 12008933_0037 | C38: Berechnen Sie für Klaus C. (Eintritt 16.11.1999) die Sonderzahlungen in der Novemberabrechnung 2026 und geben Sie den Netto-/Auszahlungsbetrag an. Gegeben: Bruttomonatsgehalt EUR 4.650,00; Jubiläumsgeld im Ausmaß des 1,5-fachen Monatsgehalts (regelmäßig wiederkehrend in größeren Abständen); im September 2026 einmalige Prämie EUR 3.000,00 (nicht wiederkehrend); laufende Bruttobezüge 01–10/2026 gesamt EUR 52.449,54; WR im November; Mehrleistungsstunden sind bei SZ nicht einzubeziehen. | D38: open_text | E38: calculation | F38: open_text | G38: 9907.94 | H38: null | I38: Akzeptiere EUR-Betrag mit 2 Dezimalstellen; Dezimaltrennzeichen „,“ oder „.“ zulässig. | J38: 1 | L38: Betrieb: FIT-GmbH, Abrechnung November 2026; Jahressechstel zu berücksichtigen; HBGL SZ beachten. | M38: C:\Users\dhoellmu\OneDrive - WU Wien\Dokumente\AccountingBench\backend\uploads\Wichtige_Werte_ab_7.1.2026-1.pdf | N38: austrian_tax_law | O38: 2026 | P38: tax | Q38: personalverrechnung | R38: Sonderzahlungen; Jubiläumsgeld; Jahressechstel; einmalige Prämie; SV/LSt | S38: professional_examinations | U38: batch_import | V38: batch_admin | W38: 1 | X38: 2026-04-29 14:52:17.870748 | Y38: Manuel Kaburek | Z38: approved
A39: 37 | B39: 12008933_0038 | C39: Berechnen Sie für Berta B. die aliquoten Sonderzahlungen (WR und Bilanzgeld) im Rahmen der Beendigung per 06.11.2026 sowie die darauf entfallende Abrechnung und geben Sie den Netto-/Auszahlungsbetrag der Sonderzahlung an. Gegeben: SZ aliquot vom 01.01.2026 bis 06.11.2026 (310 Kalendertage); bereits ausbezahlt: Urlaubsgeld EUR 6.500,00 und Bilanzgeld EUR 6.500,00. | D39: open_text | E39: calculation | F39: open_text | G39: 5308.14 | H39: null | I39: Akzeptiere EUR-Betrag mit 2 Dezimalstellen; Dezimaltrennzeichen „,“ oder „.“ zulässig. | J39: 1 | L39: Betrieb: FIT-GmbH, Abrechnung November 2026; Divisor 365; Jahressechstel zu berücksichtigen. | M39: C:\Users\dhoellmu\OneDrive - WU Wien\Dokumente\AccountingBench\backend\uploads\Wichtige_Werte_ab_7.1.2026-1.pdf | N39: austrian_tax_law | O39: 2026 | P39: tax | Q39: personalverrechnung | R39: Sonderzahlungen aliquot; Jahressechstel; Beendigung; SV/LSt | S39: professional_examinations | U39: batch_import | V39: batch_admin | W39: 1 | X39: 2026-04-29 14:53:00.746664 | Y39: Manuel Kaburek | Z39: approved
A40: 38 | B40: 12008933_0039 | C40: Berechnen Sie für Berta B. (Eintritt 01.03.2008, berechtigte Entlassung am 06.11.2026) die laufende Novemberabrechnung 2026 inklusive Urlaubsersatzleistung (lfd. Bezug) und geben Sie den Netto-/Auszahlungsbetrag für November an. Gegeben: Bruttomonatsgehalt EUR 6.500,00; Freibetragsbescheid EUR 65,00 mtl.; 4 AT Resturlaub aus Vorjahren; im laufenden Arbeitsjahr noch kein Urlaub konsumiert; Aliquotierung bei Beendigung nach tatsächlichen Kalendertagen; Divisor SZ = 365. | D40: open_text | E40: calculation | F40: open_text | G40: 2873.71 | H40: null | I40: Akzeptiere EUR-Betrag mit 2 Dezimalstellen; Dezimaltrennzeichen „,“ oder „.“ zulässig. | J40: 1 | L40: Betrieb: FIT-GmbH, Abrechnung November 2026; Entlassung am 06.11.2026; Verlängerung Entgeltanspruch bis 08.12.2026. | M40: C:\Users\dhoellmu\OneDrive - WU Wien\Dokumente\AccountingBench\backend\uploads\Wichtige_Werte_ab_7.1.2026-1.pdf | N40: austrian_tax_law | O40: 2026 | P40: tax | Q40: personalverrechnung | R40: Beendigung; Entlassung; Urlaubsersatzleistung laufend; Freibetragsbescheid; SV/LSt | S40: professional_examinations | U40: batch_import | V40: batch_admin | W40: 1 | X40: 2026-04-29 14:54:00.198754 | Y40: Manuel Kaburek | Z40: approved
A41: 39 | B41: 12008933_0040 | C41: Berechnen Sie für Anton A. (handelsrechtlicher Geschäftsführer, 15% Beteiligung, keine Sperrminorität) die laufende Novemberabrechnung 2026 und geben Sie den Netto-/Auszahlungsbetrag an. Gegeben: Bruttomonatsgehalt EUR 8.500,00. Sachbezüge: (a) Firmen-PKW (Elektrofahrzeug, CO2=0) zur vollen Privatnutzung; Anschaffung durch DG am 01.02. des Vorjahres um EUR 66.280,00; monatlicher Kostenbeitrag DN EUR 200,00 (vom Netto einzubehalten). (b) Tiefgaragenparkplatz in gebührenpflichtiger Zone; DG zahlt monatliche Miete EUR 135,00. | D41: open_text | E41: calculation | F41: open_text | G41: 2593.45 | H41: null | I41: Akzeptiere EUR-Betrag mit 2 Dezimalstellen; Dezimaltrennzeichen „,“ oder „.“ zulässig. | J41: 1 | L41: Betrieb: FIT-GmbH, Abrechnung November 2026. Sachbezüge und 20%-Regel entsprechend darzustellen bzw. zu begründen. | M41: C:\Users\dhoellmu\OneDrive - WU Wien\Dokumente\AccountingBench\backend\uploads\Wichtige_Werte_ab_7.1.2026-1.pdf | N41: austrian_tax_law | O41: 2026 | P41: tax | Q41: personalverrechnung | R41: Sachbezug (E-Auto, Parkplatz); Kostenbeitrag DN; laufende Abrechnung; SV/LSt-Berechnung | S41: professional_examinations | U41: batch_import | V41: batch_admin | W41: 1 | X41: 2026-04-29 14:55:12.107097 | Y41: Manuel Kaburek | Z41: approved
A42: 40 | B42: 12008933_0041 | C42: Berechnen Sie für Anton A. (handelsrechtlicher Geschäftsführer, 15% Beteiligung, keine Sperrminorität) die Sonderzahlungen in der Novemberabrechnung 2026 und geben Sie den Netto-/Auszahlungsbetrag an. Gegeben: Bruttomonatsgehalt EUR 8.500,00. Im November gebühren (i) Weihnachtsremuneration iHv 1 Bruttomonatsgehalt (ohne Einbeziehung schwankender Prämien/Mehrleistungsstunden) und (ii) eine jährlich wiederkehrende Prämie iHv EUR 5.000,00 (Regelmäßigkeit gegeben). Auszahlung per 30.11.2026. | D42: open_text | E42: calculation | F42: open_text | G42: 12260.11 | H42: null | I42: Akzeptiere EUR-Betrag mit 2 Dezimalstellen; Dezimaltrennzeichen „,“ oder „.“ zulässig. | J42: 1 | L42: Betrieb: FIT-GmbH, Abrechnung November 2026, NAZ 38,5h/Woche. Sonderzahlungen: UZ wurde bereits im Mai abgerechnet; WR im November. | M42: C:\Users\dhoellmu\OneDrive - WU Wien\Dokumente\AccountingBench\backend\uploads\Wichtige_Werte_ab_7.1.2026-1.pdf | N42: austrian_tax_law | O42: 2026 | P42: tax | Q42: personalverrechnung | R42: Sonderzahlungen; Weihnachtsremuneration; Prämie (wiederkehrend); Jahressechstel; SV/LSt-Berechnung | S42: professional_examinations | U42: batch_import | V42: batch_admin | W42: 1 | X42: 2026-04-29 15:02:02.852467 | Y42: Manuel Kaburek | Z42: approved
A43: 41 | B43: 12008933_0042 | C43: Welche Aussage(n) zur steuerlichen Gewinnerzielungsabsicht und Liebhaberei ist/sind richtig? (vereinfacht) | D43: multi_choice | E43: interpretation_of_law | F43: multi_choice | G43: A,C,D | H43: {"a": "Liebhaberei liegt vor, wenn eine T\u00e4tigkeit typischerweise auf Dauer keinen Gesamtgewinn erwarten l\u00e4sst.", "b": "Bei Liebhaberei sind Verluste steuerlich abzugsf\u00e4hig.", "c": "Gewinnerzielungsabsicht ist Voraussetzung f\u00fcr die Einkunftsquelleneigenschaft.", "d": "Die Beurteilung der Liebhaberei kann Einfluss auf die Anerkennung von Betriebsausgaben haben.", "e": "Liebhaberei kommt nur bei Kapitalgesellschaften vor."} | I43: Exact set match required (A, C and D). Order irrelevant. Case-insensitive. No additional choices allowed. | N43: austrian_tax_law | O43: 2025 | P43: tax | Q43: general_principles | R43: austrian tax law; tax determination; general principles | S43: master | U43: batch_import | V43: batch_admin | W43: 1 | X43: 2026-04-29 15:05:42.787800 | Y43: Manuel Kaburek | Z43: approved
A44: 42 | B44: 12008933_0043 | C44: Welche Aussage(n) zur kurzfristigen Erfolgsrechnung bei Teilkostenrechnung ist/sind korrekt? | D44: multi_choice | E44: interpretation_of_law | F44: multi_choice | G44: A,B,C,E | H44: {"a": "Die Erfolgsrechnung kann nach Deckungsbeitr\u00e4gen gestaffelt sein.", "b": "Fixkosten werden separat vom Deckungsbeitrag ausgewiesen.", "c": "Kurzfristige Ergebnisse k\u00f6nnen f\u00fcr Produktentscheidungen genutzt werden.", "d": "Die Teilkosten-Erfolgsrechnung ist f\u00fcr Bestandsbewertung im UGB-Abschluss verbindlich.", "e": "Mehrstufige Deckungsbeitragsrechnungen erm\u00f6glichen Bereichsergebnisanalysen."} | I44: Exact set match required (A, B, C and E). Order irrelevant. Case-insensitive. No additional choices allowed. | N44: mixed_accounting_framework | O44: 2025 | P44: management_accounting | Q44: performance_measurement | R44: management accounting; decision support; performance measurement | S44: master | U44: batch_import | V44: batch_admin | W44: 1 | X44: 2026-04-29 15:06:16.521798 | Y44: Manuel Kaburek | Z44: approved
A45: 43 | B45: 12008933_0044 | C45: Welche Aussage(n) zur Vereinbarkeit von UGB- und IFRS-Abschluss ist/sind richtig? | D45: multi_choice | E45: interpretation_of_law | F45: multi_choice | G45: A,B,C,D | H45: {"a": "UGB-Abschl\u00fcsse sind stark gl\u00e4ubigerschutzorientiert, IFRS st\u00e4rker informationsorientiert.", "b": "IFRS-Abschl\u00fcsse k\u00f6nnen zus\u00e4tzlich zum UGB-Abschluss erstellt werden.", "c": "IFRS-Abschl\u00fcsse ersetzen in \u00d6sterreich grunds\u00e4tzlich nicht den UGB-Einzelabschluss f\u00fcr Aussch\u00fcttungszwecke.", "d": "\u00dcberg\u00e4nge zwischen UGB und IFRS erfordern \u00dcberleitungsrechnungen und Anhangangaben.", "e": "IFRS folgen in vollem Umfang dem Ma\u00dfgeblichkeitsprinzip des Steuerrechts."} | I45: Exact set match required (A, B, C and D). Order irrelevant. Case-insensitive. No additional choices allowed. | N45: mixed_accounting_framework | O45: 2025 | P45: financial_accounting | Q45: ugb_vs_ifrs | R45: financial accounting; ugb vs ifrs; UGB; IFRS | S45: master | U45: batch_import | V45: batch_admin | W45: 1 | X45: 2026-04-29 15:06:43.923857 | Y45: Manuel Kaburek | Z45: approved
A46: 44 | B46: 12008933_0045 | C46: Welche Aussage(n) zur kalkulatorischen Restwertbehandlung bei Abschreibungen in der Kostenrechnung ist/sind korrekt? | D46: multi_choice | E46: interpretation_of_law | F46: multi_choice | G46: A,B,D,E | H46: {"a": "Ein kalkulatorischer Restwert reduziert die Abschreibungsbasis.", "b": "Der Restwert kann dem Recycling- oder Verwertungserl\u00f6s entsprechen.", "c": "In der Finanzbuchhaltung ist der kalkulatorische Restwert zwingend zu ber\u00fccksichtigen.", "d": "Ohne Restwertannahme fallen h\u00f6here j\u00e4hrliche Abschreibungen an.", "e": "Restwertannahmen beeinflussen die Kosten pro Periode."} | I46: Exact set match required (A, B, D and E). Order irrelevant. Case-insensitive. No additional choices allowed. | N46: mixed_accounting_framework | O46: 2025 | P46: management_accounting | Q46: cost_accounting | R46: management accounting; decision support; cost accounting | S46: master | U46: batch_import | V46: batch_admin | W46: 1 | X46: 2026-04-29 15:06:51.288790 | Y46: Manuel Kaburek | Z46: approved
A47: 45 | B47: 12008933_0046 | C47: Welche Aussage(n) zum Einfluss von Leasing nach IFRS 16 auf Kennzahlen ist/sind richtig? | D47: multi_choice | E47: interpretation_of_law | F47: multi_choice | G47: A,B,C,D | H47: {"a": "Die Aktivierung von Nutzungsrechten erh\u00f6ht die Bilanzsumme.", "b": "Leasingverbindlichkeiten erh\u00f6hen die Verschuldungskennzahlen.", "c": "Der operative Cashflow steigt tendenziell, da Leasingzahlungen teilweise in den Finanzierungsbereich wandern.", "d": "EBITDA steigt, da Abschreibungen und Zinsen statt Leasingaufwand anfallen.", "e": "Die Eigenkapitalquote verbessert sich automatisch."} | I47: Exact set match required (A, B, C and D). Order irrelevant. Case-insensitive. No additional choices allowed. | N47: IFRS | O47: 2025 | P47: financial_accounting | Q47: ifrs_16 | R47: financial accounting; ifrs 16; IFRS; leasing | S47: master | U47: batch_import | V47: batch_admin | W47: 1 | X47: 2026-04-29 15:07:21.358758 | Y47: Manuel Kaburek | Z47: approved
A48: 46 | B48: 12008933_0047 | C48: Welche Aussage(n) zu IFRS 7 Finanzinstrumente: Angaben ist/sind korrekt? | D48: multi_choice | E48: interpretation_of_law | F48: multi_choice | G48: A,B,C,E | H48: {"a": "IFRS 7 verlangt umfangreiche Angaben zu Risiken aus Finanzinstrumenten.", "b": "Es sind qualitative und quantitative Informationen bereitzustellen.", "c": "Angaben zu Kredit-, Liquidit\u00e4ts- und Marktrisiken sind typisch.", "d": "IFRS 7 regelt die Bilanzierung von Finanzinstrumenten.", "e": "Ziel der Vorschriften ist die Erh\u00f6hung der Transparenz f\u00fcr Abschlussadressaten."} | I48: Exact set match required (A, B, C and E). Order irrelevant. Case-insensitive. No additional choices allowed. | N48: IFRS | O48: 2025 | P48: financial_accounting | Q48: ifrs_disclosures | R48: financial accounting; ifrs disclosures; IFRS | S48: master | U48: batch_import | V48: batch_admin | W48: 1 | X48: 2026-04-29 15:07:52.817517 | Y48: Manuel Kaburek | Z48: approved
A49: 47 | B49: 12008933_0048 | C49: Welche Aussage(n) zu Opportunitätskosten in der Entscheidungstheorie ist/sind richtig? | D49: multi_choice | E49: interpretation_of_law | F49: multi_choice | G49: A,B,D | H49: {"a": "Opportunit\u00e4tskosten sind entgangene Beitr\u00e4ge der besten nicht gew\u00e4hlten Alternative.", "b": "Sie f\u00fchren nicht zu Zahlungen, sind aber entscheidungsrelevant.", "c": "Sie werden in der Finanzbuchhaltung als Aufwand erfasst.", "d": "In der Kostenrechnung k\u00f6nnen Opportunit\u00e4tskosten als kalkulatorische Kosten ber\u00fccksichtigt werden.", "e": "Opportunit\u00e4tskosten sind nur im Finanzbereich von Bedeutung."} | I49: Exact set match required (A, B and D). Order irrelevant. Case-insensitive. No additional choices allowed. | N49: mixed_accounting_framework | O49: 2025 | P49: management_accounting | Q49: decision_theory | R49: management accounting; decision support; decision theory | S49: master | U49: batch_import | V49: batch_admin | W49: 1 | X49: 2026-04-29 15:07:56.169301 | Y49: Manuel Kaburek | Z49: approved
A50: 48 | B50: 12008933_0049 | C50: Welche Aussage(n) zur Bilanzierung von Eventualverbindlichkeiten nach IFRS (IAS 37) ist/sind korrekt? | D50: multi_choice | E50: interpretation_of_law | F50: multi_choice | G50: B,C,D | H50: {"a": "Eventualverbindlichkeiten werden in der Bilanz als R\u00fcckstellungen ausgewiesen.", "b": "Eventualverbindlichkeiten sind nur im Anhang anzugeben, sofern sie wesentlich sind.", "c": "Sie liegen vor, wenn eine m\u00f6gliche Verpflichtung besteht, deren Eintritt vom Eintreten unsicherer Ereignisse abh\u00e4ngt.", "d": "Eine passivierungspflichtige R\u00fcckstellung liegt vor, wenn die Verpflichtung wahrscheinlich ist und verl\u00e4sslich gesch\u00e4tzt werden kann.", "e": "Eventualverbindlichkeiten sind erfolgswirksam in der GuV zu erfassen."} | I50: Exact set match required (B, C and D). Order irrelevant. Case-insensitive. No additional choices allowed. | N50: IFRS | O50: 2025 | P50: financial_accounting | Q50: ifrs_provisions | R50: financial accounting; ifrs provisions; IFRS; provisions | S50: master | U50: batch_import | V50: batch_admin | W50: 1 | X50: 2026-04-29 15:08:12.785123 | Y50: Manuel Kaburek | Z50: approved
A51: 49 | B51: 12008933_0050 | C51: Welche Aussage(n) zur Break-even-Analyse bei mehreren Produkten ist/sind richtig? | D51: multi_choice | E51: interpretation_of_law | F51: multi_choice | G51: A,B,C,E | H51: {"a": "Der Gesamt-Break-even h\u00e4ngt von der Produktmix-Annahme ab.", "b": "Deckungsbeitr\u00e4ge je Produkt sind f\u00fcr die Analyse relevant.", "c": "Bei konstantem Produktmix kann ein gemeinsamer Break-even-Umsatz ermittelt werden.", "d": "Produkte mit negativem Deckungsbeitrag sollten langfristig im Programm bleiben.", "e": "Eine Ver\u00e4nderung des Produktmixes beeinflusst den Break-even-Punkt."} | I51: Exact set match required (A, B, C and E). Order irrelevant. Case-insensitive. No additional choices allowed. | N51: mixed_accounting_framework | O51: 2025 | P51: management_accounting | Q51: cvp_analysis | R51: management accounting; decision support; cvp analysis | S51: master | U51: batch_import | V51: batch_admin | W51: 1 | X51: 2026-04-29 15:08:52.402667 | Y51: Manuel Kaburek | Z51: approved
A52: 50 | B52: 12008933_0051 | C52: Welche Aussage(n) zum Verhältnis zwischen IFRS und Steuerbilanz in Österreich ist/sind korrekt? | D52: multi_choice | E52: interpretation_of_law | F52: multi_choice | G52: A,B,C,E | H52: {"a": "IFRS-Abschl\u00fcsse sind grunds\u00e4tzlich nicht unmittelbar steuerlich ma\u00dfgeblich.", "b": "F\u00fcr die Steuerbilanz wird regelm\u00e4\u00dfig eine eigene \u00dcberleitung von IFRS auf Steuerwerte ben\u00f6tigt.", "c": "Latente Steuern werden aus IFRS-Perspektive, nicht aus steuerlicher Sicht gebildet.", "d": "IFRS-Abschl\u00fcsse ersetzen den UGB-Abschluss f\u00fcr steuerliche Zwecke vollst\u00e4ndig.", "e": "Ma\u00dfgeblichkeit besteht in \u00d6sterreich nur im Verh\u00e4ltnis UGB-Steuerbilanz, nicht IFRS-Steuerbilanz."} | I52: Exact set match required (A, B, C and E). Order irrelevant. Case-insensitive. No additional choices allowed. | N52: mixed_accounting_tax | O52: 2025 | P52: financial_accounting | Q52: ifrs_vs_tax | R52: financial accounting; ifrs vs tax; IFRS; UGB; deferred taxes | S52: master | U52: batch_import | V52: batch_admin | W52: 1 | X52: 2026-04-29 15:09:20.362913 | Y52: Manuel Kaburek | Z52: approved
A53: 51 | B53: 12008933_0052 | C53: Welche Aussage(n) zu kalkulatorischen Zinsen in der Kostenrechnung ist/sind richtig? | D53: multi_choice | E53: interpretation_of_law | F53: multi_choice | G53: A,B,D,E | H53: {"a": "Sie erfassen die Verzinsung des im Unternehmen gebundenen Kapitals.", "b": "Sie k\u00f6nnen auf Basis von Gesamtkapital oder Eigenkapital berechnet werden.", "c": "Sie sind in der Finanzbuchhaltung als Zinsaufwand erfasst.", "d": "Sie geh\u00f6ren zu den Anders- oder Zusatzkosten.", "e": "Sie dienen der verursachungsgerechten Verrechnung von Kapitalkosten auf Kostentr\u00e4ger."} | I53: Exact set match required (A, B, D and E). Order irrelevant. Case-insensitive. No additional choices allowed. | N53: mixed_accounting_framework | O53: 2025 | P53: management_accounting | Q53: cost_accounting | R53: management accounting; decision support; cost accounting | S53: master | U53: batch_import | V53: batch_admin | W53: 1 | X53: 2026-04-29 15:09:38.974553 | Y53: Manuel Kaburek | Z53: approved
A54: 52 | B54: 12008933_0053 | C54: Welche Aussage(n) zu Wertaufholungen nach IFRS ist/sind korrekt? | D54: multi_choice | E54: interpretation_of_law | F54: multi_choice | G54: A,B,C,D | H54: {"a": "Wertaufholungen sind f\u00fcr Sachanlagen zul\u00e4ssig, wenn der Wertminderungsgrund entf\u00e4llt.", "b": "F\u00fcr Goodwill sind Wertaufholungen unzul\u00e4ssig.", "c": "Wertaufholungen sind auf den Betrag begrenzt, der sich ohne zuvorige Wertminderung ergeben h\u00e4tte.", "d": "Wertaufholungen werden erfolgswirksam erfasst, sofern keine Neubewertungsr\u00fccklage betroffen ist.", "e": "Wertaufholungen sind nach IFRS generell verboten."} | I54: Exact set match required (A, B, C and D). Order irrelevant. Case-insensitive. No additional choices allowed. | N54: IFRS | O54: 2025 | P54: financial_accounting | Q54: ifrs_impairment | R54: financial accounting; ifrs impairment; IFRS | S54: master | U54: batch_import | V54: batch_admin | W54: 1 | X54: 2026-04-29 15:10:29.203759 | Y54: Manuel Kaburek | Z54: approved
... A156: 154 | B156: 12008933_0155 | C156: Was versteht man unter dem Niederstwertprinzip im Umlaufvermögen (UGB)? | D156: open_text | E156: interpretation_of_law | F156: open_text | G156: Ansatz zum niedrigeren Wert aus Anschaffungs- oder Herstellungskosten und beizulegendem Wert am Bilanzstichtag; im Umlaufvermögen gilt das strenge Niederstwertprinzip. | H156: null | I156: Answer must contain: (1) Vergleich AK/HK mit beizulegendem Wert, (2) Ansatz des niedrigeren Wertes, (3) Hinweis auf strenges Niederstwertprinzip im Umlaufvermögen. Semantische Übereinstimmung ausreichend. Minor wording deviations allowed. | N156: UGB | O156: 2025 | P156: financial_accounting | Q156: current_assets | R156: valuation principles; UGB knowledge; conceptual explanation | S156: master | U156: batch_import | V156: batch_admin | W156: 1 | X156: 2026-04-29 15:49:46.376005 | Y156: Manuel Kaburek | Z156: approved
A157: 155 | B157: 12008933_0156 | C157: Welche der folgenden Aussage(n) ist/sind korrekt? | D157: multi_choice | E157: interpretation_of_law | F157: multi_choice | G157: C,D | H157: {"a": "Bei Gewinnermittlung nach \u00a7 4 Abs 1 EStG kann sich aufgrund der Bewertung selbsterstellter Anlageg\u00fcter eine Mehr-Weniger-Rechnung ergeben.", "b": "Immaterielle Verm\u00f6gensgegenst\u00e4nde des Umlaufverm\u00f6gens d\u00fcrfen weder im EStG noch im UGB aktiviert werden.", "c": "LKW-Unfall am 27.12.X1, Meldung 5.1.X2 \u2014 werterhellender Umstand.", "d": "Wenn ein Unternehmen das Ziel der Gewinnmaximierung verfolgt, entscheidet es sich bei der Bewertung selbsterstellter Anlageg\u00fcter f\u00fcr den H\u00f6chstansatz.", "e": "Die steuerliche Nutzungsdauer von Grundst\u00fccken im Anlageverm\u00f6gen betr\u00e4gt immer 20 Jahre."} | I157: Exact set match required (C and D). Order irrelevant. Case-insensitive. No additional choices allowed. | N157: mixed_accounting_tax | O157: 2025 | P157: financial_accounting | R157: valuation; tax accounting; period allocation; conceptual judgement | S157: master | U157: batch_import | V157: batch_admin | W157: 1 | X157: 2026-04-29 15:50:22.727640 | Y157: Manuel Kaburek | Z157: approved
A158: 156 | B158: 12008933_0157 | C158: Welche der folgenden Aussagen beschreibt die Unterschiede in der Bilanzierung von Forschungs- und Entwicklungskosten nach dem UGB und den IFRS? | D158: single_choice | E158: interpretation_of_law | F158: single_choice | G158: C | H158: {"a": "Der k\u00fcnftige Nutzen ist f\u00fcr die Erf\u00fcllung der Ansatzkriterien in IFRS unerheblich.", "b": "Nach IFRS d\u00fcrfen Forschungs- und Entwicklungskosten stets aktiviert werden, wenn sie einen zuk\u00fcnftigen Nutzen erwarten lassen.", "c": "In IFRS besteht ein Aktivierungsverbot f\u00fcr Entwicklungsaufwendungen vor dem Zeitpunkt der Kriterienerf\u00fcllung.", "d": "Nach beiden Regelwerken d\u00fcrfen Forschungs- und Entwicklungskosten nur dann aktiviert werden, wenn sie durch staatliche F\u00f6rderungen gedeckt sind.", "e": "Nach dem UGB besteht ein Wahlrecht zur Aktivierung von Forschungskosten, w\u00e4hrend IFRS diese zwingend als Aufwand behandeln"} | I158: Exact match of choice_id (A/B/C/D/E); case-insensitive. No partial credit. | N158: mixed_accounting_framework | O158: 2025 | P158: financial_accounting | Q158: recognition | R158: recognition; IFRS vs UGB comparison; conceptual understanding | S158: master | U158: batch_import | V158: batch_admin | W158: 1 | X158: 2026-04-29 15:51:21.900004 | Y158: Manuel Kaburek | Z158: approved
A159: 157 | B159: 12308280_0001 | C159: Die Haus & Heim-Baumarkt OG in Wiener Neustadt kauft im Jahr 20.. Unter anderem nachstehende Anlagegenstände: 7.5.20..: Kauf eines Kombi-Geräts (Fax, Kopierer, Scann) laut abgebildeter Rechnung, Lieferant Carl Rainer Bürobedarfs GmbH (33401) 17.5.20.. B80 Überweisung des Rechnungsbetrages an die Carl Rainer Bürobedarfs GmbH Erstellen Sie die erforderlichen Buchungen im Zusammenhang mit dem Kauf. | D159: journal_entry | E159: journal_entry | F159: journal_entry | G159: 7.5.20..: 0620 Büromaschinen, EDV-Anlagen 760,00 2500 Vorsteuer 152,00 an 33401 Carl Rainer Bürobedarfs GmbH 912,00 17.5.20..: 33401 Carl Rainer Bürobedarfs GmbH 912,00 an 2800 Bank 912,00 | H159: null | I159: Answer must contain: (1) Verbuchung der Rechnung, (2) Verbuchung der Überweisung | K159: Verwendung von anderen Kontonummern | M159: C:\Users\dhoellmu\OneDrive - WU Wien\Dokumente\AccountingBench\backend\uploads\12308280_0001_File01.pdf | N159: UGB | O159: 2015 | P159: financial_accounting | Q159: non-current_assets | R159: UGB knowledge, accounting knowledge | S159: secondary_vocational_school | U159: batch_import | V159: batch_admin | W159: 1 | X159: 2026-04-29 15:51:57.272729 | Y159: Manuel Kaburek | Z159: approved
A160: 158 | B160: 12308280_0002 | C160: 22.10.20..: Beleg über den Kauf einer Heckenschere um € 210,00 (inkl. 20% UST) in Bar Erstellen Sie die erforderlichen Buchungen im Zusammenhang mit dem Kauf. | D160: journal_entry | E160: journal_entry | F160: journal_entry | G160: 20.10: 0550 Geringwertige Werkzeuge 175,00 2500 Vorsteuer 35,00 an 2700 Kassa 210,00 31.12.: 7030 Abschreibung GWG 175,00 an 0550 Geringwertige Werkzeuge 175,00 | H160: null | I160: Answer must contain: Verbuchung als geringwertiges Wirtschaftsgut und volle Abschreibung entweder sofort oder am Ende des Jahres | K160: Verwendung von anderen Kontonummern und direkte Verbuchung des geringwertigen Wirtschaftsgutes: 20.10.: 7030 Abschreibung GWG 175,00 2500 Vorsteuer 35,00 an 2700 Kassa 210,00 | N160: UGB | O160: 2015 | P160: financial_accounting | Q160: non-current_assets | R160: UGB knowledge, accounting knowledge, Tax accounting | S160: secondary_vocational_school | U160: batch_import | V160: batch_admin | W160: 1 | X160: 2026-04-29 15:53:03.952452 | Y160: Manuel Kaburek | Z160: approved
A161: 159 | B161: 12308280_0003 | C161: 28.11.: Die Eigentümerin eines Einzelhandelsunternehmens hat einen Vorhangstoff für das Geschäftslokal um 800,00 + 160,00 UST = 960,00 gekauft und mit Firmenkreditkarte (VISA) bezahlt. 22.12. B225: Monatsrechnung VISA, Abbuchung 1.548,00 Erstellen Sie die erforderlichen Buchungen im Zusammenhang mit dem Kauf. | D161: journal_entry | E161: journal_entry | F161: journal_entry | G161: 28.11.: 0660 Betriebs- und Geschäftsausstattung 800,00 2500 VSt 160,00 an 3180 Verbindlichkeiten VISA 960,00 22.12.: 3190 Verbindlichkeiten VISA 1.548,00 an 2800 Bank 1.548,00 | H161: null | I161: Answer must contain: (1) Verbuchung des Belegs als Betriebs- und Geschäftsausstattung, (2) Verbuchung der Monatsrechnung | K161: Verwendung von anderen Kontonummern | N161: UGB | O161: 2015 | P161: financial_accounting | Q161: non-current_assets | R161: UGB knowledge, accounting knowledge | S161: secondary_vocational_school | U161: batch_import | V161: batch_admin | W161: 1 | X161: 2026-04-29 15:53:37.548816 | Y161: Manuel Kaburek | Z161: approved
A162: 160 | B162: 12308280_0004 | C162: Welche Kosten müssen für die Berechnung des Anschaffungswertes einer Maschine berücksichtigt werden? | D162: multi_choice | E162: interpretation_of_law | F162: multi_choice | G162: A, C, D, F | H162: {"a": "Kaufpreis der Maschine", "b": "Kosten der Kreditbeschaffung", "c": "Transportkosten", "d": "Kosten f\u00fcr die Aufstellung und Inbetriebnahme", "e": "Vorsteuer", "f": "Skonto"} | I162: Exact set match required (A, C, D and F). Order irrelevant. Case-insensitive. No additional choices allowed. | N162: UGB | O162: 2016 | P162: financial_accounting | Q162: non-current_assets | R162: UGB knowledge, accounting knowledge | S162: secondary_vocational_school | U162: batch_import | V162: batch_admin | W162: 1 | X162: 2026-04-29 15:53:51.666464 | Y162: Manuel Kaburek | Z162: approved
A163: 161 | B163: 12308280_0005 | C163: Kauf eines neuen PKW für das Unternehmen von Renault Aichlseder GmbH (33405) um 14.000,00 + 840,00 NoVA + 168,00 NoVa-Zuschlag + 2.800,00 UST = 17.808,00 Erstellen Sie die erforderlichen Buchungen im Zusammenhang mit dem Kauf. | D163: journal_entry | E163: journal_entry | F163: journal_entry | G163: 0630 PKW 17.808,00 an 33405 Renault Aichlseder GmbH 17.808,00 | H163: null | I163: Answer must contain: (1) Verbuchung des Belegs | K163: Verwendung von anderen Kontonummern | N163: UGB | O163: 2015 | P163: financial_accounting | Q163: non-current_assets | R163: UGB knowledge, accounting knowledge | S163: secondary_vocational_school | U163: batch_import | V163: batch_admin | W163: 1 | X163: 2026-04-29 15:54:34.980271 | Y163: Manuel Kaburek | Z163: approved
A164: 162 | B164: 12030864_0001 | C164: Elias Zauner ist als Konditor (Arbeiter) beschäftigt und erhält einen monatlichen Bruttolohn von EUR 2.280,00. Für den Abrechnungsmonat gelten folgende Rahmenbedingungen: Kein Anspruch auf FABO Plus Kein Anspruch auf AV(E)AB Ein monatlicher Freibetrag in Höhe von EUR 25,00 ist zu berücksichtigen Eine Pendlerpauschale in Höhe von EUR 123,00 ist zu berücksichtigen Eine Akontozahlung in Höhe von EUR 400,00 wurde bereits geleistet Keine weiteren Zu- oder Abschläge Keine Sonderzahlungen Die Sozialversicherungsbeiträge sowie die lohnsteuerliche Behandlung sind gemäß den in Österreich für das betreffende Jahr geltenden gesetzlichen Bestimmungen zu ermitteln. Rundung auf zwei Dezimalstellen. Aufgabe: Ermitteln Sie den Sozialversicherungs-Dienstnehmeranteil. Bestimmen Sie die Lohnsteuer-Bemessungsgrundlage. Berechnen Sie die Lohnsteuer. Ermitteln Sie den Auszahlungsbetrag. | D164: open_text | E164: calculation | F164: open_text | G164: {"person":"Elias Zauner","beruf":"Konditor","bruttolohn":2280.00,"sozialversicherung":{"satz_prozent":17.12,"betrag":390.34},"lohnsteuer_bemessungsgrundlage":{"brutto":2280.00,"minus_sv":390.34,"minus_freibetrag":25.00,"minus_pendlerpauschale":123.00,"steuerbasis":1741.66},"lohnsteuer":80.25,"akontozahlung":400.00,"auszahlungsbetrag":1409.41} | H164: null | I164: Exact match required for all final numeric results. Intermediate values must be economically and mathematically correct. Correct application of social security rate, tax allowance and commuter allowance required. Correct determination of the wage tax base and wage tax required. Correct deduction of advance payment required. Minor rounding deviations within tolerance allowed. Follow-up errors are considered if calculation logic is consistent. | N164: austrian_tax_law | O164: 2025 | P164: tax | R164: Payroll accounting; Social security calculation; Wage tax calculation; Tax allowance application; Net pay computation; Numerical accuracy | S164: secondary_vocational_school | U164: batch_import | V164: batch_admin | W164: 1 | X164: 2026-04-29 15:55:06.225970 | Y164: Manuel Kaburek | Z164: approved
A165: 163 | B165: 12030864_0002 | C165: Thomas Gasser ist Versicherungskaufmann (Angestelltenlehrling) und befindet sich im 1. Lehrjahr. Das Lehrverhältnis begann im Juni 2025. Für den Abrechnungsmonat Juli 2025 gilt: Lehrlingseinkommen (Brutto): EUR 970,00 Kein Anspruch auf FABO Plus Kein Anspruch auf AV(E)AB Keine sonstigen Zu- oder Abschläge Keine Sonderzahlungen Die Sozialversicherungsbeiträge sind gemäß den in Österreich für Angestelltenlehrlinge im Jahr 2025 geltenden Beitragssätzen zu ermitteln. Die steuerliche Behandlung erfolgt nach den in Österreich für Juli 2025 geltenden lohnsteuerrechtlichen Bestimmungen. Rundung auf zwei Dezimalstellen. Aufgabe: Ermitteln Sie den Sozialversicherungs-Dienstnehmeranteil. Berechnen Sie die Lohnsteuer. Bestimmen Sie den Auszahlungsbetrag. | D165: open_text | E165: calculation | F165: open_text | G165: {"person":"Thomas Gasser","beruf":"Versicherungskaufmann (Angestelltenlehrling)","bruttoeinkommen":970.00,"sozialversicherung":{"satz_prozent":11.92,"betrag":115.62},"lohnsteuer_bemessungsgrundlage":{"brutto":970.00,"minus_sv":115.62,"steuerbasis":854.38},"lohnsteuer":0.00,"auszahlungsbetrag":854.38} | H165: null | I165: Exact match required for all final numeric results. Correct identification and application of the apprentice social security rate required. Correct assessment of wage tax liability required. Correct computation of net pay required. Minor rounding deviations within tolerance allowed. Follow-up errors are considered if calculation logic is consistent. | N165: austrian_tax_law | O165: 2025 | P165: tax | R165: Payroll accounting; Social security calculation; Wage tax calculation; Tax allowance application; Net pay computation; Numerical accuracy | S165: secondary_vocational_school | U165: batch_import | V165: batch_admin | W165: 1 | X165: 2026-04-29 15:55:42.445535 | Y165: Manuel Kaburek | Z165: approved
A166: 164 | B166: 12030864_0003 | C166: Dienstreise des Angestellten Georg Teigl (Programmierer): Beginn Montag 17:00 Uhr, Ende Mittwoch 21:30 Uhr. Tagesgeld lt. Kollektivvertrag € 34,80, nachgewiesene tatsächliche Nächtigungskosten € 146,–. Kollektivvertrag: Das volle Tagesgeld von € 34,80 gebührt 1. für 24 Stunden, 2. je Kalendertag. Es gebührt bei einer Reisedauer bis zu 4 Stunden – kein Tagesgeld, von mehr als 4 bis 6 Stunden – ⅓ des Tagesgeldes, von mehr als 6 bis 8 Stunden – ⅔ des Tagesgeldes und von mehr als 8 Stunden – das volle Tagesgeld. Berechne das Tagesgeld für diese Dienstreise im Sinne der 24-Stunden-Regelung (1.) bzw. der Kalendertags-regelung (2.). Wie viel davon ist abgabenfrei bzw. abgabenpflichtig zu behandeln? Stelle fest, ob die Nächti-gungskosten abgabenpflichtig sind. | D166: open_text | E166: calculation | F166: open_text | G166: {"person":"Georg Teigl","beruf":"Programmierer","reisezeitraum":{"beginn":"Montag 17:00","ende":"Mittwoch 21:30"},"tagesgeld_kv":34.80,"24_stunden_regelung":{"intervalle":[{"von":"Mo 17:00","bis":"Di 17:00","tagesgeld":34.80,"abgabenfrei":30.00,"abgabenpflichtig":4.80},{"von":"Di 17:00","bis":"Mi 17:00","tagesgeld":34.80,"abgabenfrei":30.00,"abgabenpflichtig":4.80},{"von":"Mi 17:00","bis":"Mi 21:30","anteil":"1/3","tagesgeld":11.60,"abgabenfrei":11.60,"abgabenpflichtig":0.00}],"summe":{"gesamt":81.20,"abgabenfrei":71.60,"abgabenpflichtig":9.60}},"kalendertagsregelung":{"intervalle":[{"von":"Mo 17:00","bis":"Mo 24:00","anteil":"2/3","tagesgeld":23.20,"abgabenfrei":17.50,"abgabenpflichtig":5.70},{"von":"Di 00:00","bis":"Di 24:00","tagesgeld":34.80,"abgabenfrei":30.00,"abgabenpflichtig":4.80},{"von":"Mi 00:00","bis":"Mi 21:30","tagesgeld":34.80,"abgabenfrei":30.00,"abgabenpflichtig":4.80}],"summe":{"gesamt":92.80,"abgabenfrei":77.50,"abgabenpflichtig":15.30}},"naechigungskosten":{"betrag":146.00,"abgabenstatus":"abgabenfrei"}} | H166: null | I166: Exact match required for all final numeric results. Correct application of collective agreement rules (24-hour rule and calendar-day rule) required. Correct proportional calculation of per diem entitlements required. Correct classification of tax-free and taxable portions required. Correct assessment of accommodation cost treatment required. Minor rounding deviations within tolerance allowed. Follow-up errors are considered if calculation logic is consistent. | N166: austrian_tax_law | O166: 2025 | P166: tax | R166: Travel expense accounting; Per diem calculation; Application of collective agreement rules; Time-based entitlement determination; Tax treatment of travel allowances; Taxable vs. tax-free classification; Numerical accuracy | S166: secondary_vocational_school | U166: batch_import | V166: batch_admin | W166: 1 | X166: 2026-04-29 15:59:09.534911 | Y166: Manuel Kaburek | Z166: approved
A167: 165 | B167: 12030864_0004 | C167: Ing. Gustav Niederl betreibt ein Computer-Fachgeschäft. Im laufenden Geschäftsjahr ergeben sich folgende Geschäftsfälle: Überweisung an das Finanzamt laut Buchungsmitteilung: Vorauszahlung Einkommensteuer EUR 4.000,00 (Banküberweisung). Einzahlung von EUR 3.500,00 von der Geschäftskasse auf das Bankkonto. Gutschrift laut Kontoauszug in Höhe von EUR 3.500,00. Aufgabenstellung: a) Stellen Sie zu jedem Geschäftsfall den entsprechenden Buchungssatz auf. b) Geben Sie an, ob sich durch den jeweiligen Geschäftsfall das Eigenkapital vermehrt (↑), vermindert (↓) oder nicht verändert (→ erfolgsneutral) wird. | D167: journal_entry | E167: journal_entry | F167: journal_entry | G167: {"fall_1":{"buchung":"9610 Privatsteuern an 2800 Bank","betrag":4000.00,"eigenkapital":"↓"},"fall_2":{"buchung":"2870 Barverkehr mit Banken an 2700 Kassa","betrag":3500.00,"eigenkapital":"→"},"fall_3":{"buchung":"2800 Bank an 2870 Barverkehr mit Banken","betrag":3500.00,"eigenkapital":"→"}} | H167: null | I167: Correct journal entry structure required (proper accounts and debit/credit logic). Correct amount required for each transaction. Correct classification of equity impact required. Entries must follow accounting logic and chart of accounts. Minor wording deviations allowed if accounting meaning is correct. | N167: UGB | O167: 2025 | P167: financial_accounting | R167: Journal entry preparation; Account classification; Equity impact analysis; Application of chart of accounts; Recognition of private withdrawals and contributions; Numerical accuracy | S167: secondary_vocational_school | U167: batch_import | V167: batch_admin | W167: 1 | X167: 2026-04-29 16:00:01.564605 | Y167: Manuel Kaburek | Z167: approved
A168: 166 | B168: 12030864_0005 | C168: Ing. Gustav Niederl betreibt ein Computer-Fachgeschäft. Im laufenden Geschäftsjahr ergeben sich folgende Geschäftsfälle: Überweisung an das Finanzamt laut Bescheid: Abschlusszahlung Einkommensteuer EUR 3.280,00 sowie USt-Zahllast EUR 430,00 (Banküberweisung). Gehaltsabrechnung (Bezugserfassung): Bruttogehälter EUR 14.026,00; Sozialversicherungs-Dienstnehmeranteil EUR 2.534,50; Lohnsteuer EUR 1.102,31. Gehaltsnebenkosten (Dienstgeberabgaben): Sozialversicherungs-Dienstgeberanteil EUR 2.942,65; BV-Beitrag EUR 214,60; Dienstgeberbeitrag (DB) EUR 518,96; Zuschlag zum DB (0,40 %) EUR 56,10; Kommunalsteuer EUR 420,78. Aufgabenstellung: Stellen Sie zu jedem Geschäftsfall den entsprechenden Buchungssatz auf und geben Sie an, ob sich durch den jeweiligen Geschäftsfall das Eigenkapital vermehrt (↑), vermindert (↓) oder nicht verändert (→ erfolgsneutral) wird. | D168: journal_entry | E168: journal_entry | F168: journal_entry | G168: {"fall_4":{"buchung":["9610 Privatsteuern an 2800 Bank","3520 USt-Zahllast an 2800 Bank"],"betrag":[3280.00,430.00],"eigenkapital":"→"},"fall_5":{"buchung":"6200 Gehälter an 3600 Verbindlichkeiten Gesundheitskasse, 3540 Verbindlichkeiten Finanzamt, 3850 Verbindlichkeiten gegenüber Mitarbeiter","betrag":[14026.00,2534.50,1102.31,10389.19],"eigenkapital":"↓"},"fall_6":{"buchung":["6560 Gesetzlicher Sozialversicherungsaufwand an 3600 Verbindlichkeiten Gesundheitskasse","6441 Aufwand für Betriebliche Vorsorgekassen an 3600 Verbindlichkeiten Gesundheitskasse","6660 Dienstgeberbeitrag an 3540 Verbindlichkeiten Finanzamt","6670 Zuschlag zum DB an 3540 Verbindlichkeiten Finanzamt","6680 Kommunalsteuer an 3610 Verbindlichkeiten Gemeinde"],"betrag":[2942.65,214.60,518.96,56.10,420.78],"eigenkapital":"↓"}} | H168: null | I168: Correct journal entry structure required (proper accounts and debit/credit logic). Correct amount required for each transaction. Correct separation of payroll components and tax liabilities required. Correct classification of equity impact required. Entries must follow accounting logic and chart of accounts. Minor wording deviations allowed if accounting meaning is correct. | N168: UGB | O168: 2025 | P168: financial_accounting | R168: Journal entry preparation; Payroll accounting; Employer contribution accounting; Tax liability recognition; Equity impact analysis; Application of chart of accounts; Numerical accuracy | S168: secondary_vocational_school | U168: batch_import | V168: batch_admin | W168: 1 | X168: 2026-04-29 16:01:44.062314 | Y168: Manuel Kaburek | Z168: approved
A169: 167 | B169: 12030864_0006 | C169: Ing. Gustav Niederl betreibt ein Computer-Fachgeschäft. Im laufenden Geschäftsjahr ergeben sich folgende Geschäftsfälle: Von Karl Stammer e. U. (Konto 20021) geht eine Banküberweisung ein: Rechnungsbetrag EUR 2.710,00 abzüglich Skonto EUR 81,30. Das Skonto setzt sich zusammen aus Skonto netto EUR 67,75 und Umsatzsteuer EUR 13,55. Der tatsächliche Bankeingang beträgt EUR 2.628,70. Überweisung an das Finanzamt: USt-Zahllast EUR 3.734,00 sowie Kammerumlage für das 1. Quartal EUR 98,70 (Banküberweisung). Überweisung der Auszahlungsbeträge an die Mitarbeiter in Höhe von EUR 10.389,19 (Banküberweisung). Laut Kontoauszug erfolgen Überweisungen an die Österreichische Gesundheitskasse EUR 5.691,75, an das Finanzamt EUR 1.677,37 sowie an die Gemeinde (Stadt) EUR 420,78 (Banküberweisung). Bankeingang EUR 2.000,00 als Teilzahlung von Robert Freymuth (Konto 20020) für eine Ausgangsrechnung (A 63). Mahnung an den Kunden Seifert & Pfeiffer GmbH (Konto 20081) betreffend eine offene Rechnung über EUR 1.632,00. Zusätzlich werden EUR 10,00 Mahnspesen in Rechnung gestellt. Aufgabenstellung: Stellen Sie zu jedem Geschäftsfall den entsprechenden Buchungssatz auf und geben Sie an, ob sich durch den jeweiligen Geschäftsfall das Eigenkapital vermehrt (↑), vermindert (↓) oder nicht verändert (→ erfolgsneutral) wird. | D169: journal_entry | E169: journal_entry | F169: journal_entry | G169: {"fall_7":{"buchung":["2800 Bank an 20021 Karl Stammer e. U.","4410 Kundenskonto 20 %, 3500 Umsatzsteuer an 20021 Karl Stammer e. U."],"betrag":[2628.70,67.75,13.55,81.30],"eigenkapital":["→","↓"]},"fall_8":{"buchung":"3520 USt-Zahllast, 7780 Kammerumlage an 2800 Bank","betrag":[3734.00,98.70,3832.70],"eigenkapital":"↓"},"fall_9":{"buchung":"3850 Verbindlichkeiten gegenüber Mitarbeiter aus der Bezugsverrechnung an 2800 Bank","betrag":10389.19,"eigenkapital":"→"},"fall_10":{"buchung":"3600 Verbindlichkeiten Gesundheitskasse, 3540 Verbindlichkeiten Finanzamt, 3610 Verbindlichkeiten Gemeinde (Stadt) an 2800 Bank","betrag":[5691.75,1677.37,420.78,7789.90],"eigenkapital":"→"},"fall_11":{"buchung":"2800 Bank an 20020 Robert Freymuth","betrag":2000.00,"eigenkapital":"→"},"fall_12":{"buchung":"20081 Seifert & Pfeiffer GmbH an 4890 Mahnspesenvergütungen","betrag":10.00,"eigenkapital":"↑"}} | H169: null | I169: Correct journal entry structure required (proper accounts and debit/credit logic). Correct treatment of cash discounts and VAT adjustments required. Correct settlement of tax and payroll liabilities required. Correct recognition of receivables and additional charges required. Correct equity impact assessment required. Entries must follow accounting logic and chart of accounts. Minor wording deviations allowed if accounting meaning is correct. | N169: UGB | O169: 2025 | P169: financial_accounting | R169: Journal entry preparation; Accounts receivable accounting; Cash discount accounting; VAT accounting; Settlement of tax and payroll liabilities; Equity impact analysis; Application of chart of accounts; Numerical accuracy | S169: secondary_vocational_school | U169: batch_import | V169: batch_admin | W169: 1 | X169: 2026-04-29 16:05:35.015064 | Y169: Manuel Kaburek | Z169: approved
A170: 168 | B170: 12030864_0007 | C170: In der Führlinger & Staltner e. U. (Dekorstoffe Groß- und Einzelhandel) ergeben sich folgende Geschäftsfälle: Überweisung an das Finanzamt laut Bescheid: Abschlusszahlung Einkommensteuer EUR 5.420,00. Einlage auf das Bankkonto in Höhe von EUR 2.500,00 (von der Geschäftskasse). Überweisung an Malits OG (Konto 33029) zum Ausgleich der E 52: Rechnungsbetrag EUR 8.730,00 abzüglich Skonto EUR 261,90 (Skonto netto EUR 218,25 und USt EUR 43,65), somit Überweisung EUR 8.468,10. Kontoauszug über den Eigenerlag auf das Bankkonto in Höhe von EUR 2.500,00. Überweisung an das Finanzamt laut Buchungsmitteilung: Vorauszahlung Einkommensteuer EUR 4.600,00. Gehaltsabrechnung (Bezugserfassung): Bruttogehälter EUR 17.176,00; SV-Dienstnehmeranteil EUR 3.103,70; Lohnsteuer EUR 2.166,87. Aufgabenstellung: Stellen Sie zu jedem Geschäftsfall den entsprechenden Buchungssatz auf und geben Sie an, ob sich durch den jeweiligen Geschäftsfall das Eigenkapital vermehrt (↑), vermindert (↓) oder nicht verändert (→ erfolgsneutral) wird. | D170: journal_entry | E170: journal_entry | F170: journal_entry | G170: {"fall_1":{"buchung":"9610 Privatsteuern an 2800 Bank","betrag":5420.00,"eigenkapital":"→"},"fall_2":{"buchung":"2870 Barverkehr mit Banken an 2700 Kassa","betrag":2500.00,"eigenkapital":"→"},"fall_3":{"buchung":["33029 Malits OG an 2800 Bank","33029 Malits OG an 5880 Lieferantenskonto 20 %, 2800 Bank"],"betrag":[8468.10,261.90,218.25,43.65],"eigenkapital":["→","↑"]},"fall_4":{"buchung":"2800 Bank an 2870 Barverkehr mit Banken","betrag":2500.00,"eigenkapital":"→"},"fall_5":{"buchung":"9610 Privatsteuern an 2800 Bank","betrag":4600.00,"eigenkapital":"→"},"fall_6":{"buchung":"6200 Gehälter an 3600 Verbindlichkeiten Gesundheitskasse, 3540 Verbindlichkeiten Finanzamt, 3850 Verbindlichkeiten gegenüber Mitarbeiter aus der Bezugsverrechnung","betrag":[17176.00,3103.70,2166.87,11905.43],"eigenkapital":"↓"}} | H170: null | I170: Correct journal entry structure required (proper accounts and debit/credit logic). Correct amounts required for each transaction. Correct treatment of cash discounts required. Correct recognition of payroll components and liabilities required. Correct equity impact assessment required. Entries must follow accounting logic and chart of accounts. Minor wording deviations allowed if accounting meaning is correct. | N170: UGB | O170: 2025 | P170: financial_accounting | R170: Journal entry preparation; Cash and bank transaction accounting; Accounts payable accounting; Cash discount accounting; Payroll accounting; Equity impact analysis; Application of chart of accounts; Numerical accuracy | S170: secondary_vocational_school | U170: batch_import | V170: batch_admin | W170: 1 | X170: 2026-04-29 16:08:01.504852 | Y170: Manuel Kaburek | Z170: approved
A171: 169 | B171: 12030864_0008 | C171: In der Führlinger & Staltner e. U. (Dekorstoffe Groß- und Einzelhandel) ergeben sich folgende Geschäftsfälle: Gehaltsnebenkosten (Dienstgeberabgaben): SV-Dienstgeberanteil EUR 3.603,52; BV-Beitrag EUR 262,79; Dienstgeberbeitrag (DB) EUR 635,51; Zuschlag zum DB (0,36 %) EUR 61,83; Kommunalsteuer EUR 515,28; Wiener Dienstgeberabgabe EUR 24,00. Bankgutschrift EUR 960,00. Die Karl Grasl KG (Konto 20030) hat die Ausgangsrechnung A 117 ausgeglichen. Überweisung der Auszahlungsbeträge an die Mitarbeiter EUR 11.905,43. Überweisung an die Österreichische Gesundheitskasse EUR 6.970,01, an das Finanzamt EUR 2.864,21 sowie an die Gemeinde (Stadt) EUR 539,28. Mahnung des Lieferanten Bart Bauer GmbH (Konto 33061), dass die Rechnung E 68 über EUR 2.416,80 noch nicht bezahlt ist. Zusätzlich werden EUR 12,00 Mahnspesen in Rechnung gestellt. Nachträglicher Rabatt an den Kunden Franz Stangel e. U. (Konto 20071) in Höhe von EUR 300,00 zuzüglich EUR 60,00 USt (gesamt EUR 360,00). Aufgabenstellung: Stellen Sie zu jedem Geschäftsfall den entsprechenden Buchungssatz auf und geben Sie an, ob sich durch den jeweiligen Geschäftsfall das Eigenkapital vermehrt (↑), vermindert (↓) oder nicht verändert (→ erfolgsneutral) wird. | D171: journal_entry | E171: journal_entry | F171: journal_entry | G171: {"fall_7":{"buchung":["6560 Gesetzlicher Sozialversicherungsaufwand Angestellte an 3600 Verbindlichkeiten Gesundheitskasse","6441 Aufwand für Betriebliche Vorsorgekassen Angestellte an 3600 Verbindlichkeiten Gesundheitskasse","6660 Dienstgeberbeitrag Angestellte an 3540 Verbindlichkeiten Finanzamt","6670 Zuschlag zum DB Angestellte an 3540 Verbindlichkeiten Finanzamt","6680 Kommunalsteuer Angestellte an 3610 Verbindlichkeiten Gemeinde (Stadt)","6690 Wiener Dienstgeberabgabe Angestellte an 3610 Verbindlichkeiten Gemeinde (Stadt)"],"betrag":[3603.52,262.79,635.51,61.83,515.28,24.00],"eigenkapital":"↓"},"fall_8":{"buchung":"2800 Bank an 20030 Karl Grasl KG","betrag":960.00,"eigenkapital":"→"},"fall_9":{"buchung":"3850 Verbindlichkeiten gegenüber Mitarbeiter aus der Bezugsverrechnung an 2800 Bank","betrag":11905.43,"eigenkapital":"→"},"fall_10":{"buchung":"3500 Verbindlichkeiten Gesundheitskasse, 3540 Verbindlichkeiten Finanzamt, 3610 Verbindlichkeiten Gemeinde (Stadt) an 2800 Bank","betrag":[6970.01,2864.21,539.28,10373.50],"eigenkapital":"→"},"fall_11":{"buchung":"8321 Mahnspesen an 33061 Bart Bauer GmbH","betrag":12.00,"eigenkapital":"↓"},"fall_12":{"buchung":"4400 Erlösberichtigungen 20 %, 3500 Umsatzsteuer an 20071 Franz Stangel e. U.","betrag":[300.00,60.00,360.00],"eigenkapital":"↓"}} | H171: null | I171: Correct journal entry structure required (proper accounts and debit/credit logic). Correct amounts required for each transaction. Correct accounting for employer contributions and related liabilities required. Correct treatment of settlements (bank receipts and payments) required. Correct recognition of dunning charges and revenue/VAT adjustments required. Correct equity impact assessment required. Minor wording deviations allowed if accounting meaning is correct. | N171: UGB | O171: 2025 | P171: financial_accounting | R171: Journal entry preparation; Employer contribution accounting; Accounts receivable accounting; Settlement of payroll and tax liabilities; Late fee / dunning charge accounting; Revenue adjustment and VAT correction; Equity impact analysis; Numerical accuracy | S171: secondary_vocational_school | U171: batch_import | V171: batch_admin | W171: 1 | X171: 2026-04-29 16:10:16.661270 | Y171: Manuel Kaburek | Z171: approved
A172: 170 | B172: 12030864_0009 | C172: In der Computerhandels-GmbH (Wiener Neustadt) ergeben sich folgende Geschäftsfälle: Eine Bahnfahrt von Wiener Neustadt nach Wien Hauptbahnhof wird bar bezahlt. Der Bruttobetrag beträgt EUR 12,20 (inkl. 10 % USt). Ein Firmen-Pkw (Marke Citroën) wird vom Autohaus Weiss GmbH (Konto 33077) um EUR 32.000,00 (inkl. 20 % USt und NoVA) gegen spätere Bezahlung gekauft. Benzin für den Firmen-Pkw wird um EUR 52,00 (inkl. 20 % USt) gekauft und mit der Firmenkreditkarte bezahlt. Für eine betrieblich veranlasste Reise werden Tagesgelder in Höhe von EUR 90,00 (EUR 30,00 × 3) sowie Nächtigungskosten laut Beleg in Höhe von EUR 142,50 geltend gemacht. Zusätzlich findet ein Abendessen mit einem Kunden statt (gesamt EUR 139,60; davon EUR 64,00 zu 20 % USt und EUR 75,60 zu 10 % USt). Das Abendessen ist nur zu 50 % als Betriebsausgabe absetzbar. Ein Angestellter erhält Kilometergeld für 847 km à EUR 0,50. Ein Service für den Pkw wird mit der Firmendebitkarte bezahlt (EUR 124,00 + EUR 24,80 USt = EUR 148,80). Eine Autobahnvignette für den Pkw wird bar gekauft (EUR 103,80 inkl. 20 % USt). Aufgabenstellung: Stellen Sie die Buchungssätze auf. | D172: journal_entry | E172: journal_entry | F172: journal_entry | G172: {"fall_1":{"buchung":"7340 Bahn- und Autobuskosten Inlandsreisen, 2500 Vorsteuer an 2700 Kassa","betrag":[11.09,1.11,12.20]},"fall_2":{"buchung":"0630 Pkw und Kombis an 33077 Autohaus Weiss GmbH","betrag":32000.00},"fall_3":{"buchung":"7320 Pkw- und Kombi-Betriebsaufwand an 3180 Verbindlichkeiten Kreditkarten","betrag":52.00},"fall_4":{"buchung":["7360 Tagesgelder Inland, 2500 Vorsteuer an 2700 Kassa","7364 Nächtigungsgelder Inland, 2500 Vorsteuer an 2700 Kassa","7660 Aufwand für Geschäftsanbahnung 20 %, 7661 Aufwand für Geschäftsanbahnung 10 %, 2500 Vorsteuer an 2700 Kassa","7663 Nicht absetzbarer Aufw. f. Geschäftsanb. 20 %, 7664 Nicht absetzbarer Aufw. f. Geschäftsanb. 10 %, 2500 Vorsteuer an 2700 Kassa"],"betrag":{"tagesgeld_brutto":75.00,"tagesgeld_aufwand":68.18,"tagesgeld_vorsteuer":6.82,"naechtigung_brutto":142.50,"naechtigung_aufwand":129.55,"naechtigung_vorsteuer":12.95,"absetzbar_kassa":69.80,"absetzbar_aufwand_20":26.67,"absetzbar_aufwand_10":34.36,"absetzbar_vorsteuer":8.77,"nicht_absetzbar_kassa":69.80,"nicht_absetzbar_aufwand_20":26.67,"nicht_absetzbar_aufwand_10":34.36,"nicht_absetzbar_vorsteuer":8.77}},"fall_5":{"buchung":"7345 Kilometergelder Inland an 2700 Kassa","betrag":423.50},"fall_6":{"buchung":"7320 Pkw- und Kombi-Betriebsaufwand an 3190 Verbindlichkeiten Debitkarten","betrag":148.80},"fall_7":{"buchung":"7326 Parkgebühren, Straßenmaut Pkw u. Kombis an 2700 Kassa","betrag":103.80}} | H172: null | I172: Correct journal entry structure required (proper accounts and debit/credit logic). Correct VAT split and input tax amounts required where applicable. Correct treatment of non-deductible vs. deductible business entertainment required. Correct classification of asset acquisition, operating expenses, and travel costs required. Exact match required for all final numeric results; minor rounding deviations within tolerance allowed. Intermediate values must be economically and mathematically correct. | N172: UGB | O172: 2025 | P172: financial_accounting | R172: Journal entry preparation; VAT input tax handling; Fixed asset acquisition accounting; Travel expense accounting (per diem and lodging); Business entertainment expense split (deductible vs. non-deductible); Mileage allowance accounting; Card payment accounting (credit/debit); Numerical accuracy | S172: secondary_vocational_school | U172: batch_import | V172: batch_admin | W172: 1 | X172: 2026-04-29 16:11:41.969273 | Y172: Manuel Kaburek | Z172: approved
A173: 171 | B173: 12030864_0010 | C173: Die Mirabell AG (Salzburg) hat folgende Geschäftsfälle zu verbuchen: Eine Bahnfahrt von Salzburg Hauptbahnhof nach Graz Hauptbahnhof wird bar bezahlt. Der Bruttobetrag beträgt EUR 48,60 (inkl. 10 % USt). Eine Taxifahrt in Graz zu einem Kunden und zurück zum Hauptbahnhof wird bar bezahlt. Der Bruttobetrag beträgt EUR 8,40 (inkl. 10 % USt). Für einen Firmen-Pkw wird Benzin um EUR 44,00 (inkl. 20 % USt) gekauft und mit der Firmendebitkarte bezahlt. Ein Angestellter macht für eine Dienstreise Tagesgeld gemäß EStG in Höhe von EUR 90,00 sowie Nächtigungskosten laut Beleg in Höhe von EUR 154,50 geltend. Zusätzlich findet ein Abendessen mit einem Kunden statt (gesamt EUR 122,00; davon EUR 26,60 zu 20 % USt und EUR 95,40 zu 10 % USt). Das Abendessen ist nur zu 50 % als Betriebsausgabe absetzbar. Parkgebühren für einen Firmen-Pkw in Höhe von EUR 17,50 werden mit der Firmenkreditkarte bezahlt. Ein Firmen-Pkw wird vom Autohaus Wipplinger KG (Konto 33200) um EUR 27.500,00 (inkl. 20 % USt und NoVA) gegen spätere Bezahlung gekauft. Eine Reparatur des Firmen-Pkw wird bar bezahlt (EUR 310,00 + EUR 62,00 USt = EUR 372,00). Aufgabenstellung: Stellen Sie die Buchungssätze auf. | D173: journal_entry | E173: journal_entry | F173: journal_entry | G173: {"fall_1":{"buchung":"7340 Bahn- und Autobuskosten Inlandsreisen, 2500 Vorsteuer an 2700 Kassa","betrag":[44.18,4.42,48.60]},"fall_2":{"buchung":"7342 Taxikosten Inlandsreisen, 2500 Vorsteuer an 2700 Kassa","betrag":[7.64,0.76,8.40]},"fall_3":{"buchung":"7320 Pkw- und Kombi-Betriebsaufwand an 3190 Verbindlichkeiten Debitkarten","betrag":44.00},"fall_4":{"buchung":["7360 Tagesgelder Inland, 2500 Vorsteuer an 2700 Kassa","7364 Nächtigungsgelder Inland, 2500 Vorsteuer an 2700 Kassa","7660 Aufwand für Geschäftsanbahnung 20 %, 7661 Aufwand für Geschäftsanbahnung 10 %, 2500 Vorsteuer an 2700 Kassa","7663 Nicht absetzbarer Aufw. f. Geschäftsanb. 20 %, 7664 Nicht absetzbarer Aufw. f. Geschäftsanb. 10 %, 2500 Vorsteuer an 2700 Kassa"],"betrag":{"tagesgeld_kassa":75.00,"tagesgeld_aufwand":68.18,"tagesgeld_vorsteuer":6.82,"naechtigung_kassa":154.50,"naechtigung_aufwand":140.45,"naechtigung_vorsteuer":14.05,"essen_absetzbar_kassa":61.00,"essen_absetzbar_aufwand_20":11.08,"essen_absetzbar_aufwand_10":43.36,"essen_absetzbar_vorsteuer":6.56,"essen_nicht_absetzbar_kassa":61.00,"essen_nicht_absetzbar_aufwand_20":11.08,"essen_nicht_absetzbar_aufwand_10":43.36,"essen_nicht_absetzbar_vorsteuer":6.56}},"fall_5":{"buchung":"7326 Parkgebühren, Straßenmaut Pkw u. Kombis an 3180 Verbindlichkeiten Kreditkarten","betrag":17.50},"fall_6":{"buchung":"0630 Pkw und Kombis an 33200 Autohaus Wipplinger KG","betrag":27500.00},"fall_7":{"buchung":"7320 Pkw- und Kombi-Betriebsaufwand an 2700 Kassa","betrag":372.00}} | H173: null | I173: Exact match required for all final numeric results. Intermediate values must be economically and mathematically correct. Correct application of VAT rules (10%/20%) and deductible vs. non-deductible treatment required. Correct selection of accounts and debit/credit logic required. Minor rounding deviations within tolerance allowed. Follow-up errors are considered if calculation logic is consistent. | N173: UGB | O173: 2025 | P173: financial_accounting | R173: Journal entry preparation; VAT input tax calculation and posting (10% / 20%); Travel expense accounting (per diem and lodging); Business entertainment expense split (deductible vs. non-deductible) with VAT handling; Card payment accounting (debit/credit); Fixed asset acquisition accounting (vehicle purchase); Operating expense classification; Numerical accuracy | S173: secondary_vocational_school | U173: batch_import | V173: batch_admin | W173: 1 | X173: 2026-04-29 16:12:47.152174 | Y173: Manuel Kaburek | Z173: approved
A174: 172 | B174: 12030864_0011 | C174: Tamara Reichelt (Kfz-Zulassungssachbearbeiterin) erhält ein monatliches Gehalt von € 2.790,–. Im Abrechnungsmonat März werden zusätzlich 21 Überstunden aus dem Februar mit einem Überstundenzuschlag von 50 % berücksichtigt. Der Überstundenteiler beträgt 1/143. Es besteht kein Anspruch auf FABO Plus und kein Anspruch auf AV(E)AB. Folgende steuerliche Absetzbeträge sind zu berücksichtigen: Freibetrag: € 25,– pro Monat Pendlerpauschale: € 113,– pro Monat Pendlereuro für 57 km (einfache Fahrtstrecke) Der Sozialversicherungsbeitrag beträgt 18,07 %. Berechnen Sie: Gesamtbruttogehalt Sozialversicherung Lohnsteuer Auszahlungsbetrag | D174: open_text | E174: calculation | F174: open_text | G174: { "person": "Tamara Reichelt", "profession": "Kfz-Zulassungssachbearbeiterin", "base_salary": 2790.00, "overtime_hours": 21, "overtime_divisor": 143, "overtime_base_rate": 19.51, "overtime_total": 409.71, "overtime_tax_free": 175.68, "overtime_taxable": 29.28, "gross_total": 3404.67, "social_security_rate_percent": 18.07, "social_security_amount": 615.22, "taxable_base_before_tax": 2475.77, "income_tax": 287.41, "net_payment": 2502.04, "allowances": { "tax_allowance": 25.00, "commuter_allowance": 113.00, "pendler_euro_km": 57 } } | H174: null | I174: Exact match required for all final numeric results. Intermediate calculations (overtime rate, gross salary, tax base) must be economically and mathematically correct. Correct separation of tax-free and taxable overtime required. Proper application of contribution rates and tax rules mandatory. Minor rounding deviations within tolerance allowed. Follow-up errors are considered if calculation logic is consistent. | N174: UGB | O174: 2025 | P174: financial_accounting | R174: Payroll accounting Overtime calculation (including premium rate application) Separation of tax-free and taxable overtime components Social security contribution calculation Income tax base determination Application of tax allowances and commuter allowances Net salary computation Numerical accuracy | S174: secondary_vocational_school | U174: batch_import | V174: batch_admin | W174: 1 | X174: 2026-04-29 16:14:55.229473 | Y174: Manuel Kaburek | Z174: approved
A175: 173 | B175: 12030864_0012 | C175: Patrick Weihrauch (EDV-Analytiker) erhält ein monatliches Bruttogehalt von € 6.560,–. Er hat Anspruch auf den Familienbonus Plus (voller Bonus) für ein minderjähriges Kind. Es besteht kein Anspruch auf AV(E)AB. Ein monatlicher Freibetrag von € 40,– ist zu berücksichtigen. Dienstantritt: 19. April 2025 Abrechnung für April (Aliquotierung erforderlich). Der Sozialversicherungsbeitrag beträgt 18,07 %. Berechnen Sie: aliquotes Bruttogehalt Sozialversicherung Lohnsteuer Auszahlungsbetrag | D175: open_text | E175: calculation | F175: open_text | G175: { "person": "Patrick Weihrauch", "profession": "EDV-Analytiker", "monthly_salary": 6560.00, "employment_start": "2025-04-19", "payroll_month": "April 2025", "aliquot_days": 12, "aliquot_gross_salary": 2624.00, "social_security_rate_percent": 18.07, "social_security_amount": 466.21, "tax_allowance": 40.00, "family_bonus_plus_full": true, "children_minor": 1, "taxable_income_base": 2141.79, "income_tax": 491.76, "net_payment": 1666.03 } | H175: null | I175: Exact match required for all final numeric results. Correct aliquot salary calculation based on employment start date required. Intermediate values (gross, social security, tax base) must be economically and mathematically correct. Proper application of Family Bonus Plus and tax allowance mandatory. Minor rounding deviations within tolerance allowed. Follow-up errors are considered if calculation logic is consistent. | N175: austrian_tax_law | O175: 2025 | P175: financial_accounting | R175: Payroll accounting Salary proration (aliquot calculation based on entry date) Social security contribution calculation Income tax base determination Application of tax allowance Application of Family Bonus Plus Net salary computation Numerical accuracy | S175: secondary_vocational_school | U175: batch_import | V175: batch_admin | W175: 1 | X175: 2026-04-29 16:16:14.223570 | Y175: Manuel Kaburek | Z175: approved
... A214: 212 | B214: 12030864_0051 | C214: Ein land- und forstwirtschaftlicher Betrieb (Angelika und Peter Kern) rechnet den Lohn für den Traktorführer Ferdinand Haberl für August ab. Gegeben sind: Bruttolohn: 1.940,00 € Sozialversicherung Arbeitnehmer: 307,88 € Lohnsteuer: 122,70 € Sozialversicherung Arbeitgeber: 429,90 € Dienstgeberbeitrag: 73,72 € Kommunalsteuer: 58,20 € Aufgaben: a) Ermitteln Sie den Auszahlungsbetrag des Arbeitnehmers. b) Ermitteln Sie die an ÖGK, Finanzamt und Gemeinde abzuführenden Beträge. c) Buchen Sie die Lohnabrechnung zum 31.8. d) Buchen Sie die Auszahlung des Nettolohns. e) Buchen Sie die Überweisung an das Finanzamt. f) Buchen Sie die Überweisung an die Sozialversicherung (ÖGK). g) Buchen Sie die Überweisung an die Gemeinde. h) Ermitteln Sie den Gesamtaufwand des Monats August sowie den jährlichen Gesamtaufwand und berechnen Sie die Kosten pro Arbeitsstunde (1.703,2 Stunden jährlich). | D214: open_text | E214: journal_entry | F214: open_text | G214: { "auszahlungsbetrag": { "bruttolohn": 1940.00, "sv_dienstnehmer": 307.88, "lohnsteuer": 122.70, "nettolohn": 1509.42 }, "abgaben": { "oegk": { "sv_dienstnehmer": 307.88, "sv_dienstgeber": 429.90, "summe": 737.78 }, "finanzamt": { "lohnsteuer": 122.70, "dienstgeberbeitrag": 73.72, "ust_zahllast": 2482.15, "summe": 2678.57 }, "gemeinde": { "kommunalsteuer": 58.20 } }, "buchungen": [ { "datum": "31.08.", "konto_soll": "6000 Löhne", "betrag": 1940.00, "konto_haben": [ { "konto": "3540 Verb. Finanzamt", "betrag": 122.70 }, { "konto": "3600 Verb. ÖGK", "betrag": 307.88 }, { "konto": "3685 Verb. Mitarbeiter", "betrag": 1509.42 } ] }, { "datum": "31.08.", "konto_soll": "6500 Gesetzlicher Sozialaufwand", "betrag": 429.90, "konto_haben": [ { "konto": "3600 Verb. ÖGK", "betrag": 429.90 } ] }, { "datum": "31.08.", "konto_soll": "6570 Dienstgeberbeitrag", "betrag": 73.72, "konto_haben": [ { "konto": "3540 Verb. Finanzamt", "betrag": 73.72 } ] }, { "datum": "31.08.", "konto_soll": "6611 Kommunalsteuer", "betrag": 58.20, "konto_haben": [ { "konto": "3610 Verb. Gemeinde", "betrag": 58.20 } ] }, { "datum": "31.08.", "konto_soll": "3685 Verb. Mitarbeiter", "betrag": 1509.42, "konto_haben": [ { "konto": "2800 Bank", "betrag": 1509.42 } ] }, { "datum": "15.09.", "konto_soll": [ { "konto": "3540 Verb. Finanzamt", "betrag": 196.42 }, { "konto": "3520 USt-Zahllast", "betrag": 2482.15 } ], "gesamtbetrag": 2678.57, "konto_haben": [ { "konto": "2800 Bank", "betrag": 2678.57 } ] }, { "datum": "15.09.", "konto_soll": "3600 Verb. ÖGK", "betrag": 737.78, "konto_haben": [ { "konto": "2800 Bank", "betrag": 737.78 } ] }, { "datum": "15.09.", "konto_soll": "3610 Verb. Gemeinde", "betrag": 58.20, "konto_haben": [ { "konto": "2800 Bank", "betrag": 58.20 } ] } ], "gesamtaufwand": { "monat_august": 2501.82, "jahr": 35025.48, "jahresstunden": 1703.2, "kosten_pro_stunde": 20.56 } } | H214: null | I214: Net salary correctly calculated (1,509.42 €). All statutory contributions correctly identified and aggregated. Clear distinction between employee and employer contributions. Payroll accrual entry complete and balanced. Liabilities correctly recognized. Net salary payment correctly clears employee liability. Tax payment correctly includes wage tax, employer contribution, and VAT liability. Social security and municipal payments correctly recorded. Total monthly and annual personnel costs correctly calculated. Hourly cost (20.56 €) correctly computed. Journal entries formally correct (debit/credit logic). | N214: austrian_tax_law | O214: 2025 | P214: financial_accounting | R214: gross_to_net_calculation employee_vs_employer_contribution_distinction payroll_accounting_double_entry liability_recognition multi_step_posting_sequence tax_payment_allocation social_security_payment_processing municipal_tax_booking expense_classification equity_effect_analysis annual_cost_extrapolation unit_cost_calculation structured_accounting_output | S214: secondary_vocational_school | U214: batch_import | V214: batch_admin | W214: 1 | X214: 2026-04-29 17:33:28.545949 | Y214: Manuel Kaburek | Z214: approved
A215: 213 | B215: 11830492_0001 | C215: Welche der folgenden Aussage/n zum Betriebsabrechnungsbogen (BAB) ist/sind richtig? | D215: multi_choice | E215: interpretation_of_law | F215: multi_choice | G215: A,E | H215: {"a": "Bei Besch\u00e4ftigungs\u00e4nderungen f\u00fchrt die Berechnung der Zuschlagss\u00e4tze im Betriebsabrechnungsbogen auf Basis der Vollkosten \u2013 im Vergleich zur Berechnung auf Basis der Teilkosten \u2013 zu verzerrten Ergebnissen.", "b": "Der Betriebsabrechnungsbogen baut auf dem Betriebs\u00fcberleitungsbogen auf und dient der Gliederung der angefallenen Kosten nach Kostenarten.", "c": "Bezugsgr\u00f6\u00dfen dienen als Basis f\u00fcr die Zurechnung der Kostenstelleneinzelkosten und der Kostenstellengemeinkosten auf die Kostentr\u00e4ger.", "d": "Im Zuge der innerbetrieblichen Leistungsverrechnung sind zuerst jene Kostenstellen umzulegen, die Leistungen nur an eine einzige andere Kostenstelle erbringen.", "e": "Stromkosten, die aus wirtschaftlichen Gr\u00fcnden nicht je Kostentr\u00e4ger erfasst werden, sind im Betriebsabrechnungsbogen als Gemeinkosten zu behandeln."} | I215: Exact set match required (A and E). Order irrelevant. Case-insensitive. No additional choices allowed. | N215: mixed_accounting_framework | O215: 2024 | P215: management_accounting | Q215: cost accounting | R215: cost accounting; operating statement form (Betriebsabrechnungsbogen); internal cost allocation | S215: professional_examinations | T215: Prüfung Oktober 2025, Beispiel 1, Rechtslage mit Stand 31.12.2024 | U215: batch_import | V215: batch_admin | W215: 1 | X215: 2026-04-29 17:34:06.396794 | Y215: Manuel Kaburek | Z215: approved
A216: 214 | B216: 11830492_0002 | C216: Welche der folgenden Aussage/n zur Unterscheidung zwischen Kosten und buchhalterischem Aufwand ist/sind richtig? | D216: multi_choice | E216: interpretation_of_law | F216: multi_choice | G216: A,C,E | H216: {"a": "Gew\u00e4hrleistungs- und Produkthaftungsrisiken stellen Beispiele f\u00fcr kalkulatorische Wagnisse dar.", "b": "Der kalkulatorische Unternehmerlohn ist ein Beispiel f\u00fcr neutrale Aufwendungen.", "c": "Die pagatorische Abschreibung wird im Betriebs\u00fcberleitungsbogen in eine kalkulatorische Abschreibung \u00fcbergeleitet.", "d": "Die kalkulatorische Abschreibung zeigt den rechnerischen Wert f\u00fcr die verbrauchsbedingte technische oder wirtschaftliche Wertminderung auf Basis der historischen Anschaffungskosten.", "e": "Aufwendungen aus einem Brandschaden stellen aufgrund der Au\u00dfergew\u00f6hnlichkeit dieses Gesch\u00e4ftsvorfalls niemals Grundkosten dar."} | I216: Exact set match required (A, C and E). Order irrelevant. Case-insensitive. No additional choices allowed. | N216: mixed_accounting_framework | O216: 2024 | P216: management_accounting | Q216: cost accounting | R216: cost accounting; distinction between costs and accounting expenses | S216: professional_examinations | T216: Prüfung Oktober 2025, Beispiel 2, Rechtslage mit Stand 31.12.2024 | U216: batch_import | V216: batch_admin | W216: 1 | X216: 2026-04-29 17:36:37.824389 | Y216: Manuel Kaburek | Z216: approved
A217: 215 | B217: 11830492_0003 | C217: Welche der folgenden Aussage/n zur Kostenabweichungsanalyse ist/sind richtig? | D217: multi_choice | E217: interpretation_of_law | F217: multi_choice | G217: A,B,E | H217: {"a": "Eine Erh\u00f6hung der Wiederbeschaffungspreise von Betriebsmitteln (wie zB Maschinen, Geb\u00e4ude udgl) stellt eine Preisabweichung bei der kalkulatorischen Abschreibung dar.", "b": "Die Besch\u00e4ftigungsabweichung bezeichnet die Fixkostenunterdeckung oder -\u00fcberdeckung, die sich aus einem Unter- oder \u00dcberschreiten der Planbesch\u00e4ftigung ergibt.", "c": "Die Ermittlung einer Preisabweichung ist nur zu variablen Kosten m\u00f6glich.", "d": "Wird bei einer Kostenabweichungsanalyse die gemischte Abweichung in der Verbrauchsabweichung abgebildet, f\u00fchrt jede Preiserh\u00f6hung von Produktionsfaktoren zwangsl\u00e4ufig auch zu einer Verbrauchsabweichung.", "e": "Der Besch\u00e4ftigungsgrad dr\u00fcckt das Verh\u00e4ltnis von Ist-Besch\u00e4ftigung zur Plan-Besch\u00e4ftigung aus."} | I217: Exact set match required (A, B and E). Order irrelevant. Case-insensitive. No additional choices allowed. | N217: mixed_accounting_framework | O217: 2024 | P217: management_accounting | Q217: cost planning | R217: cost planning; cost variance analysis | S217: professional_examinations | T217: Prüfung Oktober 2025, Beispiel 3, Rechtslage mit Stand 31.12.2024 | U217: batch_import | V217: batch_admin | W217: 1 | X217: 2026-04-29 17:37:38.624759 | Y217: Manuel Kaburek | Z217: approved
A218: 216 | B218: 11830492_0004 | C218: Welche der folgenden Aussage/n zur Kostenabweichungsanalyse ist/sind richtig? | D218: multi_choice | E218: interpretation_of_law | F218: multi_choice | G218: A,B,C | H218: {"a": "Ein ungeplanter Produktionsstillstand kann ein Grund f\u00fcr eine Intensit\u00e4tsabweichung sein.", "b": "Die Gesamtabweichung besteht aus der Verbrauchsabweichung und der Preisabweichung.", "c": "Die Verbrauchsabweichung zeigt den Mehr- oder Minderverbrauch an Betriebsmitteln.", "d": "Entsprechen die Ist-Preise den Plan-Preisen, kann es zwar zu keiner reinen Preisabweichung, sehr wohl aber zu einer gemischten Abweichung kommen.", "e": "Au\u00dfer im Fall von Zusatzkosten, muss bei der Kostenabweichungsanalyse der Ist-Verbrauch zu Ist-Preisen den Aufwendungen in der unternehmensrechtlichen Gewinn- und Verlustrechnung entsprechen."} | I218: Exact set match required (A, B and C). Order irrelevant. Case-insensitive. No additional choices allowed. | N218: mixed_accounting_framework | O218: 2024 | P218: management_accounting | Q218: cost planning | R218: cost planning; cost variance analysis | S218: professional_examinations | T218: Prüfung Oktober 2025, Beispiel 4, Rechtslage mit Stand 31.12.2024 | U218: batch_import | V218: batch_admin | W218: 1 | X218: 2026-04-29 17:38:05.173875 | Y218: Manuel Kaburek | Z218: approved
A219: 217 | B219: 11830492_0005 | C219: Welche der folgenden Aussage/n zur Budgetierung ist/sind richtig? | D219: multi_choice | E219: interpretation_of_law | F219: multi_choice | G219: E | H219: {"a": "Das Unternehmensbudget besteht aus Planbilanz, Finanzplan und Eigenkapitalver\u00e4nderungsrechnung.", "b": "Eine Erh\u00f6hung der Abschreibungen in der Plan-Gewinn- und Verlustrechnung zieht nur dann eine \u00c4nderung in der Plan-Bilanz nach sich, wenn es sich dabei um variable Kosten handelt.", "c": "Die K\u00f6rperschaftsteuer wird im Leistungsbudget einer GmbH nicht ber\u00fccksichtigt.", "d": "Das Leistungsbudget verwendet ausschlie\u00dflich kalkulatorische Gr\u00f6\u00dfen, die Plan-Gewinn- und Verlustrechnung hingegen ausschlie\u00dflich pagatorische Gr\u00f6\u00dfen.", "e": "Voraussetzung f\u00fcr die Erstellung des Leistungsbudgets ist die Trennung in fixe und variable Kosten."} | I219: Exact set match required (E). Order irrelevant. Case-insensitive. No additional choices allowed. | N219: mixed_accounting_framework | O219: 2024 | P219: management_accounting | Q219: cost planning | R219: cost planning; budgeting | S219: professional_examinations | T219: Prüfung Oktober 2025, Beispiel 5, Rechtslage mit Stand 31.12.2024 | U219: batch_import | V219: batch_admin | W219: 1 | X219: 2026-04-29 17:39:51.194353 | Y219: Manuel Kaburek | Z219: approved
A220: 218 | B220: 11830492_0006 | C220: Welche der folgenden Aussage/n zur Investitions- und Finanzierungsrechnung ist/sind richtig? | D220: multi_choice | E220: calculation | F220: multi_choice | G220: B,C | H220: {"a": "Der Barwert betr\u00e4gt 5.000 \u20ac, der Endwert 6.200 \u20ac. Daraus folgt, dass bei einer Laufzeit von drei Jahren bei der Endwertberechnung ein Zinssatz von 5,87 % p.a. ber\u00fccksichtigt wurde.", "b": "Der Barwert betr\u00e4gt 5.000 \u20ac, der Endwert 6.200 \u20ac. Daraus folgt, dass bei einer Laufzeit von drei Jahren bei der Endwertberechnung ein Zinssatz von 7,43 % p.a. ber\u00fccksichtigt wurde.", "c": "Wenn Barwert und Endwert unver\u00e4ndert bleiben, aber die Laufzeit k\u00fcrzer wird, dann erh\u00f6ht sich der interne Zinssatz.", "d": "Den Kapitalwert erh\u00e4lt man, wenn man von der Summe der Endwerte der zuk\u00fcnftigen Cash Flows die Anschaffungskosten in Abzug bringt."} | I220: Exact set match required (B and C). Order irrelevant. Case-insensitive. No additional choices allowed. | N220: mixed_accounting_framework | O220: 2024 | P220: management_accounting | Q220: investment/financing calculation | R220: investment/financing calculation; net present value; internal rate of return | S220: professional_examinations | T220: Prüfung Oktober 2025, Beispiel 6, Rechtslage mit Stand 31.12.2024 | U220: batch_import | V220: batch_admin | W220: 1 | X220: 2026-04-29 17:40:56.905873 | Y220: Manuel Kaburek | Z220: approved
A221: 219 | B221: 11830492_0007 | C221: Ein Anleger kauft am 01.01.2026 eine Wohnung zu Vermietungszwecken, wobei er über 10 Jahre mit jährlichen nachschüssigen Cash Flows von 25.000 € rechnet. Hinweis: Steuern sind vereinfachend zu vernachlässigen. Aufgabenstellung: Wie hoch ist der Barwert dieser Cash Flows am 01.01.2026, wenn der Anleger von einer konstanten Verzinsung von 10 % ausgeht? | D221: open_numeric | E221: calculation | F221: open_numeric | G221: Barwert: 25.000*((1,1^10-1)/(1,1^10-0,1))=153.614,18 | H221: null | I221: Answer must contain: (1) Barwert = 153.614,18 | N221: mixed_accounting_framework | O221: 2024 | P221: management_accounting | Q221: investment/financing calculation | R221: investment/financing calculation; present value calculation | S221: professional_examinations | T221: Prüfung Oktober 2025, Beispiel 7, Rechtslage mit Stand 31.12.2024 | U221: batch_import | V221: batch_admin | W221: 1 | X221: 2026-04-29 17:41:05.145255 | Y221: Manuel Kaburek | Z221: approved
A222: 220 | B222: 11830492_0008 | C222: Ermitteln Sie die Umschlagshäufigkeit und -dauer der Debitoren für das Geschäftsjahr 2024. Interpretieren Sie Ihr Ergebnis. | D222: open_numeric | E222: calculation | F222: open_numeric | G222: Umschlagshäufigkeit der Debitoren: 10,59; Umschlagsdauer der Debitoren: 34,48; Interpretation: Es vergehen durchschnittlich rund 35 Tage, bis die Kunden der Büromöbel-GmbH offene Forderungen bezahlen. Im Vergleich mit den vereinbarten Zahlungskonditionen zeigt sich, ob sich die Kunden im Durchschnitt an diese halten. Gegebenenfalls können Rückschlüsse auf das Mahnwesen gezogen werden. Der Anstieg der Forderungen im Vergleich zum Vorjahr sollte kritisch hinterfragt werden, insbesondere da auch die Vorräte zugenommen haben. Dies könnte eventuell auf Absatzprobleme hinweisen, gegebenenfalls auch auf die Einräumung längerer Zahlungsziele. | H222: null | I222: Answer must contain: (1) Umschlagshäufigkeit der Debitoren: 10,59, (2) Umschlagsdauer der Debitoren: 34,48, (3) durchschnittlich vergehen vergehen rund 35 Tage, bis die Kunden der Büromöbel-GmbH offene Forderungen bezahlen (4) Vergleich mit den Zahlungskonditionen zeigt sich, ob sich die Kunden im Durchschnitt an diese halten. (5) Rückschlüsse auf das Mahnwesen gezogen werden (6) Der Anstige der Forderungen sollte kristisch hinterfragt werden, da auch die Vorräte zugenommen haben (Hinweis für ein Absatzproblem). Semantische Übereinstimmung ausreichend. Minor wording deviations allowed. | L222: Umsatzerlös inkl Ust: 2.154.784*0,9*1,2+2.154.784*0,1=2.542.645,12; durschnittlicher Forderungsbestand L+L: (174.752+209.113+49.775,7+46.711,6)/2=240.176,15; Umschlagshäufigkeit der Debitoren: 10,59; Umschlagsdauer der Debitoren (in Tagen): 34,48 | M222: C:\Users\dhoellmu\OneDrive - WU Wien\Dokumente\AccountingBench\backend\uploads\Jahresabschlussanalyse_102025.pdf | N222: mixed_accounting_framework | O222: 2024 | P222: management_accounting | Q222: financial statements analysis | R222: financial statements analysis; turnover rate debitors | S222: professional_examinations | T222: Prüfung Oktober 2025, Beispiel 8, Rechtslage mit Stand 31.12.2024 | U222: batch_import | V222: batch_admin | W222: 1 | X222: 2026-04-29 17:41:54.060972 | Y222: Manuel Kaburek | Z222: approved
A223: 221 | B223: 11830492_0009 | C223: Berechnen Sie die Gesamtkapitalrentabilität nach KFS/BW 3 für das Geschäftsjahr 2024. Erläutern Sie den Leverageeffekt. Was sind wesentliche Einschränkungen des Leverageeffekts? Ermitteln Sie den kritischen Fremdkapitalzinssatz, der zu einer Umkehrung des Leverageeffekts bei der Büromöbel-GmbH führt. | D223: open_numeric | E223: calculation | F223: open_numeric | G223: Gesamtkapitalrentabilität: 150.049/1.860.239= 8,07%; Der Leverageeffekt bezeichnet den Effekt, dass die Eigenkapitalrentabiliät bei steigender Verschuldung zunimmt, solange der Fremdkapitalzinssatz unter der Gesamtkapitalrentabilität liegt. Grenzen der Aussagekraft des Leverageeffekts liegen ua darin, dass mit der Aufnahme zusätzlicher Fremdmittel auch Aktivitäten des Unternehmens verbunden sein können, deren Rentabilität sich von den bisherigen (im Normalfall risikoärmeren) Tätigkeiten unterscheidet. Weiters bewirkt die Aufnahme von zusätzlichem Fremdkapital eine Erhöhung des Verschuldungsgrades und damit des Risikos des Fremdkapitalgebers, der- bis zur Frage der Zurverfügungstellung zusätzlichen Fremdkapitals - zumindest höhere Fremdkapitalzinsen in Rechnung stellen wird. Der kritische Fremdkapitalzinssatz, der bei der Büromöbel-GmbH zu einer Umkehrung des Leverageeffekts führt, liegt bei 8,07%. Solange Fremdkapital zu einem Zinssatz aufgenommen werden kann, der unter 8,07% liegt, führt die zusätzliche Aufnahme von Fremdkapital zu einer Steigerung der Eigenkapitalrentabilität. | H223: null | I223: Answer must contain: (1) Gesamtkapitalrentabilität= 8,07%, (2) Leverageeffekt: Eigenkapitalrentabiliät bei steigender Verschuldung zunimmt, solange der Fremdkapitalzinssatz unter der Gesamtkapitalrentabilität liegt. (3) Grenzen der Aussagekraft des Leverageeffekts: mit der Aufnahme zusätzlicher Fremdmittel auch Aktivitäten des Unternehmens verbunden sein können, deren Rentabilität sich von den bisherigen (im Normalfall risikoärmeren) Tätigkeiten unterscheidet. (4) Aufnahme von zusätzlichem Fremdkapital: Erhöhung des Verschuldungsgrades, höhere Fremdkapitalzinsen, (5) Der kritische Fremdkapitalzinssatz: 8,07%, (6) Fremdkapital zu einem Zinssatz aufgenommen werden kann, der unter 8,07% liegt, führt die zusätzliche Aufnahme von Fremdkapital zu einer Steigerung der Eigenkapitalrentabilität. Semantische Übereinstimmung ausreichend. Minor wording deviations allowed | M223: C:\Users\dhoellmu\OneDrive - WU Wien\Dokumente\AccountingBench\backend\uploads\Jahresabschlussanalyse_102025.pdf | N223: mixed_accounting_framework | O223: 2024 | P223: management_accounting | Q223: financial statements analysis | R223: financial statements analysis; return on investment; everage effect | S223: professional_examinations | T223: Prüfung Oktober 2025, Beispiel 8, Rechtslage mit Stand 31.12.2024 | U223: batch_import | V223: batch_admin | W223: 1 | X223: 2026-04-29 17:42:36.926766 | Y223: Manuel Kaburek | Z223: approved
A224: 222 | B224: 11830492_0010 | C224: Ist die Büromöbel-GmbH fristenkongruent finanziert? Stützen Sie Ihre Beurteilung dabei auf die Kennzahlen Anlagendeckungsgrad 1 sowie den Anlagendeckungsgrad 2 und interpretieren Sie Ihr Ergebnis. | D224: open_numeric | E224: calculation | F224: open_numeric | G224: Bereinigtes Eigenkapital = 491.396,25; bereinigtes Anlagevermögen = 1.287.593,00; Anlagendeckungsgrad 1 = 38,16%; bereinigtes langfristiges Fremdkapital = 1.057.506,25; Anlagendeckungsgrad 2 = 120,29%; Interpretation Anlagendeckungsgrad 1: Der Anlagendeckungsgrad zeigt, inwieweit das Anlagevermögen, das dem Unternehmen dauerhaft zur Verfügung stehen soll, durch Eigenkapital gedeckt ist. Ein Deckungsgrad von 38,16% zeigt, dass mehr als die Hälfte des Anlagevermögens mittels Fremdkapital finanziert ist. Im Sinne einer fristenkongruenten Finanzierung wäre zu fordern, dass diese mit langfristig zur Verfügung stehendem Fremdkapital erfolgt.; Interpretation Anlagendeckungsgrad 2: Ein Anlagendeckungsgrad 2 iHv rund 120% zeigt an, dass dauerhaft dem Unternehmen zur Verfügung stehendes Anlagevermögen auch langfristig, und zwar mittels Eigenkapital und langfristigem Fremdkapital, finanziert ist. Insofern ist von einer fristenkongruenten Finanzierung auszugehen und ein kurzfristiger Liquiditätsengpass ist nicht zu erwarten. | H224: null | I224: Answer must contain: (1) Bereinigtes Eigenkapital = 491.396,25 (2) bereinigtes Anlagevermögen = 1.287.593,00 (3) Anlagendeckungsgrad 1 = 38,16% (4) bereinigtes langfristiges Fremdkapital = 1.057.506,25 (5) Anlagendeckungsgrad 2 = 120,29% (6) Interpretation Anlagendeckungsgrad 1: Der Anlagendeckungsgrad zeigt, inwieweit das Anlagevermögen, das dem Unternehmen dauerhaft zur Verfügung stehen soll, durch Eigenkapital gedeckt ist. Ein Deckungsgrad von 38,16% zeigt, dass mehr als die Hälfte des Anlagevermögens mittels Fremdkapital finanziert ist. Im Sinne einer fristenkongruenten Finanzierung wäre zu fordern, dass diese mit langfristig zur Verfügung stehendem Fremdkapital erfolgt. (7) Interpretation Anlagendeckungsgrad 2: Ein Anlagendeckungsgrad 2 iHv rund 120% zeigt an, dass dauerhaft dem Unternehmen zur Verfügung stehendes Anlagevermögen auch langfristig, und zwar mittels Eigenkapital und langfristigem Fremdkapital, finanziert ist. Insofern ist von einer fristenkongruenten Finanzierung auszugehen und ein kurzfristiger Liquiditätsengpass ist nicht zu erwarten. Semantische Übereinstimmung ausreichend. Minor wording deviations allowed | L224: bereinigtes Eigenkapital = Eigenkapital lt Bilanz + stille Reserven (nach Steuern) - aktive latente Steuern - geplante Gewinnausschüttung; bereinigtes Anlagevermögen = Anlagevermögen lt Bilanz + stille Reserven + Operating Leasing; Anlagendeckungsgrad 1 = 38,16%; bereinigtes lfr Fremdkapital = AbfertigungsRSt + PensionsRSt + sonstige RSt + passive latente Steuer + lfr Verbindlichkeiten + lfr Operating Leasing Verpflichtung; Anlagendeckungsgrad 2 = 120,29% | M224: C:\Users\dhoellmu\OneDrive - WU Wien\Dokumente\AccountingBench\backend\uploads\Jahresabschlussanalyse_102025.pdf | N224: mixed_accounting_framework | O224: 2024 | P224: management_accounting | Q224: financial statements analysis | R224: financial statements analysis; matching maturities of assets and liabilities; fixed asset coverage ratio 1 and 2 | S224: professional_examinations | T224: Prüfung Oktober 2025, Beispiel 8, Rechtslage mit Stand 31.12.2024 | U224: batch_import | V224: batch_admin | W224: 1 | X224: 2026-04-29 17:44:16.147944 | Y224: Manuel Kaburek | Z224: approved
A225: 223 | B225: 11830492_0011 | C225: { "Unternehmen": "Zuckersüß-GmbH", "Beschreibung": "Produziert hochwertige traditionelle Wiener Süßwaren", "Betriebsabrechnungsbogen": { "Kostenstellen": [ { "Name": "Mischerei", "Gemeinkosten": 100000, "Bezugsgröße": { "Bezeichnung": "Einkaufskosten Zutaten", "Wert": 500000 }, "ZS_VS": "20%" }, { "Name": "Gießerei", "Gemeinkosten": 300000, "Bezugsgröße": { "Bezeichnung": "Maschinenstunden", "Wert": 1000 }, "ZS_VS": 300 }, { "Name": "Veredelung", "Gemeinkosten": 600000, "Bezugsgröße": { "Bezeichnung": "Fertigungslöhne", "Wert": 400000 }, "ZS_VS": "150%" }, { "Name": "Qualitätskontrolle", "Gemeinkosten": 190000, "Bezugsgröße": { "Bezeichnung": "Herstellkosten", "Wert": null }, "ZS_VS": "10%" } ], "Fixkostenblock": 2000000 }, "Bereits_verplante_Kapazitäten": { "Kapazität_BZG": { "Mischerei": 400000, "Gießerei": 900, "Veredelung": 350000 }, "Summe_Erlöse_bereits_hereingenommene_Aufträge": 5000000 }, "Zusatzaufträge": [ { "Name": "Pfirsichspalten", "Kapazitätsbeanspruchung": { "Mischerei": 30000, "Gießerei": 0, "Veredelung": 10000 }, "Erlös": 100000 }, { "Name": "Krachmandeln", "Kapazitätsbeanspruchung": { "Mischerei": 20000, "Gießerei": 50, "Veredelung": 10000 }, "Erlös": 90000 }, { "Name": "Aschanti", "Kapazitätsbeanspruchung": { "Mischerei": 50000, "Gießerei": 80, "Veredelung": 20000 }, "Erlös": 150000 } ], "Aufgabenstellung": [ "1. Wie hoch ist das Periodenergebnis, wenn nur die bereits hereingenommenen Aufträge produziert werden?", "2. Sollen Zusatzaufträge hereingenommen werden und wenn ja, welche? Begründen Sie Ihre Entscheidung.", "3. Falls unter Aufgabenstellung 2 ein Zusatzauftrag abzulehnen ist: Berechnen Sie für jeden abgelehnten Zusatzauftrag den Mindesterlös, der für eine betriebswirtschaftlich optimale Hereinnahme erforderlich wäre." ] | D225: open_numeric | E225: calculation | F225: open_numeric | G225: Aufgabenstellung 1: Periodenergebnis: 1.212.500; Aufgabenstellung 2: Engpass in der Gießerei; Deckungsbeitrag Pfirsichspalten: 32.900, Deckungsbeitrag Krachmandeln: 19.600, Deckungsbeitrag Aschanit: 2.600; Betriebswirtschaftlich optimale Entscheidung: Hereinnnahme der beiden Aufträge 'Pfirsichspalten' und 'Krachmandeln', Ablehnung Auftrag 'Aschanti'. Begründung: Engpass nur in der Kostenstelle 'Gießerei'. Nachdem der Auftrag 'Pfirsichspalten' keine Kapazitäten in der Kostenstelle 'Gießerei' beansprucht, Auftrag 'Pfirsichspalten' annehmen, wenn dessen DB positiv ist. Aufträge 'Krachmandeln' und 'Aschanti' beanspruchen beide Gießerei-Kapazitäten➔ Auftrag mit höherem absoluten DB hereinnehmen.; Aufgabenstellung 3: Mindesterlös für Auftrag Aschanti 167.000 | H225: null | I225: Answer must contain: (1) Aufgabenstellung 1: Periodenergebnis: 1.212.500; (2) Aufgabenstellung 2: Engpass in der Gießerei; (3) Deckungsbeitrag Pfirsichspalten: 32.900, Deckungsbeitrag Krachmandeln: 19.600, Deckungsbeitrag Aschanit: 2.600; Betriebswirtschaftlich (4) optimale Entscheidung: Hereinnnahme der beiden Aufträge 'Pfirsichspalten' und 'Krachmandeln', Ablehnung Auftrag 'Aschanti'. (5) Begründung: Nachdem der Auftrag 'Pfirsichspalten' keine Kapazitäten in der Kostenstelle 'Gießerei' beansprucht, Auftrag 'Pfirsichspalten' annehmen, wenn dessen DB positiv ist. Aufträge 'Krachmandeln' und 'Aschanti' beanspruchen beide Gießerei-Kapazitäten, Auftrag mit höherem absoluten DB hereinnehmen.; (6) Aufgabenstellung 3: Mindesterlös für Auftrag Aschanti 167.000; nur bei Begründung: Semantische Übereinstimmung ausreichend. Explanation: Minor wording deviations allowed | L225: Aufgabenstellung 1: 1. Berechnung der variablen Selbstkosten mit Hilfer der ZS/VS laut Angabe; 2. Berechnung des Periodenergebnisses; Aufgabenstellung 2: 1. Prüfung des Engpasses; 2. Ermittlung der Deckungsbeiträge der Zusatzaufträge; 3. Begründung der wirtschaftlichen optimalen Entscheidung; Aufgabenstellung 3: variable Selbstkosten für Auftrag "Aschanti" + entgangener DB von Auftrag "Krachmandeln" = Mindesterlös für Auftrag "Aschanti" | N225: mixed_accounting_framework | O225: 2024 | P225: management_accounting | Q225: cost accounting | R225: cost accounting under a bottleneck constraint | S225: professional_examinations | T225: Prüfung Oktober 2025, Beispiel 9, Rechtslage mit Stand 31.12.2024 | U225: batch_import | V225: batch_admin | W225: 1 | X225: 2026-04-29 17:44:52.576482 | Y225: Manuel Kaburek | Z225: approved
A226: 224 | B226: 11830492_0012 | C226: { "Titel": "Daten zu variablen Plan- und Istpreisen", "Kostenarten": [ { "Bezeichnung": "Fertigungslöhne", "Einheit": "EUR", "Plan": 4000000, "Ist": null, "Abhängig_von": "Fertigungsstunden" }, { "Bezeichnung": "Hilfslöhne", "Einheit": "EUR", "Plan": 1000000, "Ist": null, "Abhängig_von": "Fertigungsstunden" }, { "Bezeichnung": "Fertigungsmaterial", "Einheit": "EUR", "Plan": 720000, "Ist": 660000, "Abhängig_von": "Ausbringungsmenge" }, { "Bezeichnung": "Kalkulatorische Abschreibung", "Einheit": "EUR", "Plan": 800000, "Ist": 608000, "Abhängig_von": "Ausbringungsmenge" } ], "Zusatzinformationen": { "Preisänderungen_in_Prozent": { "Löhne": { "Plan": 100, "Ist": 110, "Begründung": "Erhöhung der Löhne laut Kollektivvertrag wegen hoher Inflation" }, "Material": { "Plan": 100, "Ist": 90, "Begründung": "Weniger Materialabfall durch Wechsel zu einem Lieferanten mit höheren Qualitätsstandards" }, "Wiederbeschaffungspreise_Anlagevermögen": { "Plan": 100, "Ist": 80, "Begründung": "Niedrigere Anschaffungskosten aufgrund gesunkener Nachfrage am Weltmarkt" } }, "Fertigungsstunden": { "Plan": 40000, "Ist": 36000 }, "Ausbringungsmenge_Stueck": { "Plan": 2000000, "Ist": 1900000 } }, "Aufgabenstellung": [ "1. Ermitteln Sie die Lohnkosten auf Istkosten-Basis.", "2. Ermitteln Sie die Verbrauchs- und Preisabweichung auf Basis der variablen Kosten. Stellen Sie dabei eine allfällige gemischte Abweichung in der Preisabweichung dar." ] } | D226: open_numeric | E226: calculation | F226: open_numeric | G226: Aufgabenstellung 1: Beschäftigungsgrad abhängig von den Fertigungsstunden = 90%; Beschäftigungsgrad abhängig von der Ausbringungsmenge = 95%; IST-Kosten Fertigungslöhne = 3.960.000; IST-Kosten Hilfslöhne = 990.000,00; Aufgabenstellung 2: Fertigungslöhne: Verbrauchsabweichung = 0, Preisabweichung inkl gemischte Abweichung = -360.000; Hilfslöhne: Verbrauchsabweichung = 0, Preisabweichung inkl gemischte Abweichung = -90.000; Fertigungsmaterial: Verbrauchsabweichung = 68.400, Preisabweichung inkl gemischte Abweichung = -44.400; kalkulatorische Abschreibung: Verbrauchsabweichung = 0, Preisabweichung inkl gemischte Abweichung = 152.000; Verbrauchsabweichung gesamt = 68.400; Preisabweichung inkl gemischte Abweichung gesamt = -342.400 | H226: null | I226: Answer must contain: (1) Beschäftigungsgrad abhängig von den Fertigungsstunden = 90%, (2) Beschäftigungsgrad abhängig von der Ausbringungsmenge = 95%, (3) IST-Kosten Fertigungslöhne = 3.960.000, (4) IST-Kosten Hilfslöhne = 990.000,00, (5)Fertigungslöhne: Verbrauchsabweichung = 0, Preisabweichung inkl gemischte Abweichung = -360.000, (6) Hilfslöhne: Verbrauchsabweichung = 0, Preisabweichung inkl gemischte Abweichung = -90.000, (7) Fertigungsmaterial: Verbrauchsabweichung = 68.400, Preisabweichung inkl gemischte Abweichung = -44.400, (8) kalkulatorische Abschreibung: Verbrauchsabweichung = 0, Preisabweichung inkl gemischte Abweichung = 152.000, (9) Verbrauchsabweichung gesamt = 68.400; Preisabweichung inkl gemischte Abweichung gesamt = -342.400 | L226: Beschäftigungsgrad ermitteln; IST-Kosten von Fertigungslöhne und Hilfslöhne berechnen, danach PM zu PP PLAN (lst-BG), VA, IM zu PP IST (zu PP) und PA inkl gem Abw IST (zu IP) für Fertigungslöhne, Hilflöhne, Fertigungsmaterial und kalkulatorische Abschreibung ermitteln | N226: mixed_accounting_framework | O226: 2024 | P226: management_accounting | Q226: cost planning | R226: cost planning, variance analysis, consumption and price variance | S226: professional_examinations | T226: Prüfung Oktober 2025, Beispiel 10, Rechtslage mit Stand 31.12.2024 | U226: batch_import | V226: batch_admin | W226: 1 | X226: 2026-04-29 17:45:30.661642 | Y226: Manuel Kaburek | Z226: approved
A227: 225 | B227: 11830492_0013 | C227: { "investment": { "type": "Erweiterungsinvestition", "production_machine": { "acquisition_date": "2025-12-30", "acquisition_cost": { "value": 1980000.00, "currency": "EUR" }, "financing": { "equity_percentage": 100 }, "start_of_operation": "2025-12-30", "useful_life_years": 5, "depreciation_method": "linear", "liquidation_value_2029": { "value": 50000.00, "currency": "EUR" } }, "tax": { "corporate_tax_rate": 23, "minimum_corporate_tax_considered": false }, "discount_rate": { "alternative_return_percent": 7.5 } }, "revenues_and_costs": { "production": { "increase_units": 5000, "old_production_units": 10000 }, "sales_price_per_unit": { "at_10000_units": { "value": 230.00, "currency": "EUR", "constant": true }, "at_15000_units": { "value": 220.00, "currency": "EUR", "constant": true } }, "costs_per_unit": { "labor_year_1": { "value": 49.00, "currency": "EUR" }, "labor_increase_percent_per_year": 3, "material_year_1": { "value": 21.00, "currency": "EUR" }, "material_increase_percent_per_year": 4, "other_costs": { "value": 3.90, "currency": "EUR", "constant": true } }, "maintenance_cost_per_year": { "value": 5000.00, "currency": "EUR", "constant": true, "payment_date": "06-30" } }, "payment_notes": { "year_end_payments_except_maintenance": true, "cash_flows_before_depreciation": true }, "without_investment_tax_results": { "2025": 10000.00, "2026": -50000.00, "2027": 75000.00, "2028": 150000.00, "2029": 150000.00, "currency": "EUR" }, "task": { "type": "Open Numeric", "description": "Kapitalwert der Erweiterungsinvestition unter Berücksichtigung von Steuern zum 31.12.2025 berechnen." } } | D227: open_numeric | E227: calculation | F227: open_numeric | G227: Alternativrendite nach Steuern: 5,775% p.a effektiv; (DB Produktion Erweiterung von 5.000 Stk (ohne Preisminderung Altproduktion): 2026: 730.500; 2027: 718.950; 2028: 707.011,50; 2029: 694.671,17); (Änderung DB: 2026: 630.500; 2027: 618.950; 2028: 607.011,50; 2029: 594.671,17); (KöSt Gesamtunternehmen VOR Berücksichtigung der Erweiterungsinvestition: 2025: -2.300; 2026: 0; 2027: -5.750; 2028: -34.500; 2029: -34.500); (KöSt Gesamtunternehmen NACH Berücksichtigung der Erweiterungsinvestition: 2025: 0; 2026: -10.321,25; 2027: -32.102,25; 2028: -81.882,65; 2029: -45.004,37); (Veränderung KöSt: 2025: 2.300; 2026: -10.321,25; 2027: -26.352,25; 2028: -47.382,65; 2029: -10.504,37); (Cash Flow: 31.12.2025: -1.977.700; 30.6.2026: -5.000; 31.12.2026: 620.178,75; 30.06.2027: -5.000; 31.12.2027: 592.597,75; 30.06.2028: -5.000; 31.12.2028: 559.628,86; 30.06.2029: -5.000; 31.12.2029: 634.166,80); Kapitalwert: 99.851,17 | H227: null | I227: Answer must contain: (1) Alternativrendite nach Steuern: 5,775% p.a effektiv; (2) (DB Produktion Erweiterung von 5.000 Stk (ohne Preisminderung Altproduktion): 2026: 730.500; 2027: 718.950; 2028: 707.011,50; 2029: 694.671,17); (3) (Änderung DB: 2026: 630.500; 2027: 618.950; 2028: 607.011,50; 2029: 594.671,17); (4)(KöSt Gesamtunternehmen VOR Berücksichtigung der Erweiterungsinvestition: 2025: -2.300; 2026: 0; 2027: -5.750; 2028: -34.500; 2029: -34.500); (5) (KöSt Gesamtunternehmen NACH Berücksichtigung der Erweiterungsinvestition: 2025: 0; 2026: -10.321,25; 2027: -32.102,25; 2028: -81.882,65; 2029: -45.004,37); (6) (Veränderung KöSt: 2025: 2.300; 2026: -10.321,25; 2027: -26.352,25; 2028: -47.382,65; 2029: -10.504,37); (7) (Cash Flow: 31.12.2025: -1.977.700; 30.6.2026: -5.000; 31.12.2026: 620.178,75; 30.06.2027: -5.000; 31.12.2027: 592.597,75; 30.06.2028: -5.000; 31.12.2028: 559.628,86; 30.06.2029: -5.000; 31.12.2029: 634.166,80); (8) Kapitalwert: 99.851,17 | L227: 1. Berechnung DB/Stk: Umsatzerlös/Stk -Lohnnebenkosten/Stk - Materialkosten/Stk - sonstige Kosten/Stk; 2. Änderung DB = DB/Stk * 5.000 Stk - Preisminderung Altproduktion; 3. Berechnung Köst vor Berücksichtigung der Erweiterungsinvestition (2027 Verlustvortrag berücksichtigen); 4. Berechnung Köst nach Berücksichtigung der Erweiterungsinvestition (2026 und 2027 Verlustvortrag berücksichtigen); 5. Berechnung Veränderung Köst; 6. Cashflow berechnen bestehend aus Anschaffungsauszahlung, Liquidationserlös, DB Veränderung, Wartung, Veränderung KöSt | N227: mixed_accounting_framework | O227: 2024 | P227: management_accounting | Q227: investment/financing calculation | R227: investment/financing calculation, calculation net present value of the expansion investment (incl taxes) | S227: professional_examinations | T227: Prüfung Oktober 2025, Beispiel 11, Rechtslage mit Stand 31.12.2024 | U227: batch_import | V227: batch_admin | W227: 1 | X227: 2026-04-29 17:45:53.129747 | Y227: Manuel Kaburek | Z227: approved
A228: 226 | B228: 11830492_0014 | C228: { "company": "B2B7-GmbH", "valuation_date": "2025-12-31", "general_parameters": { "cost_of_debt_percent": 5.0, "market_return_percent": 9.0, "risk_free_rate_percent": 2.3, "beta_unlevered": 0.7, "corporate_tax_rate_percent": 23.0, "debt_ratio_percent": 40.0, "equity_ratio_percent": 60.0, "sustainable_free_cashflow_from_2029": { "value": 78465.00, "currency": "EUR" }, "terminal_growth_rate_percent": 0.0 }, "detailed_planning_phase": { "2026": { "revenues": 1195000.00, "asset_disposals": { "proceeds": 11000.00, "book_value": -10000.00, "gain": 1000.00 }, "material_costs": 515000.00, "labor_costs": 257500.00, "admin_distribution_costs": 163000.00, "depreciation": 170000.00 }, "2027": { "revenues": 1250000.00, "asset_disposals": { "proceeds": 9500.00, "book_value": -8000.00, "gain": 1500.00 }, "material_costs": 525500.00, "labor_costs": 265300.00, "admin_distribution_costs": 170500.00, "depreciation": 180000.00 }, "2028": { "revenues": 1350500.00, "material_costs": 575800.00, "labor_costs": 310400.00, "admin_distribution_costs": 199900.00, "depreciation": 190000.00 } }, "additional_planning_data": { "2026": { "dividends": 50000.00, "investments": 175000.00, "increase_inventory": 10500.00, "increase_receivables": 9000.00, "increase_provisions": 1520.00, "increase_liabilities": 12900.00 }, "2027": { "dividends": 45000.00, "investments": 160000.00, "increase_inventory": 14000.00, "increase_receivables": 13000.00, "increase_provisions": 1900.00, "increase_liabilities": 11100.00 }, "2028": { "dividends": 40000.00, "investments": 160000.00, "increase_inventory": 13000.00, "increase_receivables": 12000.00, "increase_provisions": 2200.00, "increase_liabilities": 13100.00 } }, "debt_development": { "2025": 440661.30, "2026": 444458.78, "2027": 436829.32, "2028": 437158.47, "2029": 437158.47, "currency": "EUR", "note": "Debt levels constant from end of 2028 onward" }, "assumptions": [ "Beta conversion according to Modigliani/Miller (Hamada formula) without debt beta.", "Full distribution of cash flows assumed.", "No legal distribution restrictions.", "Round cost of equity and WACC to two decimal places." ], "tasks": [ { "task_number": 1, "description": "Calculate market value of total capital and equity as of 31.12.2025 using an Entity Approach.", "task_format": "Open Numeric" }, { "task_number": 2, "description": "Calculate market value of equity using an Equity Approach based on given debt levels.", "task_format": "Open Numeric" } ] } | D228: open_numeric | E228: calculation | F228: open_numeric | G228: Aufgabenstellung 1: Beta Faktor verschuldet: 1,06; Zinssatz(EK) verschuldet gerundet: 9,4%; WACC gerundet: 7,18%; (NOPLAT: 2026: 69.685; 2027: 84.854; 2028: 57.288); (Free Cash Flow: 2026: 69.605; 2027: 98.854; 2028: 77.588); Barwert ewige Rente: 2028: 1.092.827,30; Marktwert des Gesamtkapitals: 1.101.597,31; Marktwert des Eigenkapitals: 660.958,39; Aufgabenstellung 2: (Flow to Equity: 2026: 56.437,02; 2027: 74.112,88; 2028: 61.099,22; 2029: 61.634,40); Marktwert des Eigenkapitals: 660.951,77 | H228: null | I228: Answer must contain: Aufgabenstellung 1: (1) Beta Faktor verschuldet: 1,06; (2) Zinssatz(EK) verschuldet gerundet: 9,4%; (3) WACC gerundet: 7,18%; (4) (NOPLAT: 2026: 69.685; 2027: 84.854; 2028: 57.288); (5) (Free Cash Flow: 2026: 69.605; 2027: 98.854; 2028: 77.588); (6) Barwert ewige Rente: 2028: 1.092.827,30; (7) Marktwert des Gesamtkapitals: 1.101.597,31; (8) Marktwert des Eigenkapitals: 660.958,39; Aufgabenstellung 2: (9) (Flow to Equity: 2026: 56.437,02; 2027: 74.112,88; 2028: 61.099,22; 2029: 61.634,40); (10)Marktwert des Eigenkapitals: 660.951,77 | L228: Aufgabenstellung 1: 1. Berechnung NOPLAT= EBIT - Steuern; 2. Berechnung Free Cash Flow = NOPLAT + Abschreibungen + Buchwertabgang - Investitionen - Anstieg Vorräte - Anstieg Forderungen LL + Anstieg Rückstellungen + Anstieg Verbindlichkeiten LL; 3. Berechnung Barwert ewige Rente; 4. FCF abzinsen mit WACC; Aufgabenstellung 2: Berechnung Flow to Equity unter Berücksichtigung FK-Zinsen, Tax Shield, Veränderung FK und Abzinsung mit Zinssatz(EK) verschuldet | N228: mixed_accounting_framework | O228: 2024 | P228: management_accounting | Q228: company valuation | R228: company valuation, calculation Free Cash Flow and Flow to Equity, calculation WACC | S228: professional_examinations | T228: Prüfung Oktober 2025, Beispiel 12, Rechtslage mit Stand 31.12.2024 | U228: batch_import | V228: batch_admin | W228: 1 | X228: 2026-04-29 17:45:59.919761 | Y228: Manuel Kaburek | Z228: approved
A229: 227 | B229: 11913255_0001 | C229: Peter ist seit 10 Jahren als Gesellschafter zu 50 % an der Friseur OG beteiligt, über die er gemeinsam mit seinem Geschäftspartner mehrere Friseursalons in Wien betreibt. Der Umsatz liegt bereits seit drei Jahren konstant über EUR 700.000. Zudem gab es im Jahr 2024 einige Änderungen im Anlagevermögen der Friseur OG: Die Friseur OG schafft eine moderne Waschvorrichtung im Wert von EUR 12.000 netto an. Diese soll für 5 Jahre betrieblich genutzt werden. Die alte Waschvorrichtung, für die zum Zeitpunkt der Anschaffung ein investitionsbedingter Gewinnfreibetrag iHv EUR 9.000 geltend gemacht wurde, wurde dafür schon nach drei Jahren entfernt. Es wird ein neuer Spiegel im Wert von EUR 1.000 netto angeschafft. Dieser wird so schnell wie möglich abgeschrieben. Da die Friseure auch Haustermine annehmen, wurde von der Friseur OG ein Elektroauto für EUR 30.000 netto angeschafft. Ein Investitionsfreibetrag wird dafür nicht geltend gemacht. Im Mai 2024 wurden Wertpapiere im Sinne des § 14 Abs 7 Z 4 EStG im Wert von EUR 40.000, die für die Deckung des investitionsbedingten Gewinnfreibetrags im Jahr 2023 angeschafft wurden, getilgt. Im Juni 2024 werden Wertpapiere gleicher Art in Höhe von EUR 45.000 nachgekauft. Aufgrund der Verkleinerung eines Standorts wurde 2024 ein Gebäude, das 10 Jahre lang als Salon gedient hatte, mit einem Buchwert von EUR 200.000 für einen Verkaufspreis von EUR 250.000 netto verkauft. Ein Teil der zusätzlichen Liquidität wurde noch 2024 für einen kurz vor Jahresende eröffneten Zubau zu einem anderen Salon (ohne Erwerb von neuem Grund und Boden; Kosten: EUR 100.000 netto, die betriebliche Nutzungsdauer des Salons von 40 Jahren bleibt unverändert) genutzt. Aufgabenstellung 1. Wie ist die Friseur OG ertragsteuerlich zu behandeln? Erklären Sie, ob die Friseur OG der Rechnungslegungspflicht unterliegt und wie der steuerliche Gewinn zu ermitteln ist. Aufgabenstellung 2. Peter möchte möglichst verhindern, dass die durch den Verkauf des Gebäudes aufgedeckten stillen Reserven den steuerlichen Gewinn im Jahr 2024 erhöhen. Welche Maßnahme steht ihm dafür zu Verfügung? Welchen Einfluss hat diese Maßnahme auf den Gewinn des Jahres 2024? Aufgabenstellung 3. Unter Berücksichtigung der Gewinnauswirkungen der Aufgabenstellung 2. hat die Friseur OG im Jahr 2024 einen Gewinn von EUR 250.000 (vor Berücksichtigung eines etwaigen Gewinnfreibetrags) erwirtschaftet, wobei EUR 20.000 davon auf bereits endbesteuerte Dividenden aus einer Beteiligung entfallen. Dieser Gewinn soll durch einen möglichst hohen Gewinnfreibetrag verringert werden. Gehen Sie auf die einzelnen Änderungen im Anlagevermögen der Friseur OG ein und berechnen Sie den auf Peters Gewinnanteil entfallenden maximalen Gewinnfreibetrag für das Jahr 2024. Nehmen Sie dafür an, dass keine Sonderbetriebseinnahmen und -ausgaben sowie keine Ergänzungsbilanzen der Gesellschafter bestehen. Gehen Sie auch auf mögliche Nachversteuerungen ein. | D229: open_text | E229: interpretation_of_law | F229: open_text | G229: Lösung Aufgabenstellung 1: Die Friseur OG ist eine gewerblich tätige Personengesellschaft. Durch den Betrieb des Friseursalons werden Einkünfte aus Gewerbebetrieb iSd § 23 EStG erzielt. Die OG ist als Mitunternehmerschaft zu qualifizieren und bildet ein Einkünfteermittlungssubjekt (Feststellung nach § 188 BAO), jedoch kein Steuersubjekt. Die Gewinne werden also den Gesellschaftern entsprechend ihrer Anteilshöhe zugerechnet und auf Ebene der Gesellschafter zum Tarif nach § 33 EStG oder nach besonderem Steuersatz versteuert. Bei der Veräußerung von Grundstücken durch die OG wird die insgesamt geschuldete ImmoESt von den Abgabenkonten der Gesellschafter anteilsmäßig abgeführt. Aufgrund der konstanten Umsätze über EUR 700.000 besteht eine Verpflichtung zur Rechnungslegung nach § 189 Abs 1 Z 3 UGB. Der Gewinn ist nach § 5 Abs 1 EStG zu ermitteln (es gilt das Maßgeblichkeitsprinzip). Lösung Aufgabenstellung 2: Stille Reserven sind gem § 12 Abs 2 EStG der Unterschiedsbetrag zwischen dem Veräußerungserlös und dem Buchwert eines Wirtschaftsguts. Durch die gewinnbringende Veräußerung des Gebäudes würden 2024 EUR 50.000 an stillen Reserven der Friseur OG aufgedeckt werden. Durch den Verkauf des Gebäudes würde sich für die Gesellschafter der Friseur OG somit eine ImmoESt-Schuld von insgesamt EUR 15.000 (EUR 50.000 * 0,3) gem § 30a Abs 1 EStG ergeben. Natürliche Personen, so auch Peter als Mitunternehmer der Friseur OG, können aber stille Reserven, die bei der Veräußerung von Anlagevermögen aufgedeckt werden, von den Anschaffungskosten des im Wirtschaftsjahr der Veräußerung angeschafften Anlagevermögens absetzen (§ 12 Abs 1 erster Satz EStG), sodass eine steuerliche Aufdeckung der stillen Reserven im Veräußerungsjahr verhindert wird. Die Übertragung der stillen Reserven hat zur Voraussetzung, dass das veräußerte Anlagevermögen zuvor sieben Jahre zum Betrieb gehört hat (§ 12 Abs 3 Z 1 EStG), was beim veräußerten Teil des Salons hier der Fall ist. Des Weiteren können die stillen Reserven von Gebäuden gem § 12 Abs 4 Z 2 EStG nur auf neu angeschaffte oder hergestellte Gebäude übertragen werden. Auch diese Voraussetzung ist hier erfüllt. Der Zubau zählt als Teil des Salons auch im Wirtschaftsjahr der Veräußerung zum Anlagevermögen des Betriebs. Die Übertragung der stillen Reserven hat damit die Wirkung, dass der sonderbesteuerte Gewinn durch die Gebäudeveräußerung im Jahr 2024 auf Null reduziert wird. Die Übertragung der stillen Reserve hat weiters die Folge, dass der Parteienvertreter gem § 30c Abs 4 TS 3 EStG insoweit keine Selbstberechnung der ImmoESt vornehmen muss. Die Anschaffungskosten des Zubaus reduzieren sich gem § 12 Abs 6 EStG um die übertragenen stillen Reserven, somit von EUR 100.000 auf EUR 50.000. Dies hat ab dem Wirtschaftsjahr 2024 (Jahr der Inbetriebnahme) für die gesamte Nutzungsdauer eine geringere jährliche Abschreibung zur Folge. Die Halbjahresabschreibung 2024 (wegen Inbetriebnahme des Zubaus in zweiter Jahreshälfte) beträgt EUR 625 (40-jährige Nutzungsdauer entspricht dem Abschreibungssatz von 2,5 % gem § 8 Abs 1 EStG), somit die Hälfte der entsprechenden Abschreibung ohne § 12 EStG-Übertragung. Lösung Aufgabenstellung 3: Der Gewinnfreibetrag steht gem § 10 Abs 1 EStG natürlichen Personen zu. Bei Gesellschaften, bei denen die Gesellschafter als Mitunternehmer anzusehen sind, können nur die Gesellschafter den Gewinnfreibetrag mit einem der Gewinnbeteiligung entsprechenden Teilbetrag ansetzen (§ 10 Abs 2 EStG). Zunächst ist aber der kalkulatorische Gewinnfreibetrag auf Ebene der Friseur OG zu ermitteln: Bemessungsgrundlage für den Gewinnfreibetrag ist der Gewinn. Davon ausgenommen sind aber gem § 10 Abs 1 Z 1 TS 2 EStG ua Dividendeneinkünfte, auf die der besondere Steuersatz des § 27a Abs 1 EStG anzuwenden ist. Die Bemessungsgrundlage beträgt hier also EUR 230.000 (EUR 250.000 – EUR 20.000). Für die ersten EUR 33.000 Euro steht der sogenannte Grundfreibetrag iHv EUR 4.950 zu. Für diesen Betrag ist kein Investitionserfordernis gegeben (§ 10 Abs 1 Z 3 EStG). Für die nächsten EUR 145.000 der Bemessungsgrundlage steht ein investitionsbedingter Freibetrag (invGFB) von 13 % (somit EUR 18.850) zu, sofern dieser durch begünstigte Investitionen gedeckt ist. Für die verbleibenden EUR 52.000 (= EUR 230.000 - EUR 145.000 – EUR 33.000) steht ein investitionsbedingter Freibetrag von 7 % zu (somit EUR 3.640). Der höchstmögliche Gewinnfreibetrag beträgt auf Ebene der Friseur OG daher EUR 27.440 (Grundfreibetrag + invGFB), wobei dafür insgesamt EUR 22.490 an Investitionen nachgewiesen werden müssen. Zu den einzelnen Investitionen: Die neue Waschvorrichtung ist ein abnutzbares, körperliches Wirtschaftsgut mit einer betriebsgewöhnlichen Nutzungsdauer von mindestens 4 Jahren. Es ist daher gem 10 Abs 3 EStG ein begünstigtes Wirtschaftsgut, das mit den Anschaffungskosten zur Deckung des invGFB beiträgt (EUR 12.000). Der invGFB für das Wirtschaftsgut muss im Wirtschaftsjahr der Anschaffung geltend gemacht werden (§ 10 Abs 1 Z 5 EStG). Die alte Waschvorrichtung hat der Deckung eines invGFB in einem vergangenen Jahr gedient, aber nicht die geforderte betriebliche Nutzungsdauer von vier Jahren erreicht. Der Vorgang hat keinen Einfluss auf den invGFB 2024, aber der zuvor gewährte invGFB ist gem § 10 Abs 5 Z 1 EStG im Jahr 2024 iHv EUR 9.000 gewinnerhöhend anzusetzen (Nachversteuerung). Auch der Spiegel ist ein abnutzbares, körperliches Wirtschaftsgut mit einer betriebsgewöhnlichen Nutzungsdauer von mindestens 4 Jahren. Gem § 10 Abs 4 TS 4 EStG können aber geringwertige Wirtschaftsgüter (bis zu EUR 1.000), die gem § 13 EStG sofort in voller Höhe als Betriebsausgabe abgesetzt werden, nicht als begünstigtes Wirtschaftsgut herangezogen werden. Der Spiegel kann daher nicht der Deckung eines invGFB dienen. Gem § 10 Abs 4 TS 1 EStG kann der gekaufte Firmenwagen nicht als begünstigtes Wirtschaftsgut herangezogen werden. Eine Ausnahme für Elektroautos besteht nicht. Wertpapiere, die gem § 14 Abs 7 Z 4 EStG der Deckung von Pensionsrückstellungen dienen könnten, sind ebenso begünstigte Wirtschaftsgüter. Auch auf diese ist die Frist von vier Jahren anzuwenden. Gem § 10 Abs 5 Z 3 EStG kann jedoch eine Nachversteuerung durch eine Wertpapierersatzbeschaffung verhindert werden. Die neuen Wertpapiere müssen innerhalb von zwei Monaten nach der vorzeitigen Tilgung angeschafft werden. Die Beschaffung im Juni 2024 erfolgt in diesem Fall daher rechtzeitig. Soweit Wertpapiere der Ersatzbeschaffung dienen, kann ein neuer invGFB nicht in Anspruch genommen werden. Hier dienen die im Jahr 2024 beschafften Wertpapiere iHv EUR 40.000 dem Ersatz der vorzeitig getilgten Wertpapiere. Der Restbetrag von EUR 5.000 stellt ein begünstigtes Wirtschaftsgut für den invGFB 2024 dar. Der Zubau ist ebenso ein abnutzbares, körperliches Wirtschaftsgut mit einer betriebsgewöhnlichen Nutzungsdauer von über 4 Jahren. Gem § 10 Abs 1 Z 5 EStG ist der invGFB mit den Anschaffungs- oder Herstellungskosten begrenzt. Durch die Übertragung der stillen Reserven auf den Zubau haben sich die Anschaffungskosten gem § 12 Abs 6 EStG auf EUR 50.000 reduziert. In dieser Höhe kann der Zubau zur Deckung des invGFB dienen. Insgesamt hat die Friseur OG im Jahr 2024 daher die erforderlichen Investitionen für den höchstmöglichen invGFB 2024 getätigt. Da im Jahr 2024 begünstigte Wirtschaftsgüter mit Anschaffungskosten von insgesamt EUR 67.000 angeschafft wurden, ist gem § 10 Abs 7 EStG in einem gesonderten Verzeichnis oder im Anlageverzeichnis auszuweisen, für welches begünstigte Wirtschaftsgut der invGFB in welcher Höhe geltend gemacht wird. Die Zuordnung zu einem Wirtschaftsgut ist für den Fall einer Nachversteuerung notwendig. Auf Peter entfallen EUR 13.720 des Grundfreibetrags und des invGFB (50 % von EUR 27.440). | H229: null | I229: Answer must contain: (1) Qualifikation der Friseur OG als gewerblich tätige Personengesellschaft/Mitunternehmerschaft; Einkünfte aus Gewerbebetrieb iSd § 23 EStG; Feststellung nach § 188 BAO, kein Steuersubjekt, Zurechnung an Gesellschafter. (2) Rechnungslegungspflicht wegen Umsätzen konstant über EUR 700.000 nach § 189 Abs 1 Z 3 UGB und Gewinnermittlung nach § 5 Abs 1 EStG (Maßgeblichkeitsprinzip). (3) Definition stille Reserven gem § 12 Abs 2 EStG als Veräußerungserlös minus Buchwert; hier Gebäude: Buchwert EUR 200.000, Verkaufspreis EUR 250.000, stille Reserven EUR 50.000. (4) Hinweis auf ImmoESt-Folge aus Grundstücksveräußerung: insgesamt EUR 15.000 (= EUR 50.000 * 0,3) gem § 30a Abs 1 EStG und anteilsmäßige Abfuhr über Abgabenkonten der Gesellschafter. (5) Maßnahme zur Vermeidung der Gewinnrealisierung 2024: Übertragung stiller Reserven nach § 12 Abs 1 EStG auf im Wirtschaftsjahr der Veräußerung angeschafftes/hergestelltes Anlagevermögen; Voraussetzungen: Zugehörigkeit des veräußerten Anlagevermögens mind. 7 Jahre (§ 12 Abs 3 Z 1 EStG) und bei Gebäuden Übertragung nur auf neu angeschaffte/hergestellte Gebäude (§ 12 Abs 4 Z 2 EStG); Zubau zählt als Gebäude/Teil des Salons und ist im Wirtschaftsjahr 2024 angeschafft/hergestellt. (6) Wirkung der Übertragung: sonderbesteuerter Gewinn aus Gebäudeveräußerung 2024 wird auf Null reduziert; Parteienvertreter muss insoweit keine Selbstberechnung der ImmoESt vornehmen gem § 30c Abs 4 TS 3 EStG. (7) Konsequenz für Zubau-AK und AfA: Reduktion der Anschaffungskosten gem § 12 Abs 6 EStG von EUR 100.000 auf EUR 50.000; AfA-Satz 2,5 % bei 40 Jahren gem § 8 Abs 1 EStG; Halbjahresabschreibung 2024 wegen Inbetriebnahme in zweiter Jahreshälfte: EUR 625. (8) Gewinnfreibetrag: Anspruch natürlicher Personen gem § 10 Abs 1 EStG; bei Mitunternehmerschaft nur Gesellschafter anteilig gem § 10 Abs 2 EStG; zunächst Ermittlung auf Ebene OG. (9) Bemessungsgrundlage GFB: Gewinn EUR 250.000 minus endbesteuerte Dividenden EUR 20.000, da ausgenommen gem § 10 Abs 1 Z 1 TS 2 EStG iVm § 27a Abs 1 EStG; Bemessungsgrundlage EUR 230.000. (10) Staffelberechnung: Grundfreibetrag für erste EUR 33.000 = EUR 4.950 (§ 10 Abs 1 Z 3 EStG, kein Investitionserfordernis); invGFB 13 % für nächste EUR 145.000 = EUR 18.850; invGFB 7 % für verbleibende EUR 52.000 = EUR 3.640; maximaler GFB auf OG-Ebene EUR 27.440; erforderliche nachzuweisende Investitionen EUR 22.490. (11) Begünstigte Investitionen/Deckung invGFB 2024: neue Waschvorrichtung abnutzbar, körperlich, ND mind. 4 Jahre, begünstigt gem § 10 Abs 3 EStG; AK EUR 12.000; invGFB im Jahr der Anschaffung geltend zu machen (§ 10 Abs 1 Z 5 EStG). (12) Nachversteuerung alte Waschvorrichtung: vorzeitiges Ausscheiden vor 4 Jahren → zuvor gewährter invGFB EUR 9.000 im Jahr 2024 gewinnerhöhend anzusetzen gem § 10 Abs 5 Z 1 EStG; kein Einfluss auf invGFB 2024 laut Hauptlösung. (13) Spiegel: GWG bis EUR 1.000, sofort abzugsfähig gem § 13 EStG; daher nicht begünstigt gem § 10 Abs 4 TS 4 EStG. (14) Elektroauto/Firmenwagen: nicht begünstigt gem § 10 Abs 4 TS 1 EStG; keine Ausnahme für Elektroautos. (15) Wertpapiere: grundsätzlich begünstigt (Wertpapiere iSd § 14 Abs 7 Z 4 EStG); 4-Jahres-Frist; Tilgung EUR 40.000 und Ersatzbeschaffung zur Vermeidung Nachversteuerung gem § 10 Abs 5 Z 3 EStG; Ersatzbeschaffung innerhalb 2 Monaten, Juni 2024 rechtzeitig; kein neuer invGFB für Ersatzbetrag; Überschuss EUR 5.000 als begünstigtes Wirtschaftsgut für invGFB 2024. (16) Zubau: begünstigtes WG; invGFB gem § 10 Abs 1 Z 5 EStG durch AK/HK begrenzt; aufgrund § 12-Übertragung AK/HK EUR 50.000; in dieser Höhe zur Deckung des invGFB heranzuziehen. (17) Gesamtdeckung: erforderliche Investitionen für höchstmöglichen invGFB 2024 wurden getätigt; Hinweis auf Verzeichnis/Zuordnung gem § 10 Abs 7 EStG bei begünstigten WG mit AK gesamt EUR 67.000. (18) Anteil Peter: 50 % des maximalen Gewinnfreibetrags EUR 27.440 = EUR 13.720. Semantische Übereinstimmung ausreichend. Minor wording deviations allowed. | K229: Aufgabenstellung 3: Hinweis: Ebenso ist der Ansatz richtig zu werten, dass sich der Gewinn 2024 und damit auch die Bemessungsgrundlage des invGFB 2024 durch die Nachversteuerung um EUR 9.000 erhöht. Nach dieser Rechnung beträgt der mögliche invGFB nach § 10 Abs 1 Z 2 TS 3 EUR 4.270 und der maximale Gewinnfreibetrag insgesamt EUR 28.070. In diesem Fall müssten EUR 23.120 an begünstigten Investitionen nachgewiesen werden. Anmerkung: Bei Berücksichtigung der Nachversteuerung in der Bemessungsgrundlage für den InvGFB 2024 ist ebenso das Ergebnis von 50 % von EUR 28.070, somit EUR 14.035, als richtig zu werten. | N229: austrian_tax_law | O229: 2025 | P229: tax | Q229: Ertragsteuern und Abfassung von Abgabenerklärungen | R229: Gewinnfreibetrag und Übertragung stiller Reserven | S229: professional_examinations | U229: batch_import | V229: batch_admin | W229: 1 | X229: 2026-04-29 17:47:06.328621 | Y229: Manuel Kaburek | Z229: approved
A230: 228 | B230: 11913255_0002 | C230: Markus hat im Jahr 2015 eine große Spenglerei in Österreich gekauft, die er seitdem als Einzelunternehmer betreibt. Mit mittlerweile 62 Jahren beschließt Markus, die Spenglerei per 31.12.2024 um EUR 1.200.000 zu verkaufen. Der Erwerber übernimmt laut Vertrag auch alle betrieblichen Verbindlichkeiten. Die Bilanz der Spenglerei zeigt zum 31.12.2024 folgendes Bild: Aktiva: Anlagevermögen Buchwert EUR 600.000 (Teilwert EUR 1.000.000); Passiva: Eigenkapital Buchwert EUR 400.000 (Teilwert EUR 850.000) Umlaufvermögen Buchwert EUR 200.000 (Teilwert EUR 250.000) Verbindlichkeiten Buchwert EUR 400.000. Unter den Aktiva befinden sich weder Grundstücke noch Kapitalvermögen iSd § 27 EStG. Mit der Veräußerung seiner Spenglerei möchte Franz sämtliche bisherigen Erwerbstätigkeiten einstellen. Er hält daneben nur noch einige Wertpapiere im Privatvermögen. Aufgabenstellung 1: Berechnen Sie den Gewinn, den Markus durch die Veräußerung der Spenglerei erzielt! Gehen Sie dabei auch auf die Einkunftsart ein. Ermitteln Sie zudem den Firmenwert, den der Erwerber für die Spenglerei anzusetzen hat. Wie und ab wann kann dieser steuerlich geltend gemacht werden? Aufgabenstellung 2: Erläutern Sie für Markus die Optionen, die er zur ertragsteuerlichen Behandlung des Veräußerungsgewinns hat. Gehen Sie dabei auf die jeweiligen Voraussetzungen und Wirkungsweisen ein. Welche der Optionen dürfte für Markus hier die günstigste sein (ohne Berechnung der konkreten Steuerlast)? Was muss Markus tun, um diese Option auszuwählen? Aufgabenstellung 3: Nehmen Sie alternativ zum Grundsachverhalt an, dass Markus plant, nach der Betriebsveräußerung ab dem Jahr 2025 noch geringfügig als selbständiger Berater tätig zu sein (jährliche Einkünfte von EUR 5.000). Welche Folgen hat das in Bezug auf die ertragsteuerliche Begünstigung der Betriebsveräußerung? | D230: open_text | E230: interpretation_of_law | F230: open_text | G230: Lösung Aufgabenstellung 1: Veräußerungsgewinne sind Gewinne, die bei der Veräußerung oder der Aufgabe eines (Teil-)Betriebes erzielt werden (§ 24 Abs 1 EStG). Der Gewinn ist für den Zeitpunkt der Veräußerung zu ermitteln. Der Veräußerungsgewinn ist nach § 24 Abs 2 Satz 1 EStG der Betrag, um den der Veräußerungserlös nach Abzug der Veräußerungskosten den Wert des Betriebsvermögens übersteigt. Der Veräußerungsgewinn kann nach zwei Methoden ermittelt werden: Bruttomethode: Kaufpreis (EUR 1.200.000) + übernommene Verbindlichkeiten (EUR 400.000) = Veräußerungserlös (EUR 1.600.000) – Buchwert des Aktivvermögens (EUR 600.000 + EUR 200.000 = 800.000) = EUR 800.000 Veräußerungsgewinn. Nettomethode: Kaufpreis – Buchwert des Eigenkapitals = EUR 800.000 Veräußerungsgewinn. Als Firmenwert ist der Unterschiedsbetrag anzusetzen, um den die Gegenleistung für die Übernahme eines Betriebs die Werte der einzelnen Vermögensgegenstände abzüglich der Schulden im Zeitpunkt der Übernahme übersteigt (§ 203 Abs 5 UGB). Berechnung: Kaufpreis (EUR 1.200.000) + übernommene Verbindlichkeiten (EUR 400.000) – Teilwert der Wirtschaftsgüter (EUR 1.000.000 + EUR 250.000 = EUR 1.250.000) = Firmenwert (EUR 350.000). Der Firmenwert der Spenglerei beträgt also EUR 350.000. Gem § 8 Abs 3 EStG muss der Firmenwert von Gewerbebetrieben vom Käufer gleichmäßig verteilt auf 15 Jahre abgesetzt werden (ab 2025, weil Erwerb zum Jahreswechsel). Lösung Aufgabenstellung 2: 1. Option: Hälftesteuersatz Markus könnte den Hälftesteuersatz gem § 37 Abs 1 iVm Abs 5 EStG in Anspruch nehmen. Dabei werden außerordentliche Gewinne nur mit der Hälfte des auf das gesamte Einkommen entfallenden Durchschnittssteuersatzes besteuert. Außerordentliche Gewinne iSd Abs 5 leg cit sind Veräußerungsgewinne ua dann, wenn der Steuerpflichtige das 60. Lebensjahr vollendet hat und seine Erwerbstätigkeit mit der Veräußerung einstellt. Die Einkünfte aus Kapitalvermögen, die Markus weiterhin beziehen wird, stellen keine Erwerbstätigkeit dar. Markus hat die Spenglerei zudem vor mehr als sieben Jahren entgeltlich erworben. Er erfüllt daher alle Voraussetzungen für den Hälftesteuersatz. 2. Option: Verteilung auf 3 Jahre Markus kann den Veräußerungsgewinn gem § 37 Abs 2 Z 1 EStG gleichmäßig verteilt auf drei Jahre, beginnend mit dem Veranlagungsjahr 2024, ansetzen. Voraussetzung dafür ist lediglich, dass der letzte entgeltliche Erwerbsvorgang länger als sieben Jahre her ist. Diese Option hat den Vorteil, dass sich der Durchschnittssteuersatz wegen der geringeren Progression bei aufgeteilten Einkünften verringert. So kommt etwa der steuerfreie Einkommensanteil gem § 33 Abs 1 EStG im Ergebnis drei Mal zur Anwendung. 3. Option: Freibetrag Gem § 24 Abs 4 EStG sind die ersten EUR 7.300 des Veräußerungsgewinns steuerfrei. Dieser Freibetrag käme für Markus dann zur Anwendung, wenn er keinen Antrag auf den Hälftesteuersatz oder Verteilung auf drei Jahre stellt. Günstigkeitsbeurteilung: In Anbetracht des hohen Veräußerungsgewinns (EUR 800.000) ist offensichtlich, dass der Freibetrag gem § 24 Abs 4 EStG nicht die günstigste Option für Markus darstellt. Der volle Durchschnittssteuersatz würde 2024 nahe an 50 % herankommen. Eine Reduktion des Steuersatzes für den Veräußerungsgewinn auf knapp unter 25 % ist daher attraktiv. Selbst wenn der Veräußerungsgewinn auf drei Jahre verteilt würde, wäre der jeweilige Durchschnittssteuersatz bei einem jährlichen Einkommen von über EUR 200.000 weit über 25 %. Der Hälftesteuersatz dürfte hier daher die günstigste Regelung für Markus sein. Dafür ist gem § 37 Abs 5 letzter Satz EStG ein gesonderter Antrag zu stellen. Lösung Aufgabenstellung 3: Gem § 37 Abs 5 Z 3 EStG darf Markus nach der Betriebsveräußerung keiner Erwerbstätigkeit mehr nachgehen, wenn er den Hälftesteuersatz für den Veräußerungsgewinn in Anspruch nehmen möchte. Eine Erwerbstätigkeit ist schon dann anzunehmen, wenn die gesamten Einkünfte aus den ausgeübten Tätigkeiten EUR 730 übersteigen. Für die Begünstigung ist es nach VwGH-Rechtsprechung jedenfalls schädlich, wenn die Erwerbstätigkeit von vornherein geplant war. Für die Begünstigung ist daher eine längerfristige Einstellung der Erwerbstätigkeit erforderlich. Da Markus die Erwerbstätigkeit schon von vornherein geplant hat und damit EUR 5.000 pro Jahr erzielt, ist der Hälftesteuersatz auf die Veräußerungsgewinne nicht anwendbar. Ihm steht aber nach wie vor die Verteilung des Veräußerungsgewinns auf drei Jahre nach § 37 Abs 2 Z 1 EStG zu Verfügung. | H230: null | I230: Answer must contain: (1) Qualifikation als Veräußerungsgewinn iSd § 24 Abs 1 EStG (Veräußerung oder Aufgabe eines (Teil-)Betriebes) und Gewinnermittlung zum Zeitpunkt der Veräußerung. (2) Definition Veräußerungsgewinn gem § 24 Abs 2 Satz 1 EStG als Übersteigen des Veräußerungserlöses (nach Abzug Veräußerungskosten) über den Wert des Betriebsvermögens. (3) Veräußerungsgewinn rechnerisch EUR 800.000 und Herleitung über Bruttomethode: Kaufpreis EUR 1.200.000 + übernommene Verbindlichkeiten EUR 400.000 = Veräußerungserlös EUR 1.600.000; minus Buchwert Aktivvermögen EUR 600.000 + EUR 200.000 = EUR 800.000; Ergebnis EUR 800.000. (4) Alternativdarstellung Nettomethode: Kaufpreis – Buchwert Eigenkapital = EUR 800.000 (ohne dass beide Methoden zwingend parallel ausführlich sein müssen, aber Ergebnis und methodische Logik müssen korrekt sein). (5) Firmenwertdefinition gem § 203 Abs 5 UGB als Unterschiedsbetrag, um den die Gegenleistung die Werte der einzelnen Vermögensgegenstände abzüglich Schulden im Zeitpunkt der Übernahme übersteigt. (6) Firmenwertberechnung: Kaufpreis EUR 1.200.000 + übernommene Verbindlichkeiten EUR 400.000 – Teilwert Wirtschaftsgüter (EUR 1.000.000 + EUR 250.000 = EUR 1.250.000) = Firmenwert EUR 350.000. (7) Steuerliche Geltendmachung Firmenwert beim Käufer gem § 8 Abs 3 EStG gleichmäßig auf 15 Jahre, Beginn ab 2025 (Erwerb zum Jahreswechsel). (8) Darstellung der drei Begünstigungsoptionen für den Veräußerungsgewinn: Hälftesteuersatz (§ 37 Abs 1 iVm Abs 5 EStG), Verteilung auf 3 Jahre (§ 37 Abs 2 Z 1 EStG; Beginn Veranlagungsjahr 2024), Freibetrag (§ 24 Abs 4 EStG: erste EUR 7.300 steuerfrei bei keinem Antrag auf andere Optionen). (9) Voraussetzungen Hälftesteuersatz: Vollendung 60. Lebensjahr, Einstellung der Erwerbstätigkeit mit der Veräußerung; Kapitalvermögenseinkünfte sind keine Erwerbstätigkeit; letzter entgeltlicher Erwerb länger als sieben Jahre her. (10) Wirkungsweise Hälftesteuersatz: außerordentliche Gewinne nur mit der Hälfte des auf das gesamte Einkommen entfallenden Durchschnittssteuersatzes besteuert. (11) Verteilung auf 3 Jahre: gleichmäßige Verteilung über drei Jahre, Vorteil geringere Progression/mehrfache Wirkung des § 33 Abs 1 EStG im Ergebnis. (12) Günstigkeitsbeurteilung: bei EUR 800.000 ist Freibetrag nicht günstig; Hälftesteuersatz voraussichtlich günstigster (Reduktion auf knapp unter 25 % vs Durchschnittssteuersätze bei > EUR 200.000 pro Jahr weit über 25 % auch bei 3-Jahres-Verteilung). (13) Erfordernis zur Auswahl der günstigsten Option: gesonderter Antrag gem § 37 Abs 5 letzter Satz EStG. (14) Variante Aufgabenstellung 3: Nachveräußerliche Erwerbstätigkeit schädlich für Hälftesteuersatz gem § 37 Abs 5 Z 3 EStG; Erwerbstätigkeit schon bei gesamten Einkünften > EUR 730; schädlich, wenn von vornherein geplant (VwGH). (15) Konsequenz bei geplanter Beratungstätigkeit EUR 5.000 p.a.: Hälftesteuersatz nicht anwendbar; Verteilung auf drei Jahre nach § 37 Abs 2 Z 1 EStG weiterhin möglich. Semantische Übereinstimmung ausreichend. Minor wording deviations allowed. | N230: austrian_tax_law | O230: 2025 | P230: tax | Q230: Ertragsteuern und Abfassung von Abgabenerklärungen | R230: Betriebsveräußerung | S230: professional_examinations | U230: batch_import | V230: batch_admin | W230: 1 | X230: 2026-04-29 17:50:27.024122 | Y230: Manuel Kaburek | Z230: approved
A231: 229 | B231: 11913255_0003 | C231: Welche der folgenden Aussagen treffen/trifft zu? Kreuzen Sie die richtige(n) Antwortmöglichkeit(en) an! | D231: multi_choice | E231: interpretation_of_law | F231: multi_choice | G231: C,D | H231: {"a": "Wenn Einzelunternehmer Forschungst\u00e4tigkeiten betreiben, k\u00f6nnen sie ihren Unternehmerlohn von bis zu EUR 100.000 pro Wirtschaftsjahr als beg\u00fcnstigte Forschungsausgabe geltend machen.", "b": "Die Forschungspr\u00e4mie reduziert die Bemessungsgrundlage der Einkommen- oder K\u00f6rperschaftsteuer.", "c": "Die Forschungspr\u00e4mie ist f\u00fcr Steuerpflichtige auch in Verlustjahren in voller H\u00f6he liquidit\u00e4tswirksam.", "d": "Sofern keine Forschungsbest\u00e4tigung nach \u00a7 118a BAO vorliegt, darf eine Forschungspr\u00e4mie nur dann gew\u00e4hrt werden, wenn der Steuerpflichtige ein Gutachten der Forschungsf\u00f6rderungsgesellschaft vorlegt, das die Forschungst\u00e4tigkeit nach \u00a7 108c EStG best\u00e4tigt.", "e": "Die Forschungspr\u00e4mie ist in der ESt- oder K\u00f6St-Erkl\u00e4rung eines Wirtschaftsjahres zu beantragen."} | I231: Exact set match required (C and D). Order irrelevant. Case-insensitive. No additional choices allowed. | L231: Gem § 1 Abs 2 Z 5 ForschungsprämienVO können Einzelunternehmer einen Betrag von EUR 50 für jede im Wirtschaftsjahr geleistete Tätigkeitsstunde in begünstigter Forschung und experimenteller Entwicklung, maximal jedoch EUR 86.000 pro Wirtschaftsjahr (fiktiver Unternehmerlohn) geltend machen. Die Forschungsprämie ist gem § 108c Abs 4 EStG als Steuergutschrift konzipiert. Sie reduziert also die Steuerlast unmittelbar und nicht nur den Gewinn. Da die Forschungsprämie nicht nur eine anfallende Steuerlast reduziert, sondern auch bei Verlust tatsächlich ausbezahlt wird, fördert sie die Forschung auch in Verlustjahren. Die FFG hat zur Geltendmachung einer Forschungsprämie auf Anforderung des Steuerpflichtigen ein Jahresgutachten zu erstellen. Das Jahresgutachten hat sich auf alle Forschungsschwerpunkte und Investitionen zu beziehen, aus denen für die Forschungsprämie maßgebliche Aufwendungen resultieren (§ 4 Abs 1 ForschungsprämienVO). Die Forschungsprämie ist gem § 108c Abs 3 EStG abgesondert vom Veranlagungsverfahren in einem eigenen Prämienverfahren jeweils für ein Kalenderjahr zu beantragen. | N231: austrian_tax_law | O231: 2025 | P231: tax | Q231: Ertragsteuern und Abfassung von Abgabenerklärungen | R231: Forschungsprämie | S231: professional_examinations | U231: batch_import | V231: batch_admin | W231: 1 | X231: 2026-04-29 17:56:01.433708 | Y231: Manuel Kaburek | Z231: approved
A232: 230 | B232: 11913255_0004 | C232: Welche der folgenden Aussagen treffen/ trifft zu? Kreuzen Sie die richtige(n) Antwortmöglichkeit(en) an! | D232: multi_choice | E232: interpretation_of_law | F232: multi_choice | G232: A,B,E | H232: {"a": "Ein Zuschuss des Arbeitgebers zur Kinderbetreuung der Arbeitnehmer kann nicht nur im Vorhinein, sondern auch als sp\u00e4terer Kostenersatz bei Nachweis der Kosten steuerfrei gew\u00e4hrt werden.", "b": "Eine Dienstwohnung, die dem Dienstnehmer verbilligt zur Verf\u00fcgung gestellt wird, stellt einen steuerpflichtigen Vorteil aus dem Dienstverh\u00e4ltnis dar.", "c": "Direkte Geldleistungen, die der Arbeitgeber dem Arbeitnehmer zur Konsumation von Mahlzeiten gew\u00e4hrt, sind steuerfrei.", "d": "Der Arbeitgeber kann einen betriebs\u00e4rztlichen Dienst nur leitenden Angestellten steuerfrei zu Verf\u00fcgung stellen.", "e": "Mitarbeiterrabatte f\u00fcr Waren oder Dienstleistungen, die der Arbeitgeber im allgemeinen Gesch\u00e4ftsverkehr anbietet, sind bis zu 20 % unabh\u00e4ngig von der absoluten H\u00f6he des Rabatts steuerfrei."} | I232: Exact set match required (A, B and E). Order irrelevant. Case-insensitive. No additional choices allowed. | L232: Durch das Progressionsabgeltungsgesetz 2024 kann ab 2024 der Kinderbetreuungszuschuss von höchstens EUR 2.000 nicht nur direkt an die Betreuungsperson, die Betreuungseinrichtung oder als Gutschein gewährt werden, sondern auch als Kostenersatz (§ 3 Abs 1 Z 13 lit b TS 4 EStG). Für die Zuordnung zu den Einkünften aus nichtselbständiger Arbeit ist der Konnex zum Dienstverhältnis ausschlaggebend. Eine verbilligte Dienstwohnung erfüllt keinen Befreiungstatbestand des EStG. Details zur Höhe des Sachbezugs regelt § 2 SachbezugswerteVO. Steuerfrei sind nur freie oder verbilligte Mahlzeiten, die der Arbeitgeber zur Verköstigung am Arbeitsplatz freiwillig gewährt, oder Gutscheine bis zu einem Wert von EUR 8, die nur zur Konsumation von Mahlzeiten von einer Gaststätte oder einem Lieferservice eingelöst werden können (§ 3 Abs Abs 1 Z 17 EStG). Der geldwerte Vorteil aus der Benützung von Einrichtungen wie etwa eines Betriebsarztes muss allen Arbeitnehmern oder bestimmten Gruppen von Arbeitnehmern gewährt werden, um von der Steuerbefreiung gem § 3 Abs 1 Z 13 lit a EStG zu profitieren. Leitende Angestellte bilden aber keine Arbeitnehmergruppe. Zulässig wären etwa alle Arbeitnehmer des kaufmännischen Dienstes, des Außendienstes etc. § 3 Abs 1 Z 21 lit c EStG stellt bei Mitarbeiterrabatten bis zu 20 % nicht auf die absolute Höhe des Rabatts ab. Solche Rabatte sind von der allgemeinen EUR 1.000-Grenze des § 3 Abs 1 Z 21 lit d EStG ausdrücklich ausgenommen. | N232: austrian_tax_law | O232: 2025 | P232: tax | Q232: Ertragsteuern und Abfassung von Abgabenerklärungen | R232: Mitarbeiter-Benefits | S232: professional_examinations | U232: batch_import | V232: batch_admin | W232: 1 | X232: 2026-04-29 17:58:05.366639 | Y232: Manuel Kaburek | Z232: approved
A233: 231 | B233: 11913255_0005 | C233: Herr Fugger ist Eigentümer eines Mietwohngebäudes in Wien. Er hat es am 3.4.2021 um EUR 4.000.000 erworben. Davon entfielen nachgewiesen EUR 1.300.000 auf Grund und Boden, der Rest auf das Gebäude, welches in den Vollanwendungsbereich des MRG fällt. Das Grundstück befindet sich in seinem Privatvermögen. Im Jahr 2024 nimmt er einige bauliche Änderungen am Gebäude vor. Im Februar und März lässt er zwei Wohnungen zusammenlegen. Die Kosten belaufen sich auf EUR 600.000. Im Mai lässt er die Fassade reparieren, weil aufgrund von Feuchtigkeit der Verputz an einigen Stellen abgeblättert ist. Derartige Ausbesserungen erfolgen regelmäßig alle zehn Jahre. Es entstehen Kosten iHv EUR 10.000. Im Juli beschädigt Hagel einen Teil des Daches. Anstelle der bloßen Ausbesserung der Schäden lässt Herr Fugger das gesamte Dach abtragen und komplett neu errichten. Die Kosten betragen EUR 75.000. Für den Dachumbau wurden keine Förderungen in Anspruch genommen. Im September lässt er erstmalig einen Personenaufzug in das Gebäude einbauen. Hierauf entfallen Kosten iHv EUR 100.000. Im November lässt er das Gebäude mit Wärmedämmung ausrüsten. Darauf entfallen Kosten iHv EUR 60.000. Dafür wurden allerdings EUR 30.000 in Form von steuerfreien staatlichen Förderungen in Anspruch genommen. Aufgabenstellung 1: Berechnen Sie den steuerlichen Wertansatz des Gebäudes per Ende 2024. Gehen Sie davon aus, dass Herr Fugger von einer möglichst schnellen Abschreibung Gebrauch machen möchte. Aufgabenstellung 2: Begründen Sie, in welchem betraglichen Ausmaß Herr Fugger die angefallenen Kosten für die baulichen Änderungen steuerlich möglichst zeitnah berücksichtigen kann. | D233: open_text | E233: interpretation_of_law | F233: open_text | G233: Lösung Aufgabenstellung 1: Herr Fugger bezieht Einkünfte aus Vermietung und Verpachtung iSd § 28 Abs 1 Z 1 EStG (im Sachverhalt kein Hinweis auf Gewerblichkeit der Vermietung). Entsprechend wird die Bemessungsgrundlage für die Einkommensteuer auf Grund des Überschusses der Einnahmen über die Werbungskosten gebildet (§§ 15, 16 EStG). Infolgedessen sind die Anschaffungskosten für das Gebäude zu aktivieren und um die Abschreibung für Abnutzung zu verringern. Die Kosten für Grund und Boden unterliegen nicht der AfA. Da diese hier exakt angegeben sind, ist die 40 %-Vermutung des § 16 Abs 1 Z 8 EStG nicht heranzuziehen. Insgesamt wurden für das Gebäude folglich im Jahr der Anschaffung EUR 2.700.000 aktiviert. Nach § 16 Abs 1 Z 8 lit d EStG sind bei Gebäuden, mit denen Einkünfte iSv § 28 EStG erzielt werden, ohne Nachweis der Nutzungsdauer (hierzu kein Hinweis im Sachverhalt) 1,5 % pro Jahr abzuschreiben. Das sind im vorliegenden Fall EUR 2.700.000 x 0,015 = EUR 40.500 p.a. Allerdings gibt es die Möglichkeit, eine beschleunigte AfA für Gebäude gem § 16 Abs 1 Z 8 lit e EStG vorzunehmen. Im ersten Jahr (2021) ist eine Abschreibung in dreifacher Höhe (4,5 % = EUR 121.500), im Folgejahr (2022) in doppelter Höhe (3 % = EUR 81.000) möglich. Da eine möglichst schnelle Abschreibung erfolgen soll, beträgt der steuerliche Wertansatz per Ende 2024 somit EUR 2.416.500 (EUR 2.700.000 x 0,045 + EUR 2.700.000 x 0,03 + EUR 2.700.000 x 0,015 x 2 = EUR 283.500; EUR 2.700.000 – EUR 283.500 = EUR 2.416.500). Lösung Aufgabenstellung 2: Zunächst ist zwischen Herstellungs- und Erhaltungsaufwänden zu unterscheiden: Zusammenlegung und Aufzug: Die Zusammenlegung und der Aufzug sind Herstellungsaufwand. Darunter fallen nachträgliche Herstellungskosten, wenn also ein Wirtschaftsgut neu hergestellt wird oder seine Wesensart verändert wird. Bei der Zusammenlegung verändert sich die Wesensart des Gebäudes insoweit, als einzelne Teile anders genutzt werden können und nicht von untergeordneter Bedeutung sind (vgl EStR 2000 Rz 6467). Beim Aufzug handelt es sich um eine wesentliche Verbesserung des Gebäudes, weil sich die Wesensart des Gebäudes derart verändert, dass der Nutzungswert wesentlich erhöht ist (vgl EStR 2000 Rz 6476). Da das Mietwohngebäude dem Sachverhalt nach in den Vollanwendungsbereich des MRG fällt und es sich um Maßnahmen iSd §§ 3-5 MRG handelt, können gem § 28 Abs 3 Z 1 EStG die Herstellungsaufwände über Antrag auf 15 Jahre verteilt abgesetzt werden. Dies ist deutlich schneller als die Normalabschreibung gem § 16 Abs 1 Z 8 lit d EStG. Daher: Zusammenlegung: EUR 600.000 x 0,067 = EUR 40.000. Aufzug: EUR 100.000 x 0,067 = EUR 6.666,67. Fassade, Dach und Wärmedämmung: Für diese Aufwendungen ist § 28 Abs 2 EStG anzuwenden. Hierbei muss unterschieden werden, ob es sich um Instandsetzungs- oder Erhaltungsaufwand handelt. Instandsetzungsaufwendungen sind gem § 28 Abs 2 fünfter Satz EStG jene Aufwendungen, die nicht zu den Anschaffungs- oder Herstellungskosten gehören und allein oder zusammen mit Herstellungsaufwand den Nutzungswert des Gebäudes wesentlich erhöhen oder seine Nutzungsdauer wesentlich verlängern. Instandhaltungsaufwendungen sind hingegen nicht regelmäßig jährlich anfallende Aufwendungen. Hierunter fallen insb der Austausch unwesentlicher Gebäudeteile oder wenn es durch die Maßnahme nicht zu einer wesentlichen Erhöhung des Nutzungswert oder einer wesentlichen Verlängerung der Nutzungsdauer kommt (EStR 2000 Rz 6460). Bei der Reparatur der Fassade ist die Schwelle der wesentlichen Erhöhung des Nutzungswerts oder der wesentlichen Verlängerung der Nutzungsdauer nicht erreicht. Es liegen nicht regelmäßig jährlich anfallende Instandhaltungsaufwendungen iSv § 28 Abs 2 TS 1 EStG vor. Damit besteht ein Wahlrecht, den Aufwand auf Antrag auf 15 Jahre zu verteilen oder sofort abzuschreiben. Nach der Angabe ist eine Sofortabschreibung in 2024 in Höhe der gesamten EUR 10.000 gewünscht. Der Umbau des Daches ist hingegen ein Instandsetzungsaufwand, weil die Nutzungsdauer des Gebäudes wesentlich verlängert wird und damit kein bloßer Instandhaltungsaufwand vorliegt (wobei gleichzeitig die Wesensart des Gebäudes nicht verändert wird und damit ein Herstellungsaufwand ausgeschlossen ist). Da die Aufwendungen nicht von steuerfreien Subventionen gedeckt sind, ist eine gleichmäßige Aufteilung auf 15 Jahre vorzunehmen. Dabei sind im Jahr 2024 EUR 5.000 abzugsfähig: EUR 75.000 x 0,067 = EUR 5.000. Die Wärmedämmung führt ebenso zu einer wesentlichen Erhöhung des Nutzungswerts und stellt damit einen Instandsetzungsaufwand dar, der grds über 15 Jahre zu verteilen ist (EStR 2000 Rz 6469; BFG 27.6.2019, RV/7100083/2019). Die Absetzbarkeit ist allerdings in dem Umfang ausgeschlossen, als die Kosten durch steuerfreie Subventionen gedeckt sind. Die staatlichen Förderungen decken hierbei die Hälfte der Kosten ab, weswegen nur EUR 30.000 auf 15 Jahre verteilt werden können. Damit sind im Jahr 2024 EUR 2.000 abzugsfähig. Daher: Fassade: EUR 10.000. Dach: EUR 75.000 x 0,067 = EUR 5.000. Wärmedämmung: (EUR 60.000 – EUR 30.000) x 0,5 x 0,067 = EUR 2.000 | H233: null | I233: Answer must contain: (1) Qualifikation der Einkünfte als Vermietung und Verpachtung iSd § 28 Abs 1 Z 1 EStG und Bemessungsgrundlage als Überschuss der Einnahmen über die Werbungskosten (§§ 15, 16 EStG). (2) Aussage, dass Anschaffungskosten des Gebäudes zu aktivieren sind und um AfA zu verringern; Grund und Boden unterliegt nicht der AfA. (3) Aussage, dass die 40 %-Vermutung des § 16 Abs 1 Z 8 EStG nicht heranzuziehen ist, weil Grund und Boden hier exakt angegeben ist. (4) Ermittlung aktivierter Gebäudewert bei Anschaffung: EUR 2.700.000 (EUR 4.000.000 – EUR 1.300.000). (5) Regel-AfA ohne Nutzungsdauernachweis: 1,5 % p.a. gem § 16 Abs 1 Z 8 lit d EStG und Berechnung EUR 2.700.000 x 0,015 = EUR 40.500 p.a. (6) Beschleunigte AfA gem § 16 Abs 1 Z 8 lit e EStG: im ersten Jahr (2021) dreifache Höhe 4,5 % = EUR 121.500, im Folgejahr (2022) doppelte Höhe 3 % = EUR 81.000. (7) Steuerlicher Wertansatz per Ende 2024 bei möglichst schneller Abschreibung: EUR 2.416.500 samt Rechenlogik (AfA gesamt EUR 283.500 aus 4,5 % + 3 % + 1,5 % x 2; EUR 2.700.000 – EUR 283.500). (8) Abgrenzung bauliche Änderungen: Unterscheidung Herstellungs- vs Erhaltungsaufwand. (9) Zusammenlegung und Aufzug als Herstellungsaufwand: nachträgliche Herstellungskosten bei Neuherstellung/Wesensartänderung; Zusammenlegung Wesensartänderung (anders nutzbare Teile, nicht untergeordnet) unter Hinweis auf EStR 2000 Rz 6467; Aufzug wesentliche Verbesserung/Nutzungswert wesentlich erhöht unter Hinweis auf EStR 2000 Rz 6476. (10) Anwendung § 28 Abs 3 Z 1 EStG wegen Vollanwendungsbereich MRG und Maßnahmen iSd §§ 3-5 MRG: Herstellungsaufwände über Antrag auf 15 Jahre verteilt absetzbar (schneller als Normalabschreibung gem § 16 Abs 1 Z 8 lit d EStG). (11) Betragliche zeitnahe Berücksichtigung 2024 für Herstellungsaufwand bei 15-Jahres-Verteilung: Zusammenlegung EUR 600.000 x 0,067 = EUR 40.000; Aufzug EUR 100.000 x 0,067 = EUR 6.666,67. (12) Für Fassade/Dach/Wärmedämmung Anwendung § 28 Abs 2 EStG und Definition Instandsetzungsaufwendungen gem § 28 Abs 2 fünfter Satz EStG (wesentliche Erhöhung Nutzungswert oder wesentliche Verlängerung Nutzungsdauer) sowie Instandhaltungsaufwendungen als nicht regelmäßig jährlich anfallende Aufwendungen inkl Hinweis EStR 2000 Rz 6460. (13) Fassade als Instandhaltungsaufwand: Schwelle der wesentlichen Erhöhung/Verlängerung nicht erreicht; Wahlrecht 15-Jahres-Verteilung oder Sofortabschreibung; gewünschte Sofortabschreibung 2024 iHv EUR 10.000. (14) Dachumbau als Instandsetzungsaufwand: wesentliche Verlängerung der Nutzungsdauer; kein Instandhaltungsaufwand und kein Herstellungsaufwand (Wesensart nicht verändert); keine steuerfreien Subventionen; 15-Jahres-Aufteilung; 2024 abzugsfähig EUR 75.000 x 0,067 = EUR 5.000. (15) Wärmedämmung als Instandsetzungsaufwand: wesentliche Erhöhung Nutzungswert; grds 15-Jahres-Verteilung (EStR 2000 Rz 6469; BFG 27.6.2019, RV/7100083/2019); Abzugsverbot soweit durch steuerfreie Subventionen gedeckt; nur EUR 30.000 verteilbar; 2024 abzugsfähig EUR 2.000 und Formel wie in Lösung: (EUR 60.000 – EUR 30.000) x 0,5 x 0,067 = EUR 2.000. Semantische Übereinstimmung ausreichend. Minor wording deviations allowed. | N233: austrian_tax_law | O233: 2025 | P233: tax | Q233: Ertragsteuern und Abfassung von Abgabenerklärungen | R233: Mietwohngebäude | S233: professional_examinations | U233: batch_import | V233: batch_admin | W233: 1 | X233: 2026-04-29 17:59:13.453894 | Y233: Manuel Kaburek | Z233: approved
A234: 232 | B234: 11913255_0006 | C234: Prompt (Spalte D): MC-Frage Beteiligungsertragsbefreiung Welche der folgenden Aussagen zu Beteiligungsertragsbefreiungen im Sinne des § 10 KStG treffen/trifft zu? Kreuzen Sie die richtige(n) Antwortmöglichkeit(en) an! | D234: multi_choice | E234: interpretation_of_law | F234: multi_choice | G234: B,E | H234: {"a": "R\u00fcckverg\u00fctungen, die von Erwerbs- und Wirtschaftsgenossenschaften gem \u00a7 8 Abs 3 Z 2 KStG gew\u00e4hrt werden und aus dem Mitgliedergesch\u00e4ft erwirtschaftet wurden, fallen nicht unter die Beteiligungsertragsbefreiung des \u00a7 10 Abs 1 KStG.", "b": "Verluste aus der Ver\u00e4u\u00dferung einer ausl\u00e4ndischen K\u00f6rperschaft, an der eine internationale Schachtelbeteiligung iSd \u00a7 10 Abs 2 und 3 KStG besteht, sind nicht steuerneutral, sofern die Option zugunsten der Steuerwirksamkeit ausge\u00fcbt wurde.", "c": "Soweit Gewinnanteile aus einer internationalen Schachtelbeteiligung im Ausland abzugsf\u00e4hig sind, sind sie unter den Voraussetzungen des \u00a7 10 Abs 2 KStG in \u00d6sterreich dennoch steuerbefreit.", "d": "Eine internationale Schachtelbeteiligung iSd \u00a7 10 Abs 2 KStG liegt vor, wenn die Beteiligung entweder mindestens bereits ein Jahr besteht oder das Beteiligungsausma\u00df mindestens 10 % betr\u00e4gt.", "e": "Geht eine internationale Schachtelbeteiligung durch die Verlegung des Sitzes nach \u00d6sterreich unter und hat die beteiligte inl\u00e4ndische K\u00f6rperschaft die Option nach \u00a7 10 Abs 3 Z 1 KStG nicht ausge\u00fcbt, gilt der h\u00f6here Teilwert der Wirtschaftsg\u00fcter als Buchwert."} | I234: Exact set match required (B and E). Order irrelevant. Case-insensitive. No additional choices allowed. | L234: Gem § 10 Abs 1 Z 2 KStG sind Rückvergütungen von inländischen Erwerbs- und Wirtschaftsgenossenschaften nach § 8 Abs 3 Z 2 KStG steuerfrei. Gem § 8 Abs 3 Z 2 KStG handelt es sich hierbei um Rückvergütungen, die von Erwerbs- und Wirtschaftsgenossenschaften in Form von Kaufpreisrückvergütungen gewährt werden und aus dem Mitgliedergeschäft erwirtschaftet wurden. Gem § 10 Abs 3 KStG bleiben Veräußerungsgewinne, Veräußerungsverluste und sonstige Wertänderungen aus nicht optierten internationalen Schachtelbeteiligungen iSd § 10 Abs 2 KStG außer Ansatz. Wird die Option gem § 10 Abs 3 Z 1 KStG hingegen ausgeübt, sind die Veräußerungsverluste steuerwirksam Nach § 10 Abs 4 KStG sind Gewinnanteile im Sinne des § 10 Abs 1 Z 5 bis 7 KStG – somit auch Gewinnbeteiligungen aus internationalen Schachtelbefreiungen – insoweit nicht befreit, als sie bei der ausländischen Körperschaft abzugsfähig sind. § 10 Abs 2 KStG listet die Voraussetzungen für eine internationale Schachtelbeteiligung auf: Der Steuerpflichtige muss unter § 7 Abs 3 KStG fallen oder eine vergleichbare unbeschränkt steuerpflichtige ausländische Gesellschaft sein und zu mindestens zehn Prozent seit mindestens einem Jahr an der ausländischen Gesellschaft beteiligt sein, die selbst einer inländischen Kapitalgesellschaft verbunden ist oder die Voraussetzungen in Anlage 2 zum EStG erfüllen. Diese Voraussetzungen sind also kumulativ zu verstehen und müssen jedenfalls erfüllt sein. Gem § 10 Abs 3 Z 5 KStG gilt der höhere Teilwert im Zeitpunkt der Sitzverlegung als Buchwert, soweit für sie keine Option zugunsten der Steuerwirksamkeit erklärt worden ist. | N234: austrian_tax_law | O234: 2025 | P234: tax | Q234: Ertragsteuern und Abfassung von Abgabenerklärungen | R234: Beteiligungsertragsbefreiung | S234: professional_examinations | U234: batch_import | V234: batch_admin | W234: 1 | X234: 2026-04-29 17:59:55.491351 | Y234: Manuel Kaburek | Z234: approved
A235: 233 | B235: 11913255_0007 | C235: Die Theta AG (Sitz und Ort der Geschäftsleitung in Salzburg) hält 100 % der Kapitalanteile und Stimmrechte an der Iota GmbH (Sitz und Ort der Geschäftsleitung in Wien). Die Iota GmbH hält wiederum 60 % der Kapitalanteile und Stimmrechte an der Kappa GmbH (Sitz und Ort der Geschäftsleitung in Wien) und 50 % der Kapitalanteile und Stimmrechte an der Lambda GmbH (Sitz und Ort der Geschäftsleitung in Eisenstadt). Weitere 10 % der Kapitalanteile und Stimmrechte an der Lambda GmbH werden von der Kappa GmbH gehalten. Außerdem hält die Kappa GmbH seit dem 1.1.2022 noch 30 % an der My GmbH (Sitz und Ort der Geschäftsleitung in München). Die Beteiligungsausmaße sind seit dem 1.1.2022 unverändert und die Theta AG ist seit dem 1.1.2022 Gruppenträgerin der größtmöglichen Unternehmensgruppe nach § 9 KStG. Die aus dem Unternehmensrecht übergeleiteten Einzelabschlüsse ergeben folgende vorläufige steuerliche Gewinne für das Jahr 2024: Theta AG: EUR +50.000. Iota GmbH: EUR +100.000. Kappa GmbH: EUR +200.000. Lambda GmbH: EUR -150.000. My GmbH: EUR -50.000 (nach deutschem Steuerrecht EUR -100.000). Folgende steuerliche Verlustvorträge wurden zum 1.1.2024 in Evidenz gehalten: Theta AG: EUR 50.000 (aus dem Vorjahr). Iota GmbH: EUR 300.000 (aus der Zeit vor dem 1.1.2022). Kappa GmbH: EUR 0. Lambda GmbH: EUR 100.000 (aus der Zeit vor dem 1.1.2022). My GmbH: EUR 0. Aufgabenstellung 1: Begründen Sie, welche Gesellschaften Teil der steuerlichen Unternehmensgruppe der Theta AG sein können! Aufgabenstellung 2: Ermitteln Sie den geringstmöglichen steuerlichen Gewinn der Theta AG. Ermitteln Sie dafür zunächst die steuerlichen Ergebnisse auf Ebene der Gruppenmitglieder. Aufgabenstellung 3: In welchem Umfang können die Verluste der My GmbH in der steuerlichen Unternehmensgruppe im Jahr 2024 verwertet werden, wenn die Kappa GmbH 80 % der Kapitalanteile und Stimmrechte an der My GmbH halten würde? | D235: open_text | E235: interpretation_of_law | F235: open_text | G235: Lösung Aufgabenstellung 1: Die Theta AG kann gem § 9 Abs 3 TS 1 KStG als unbeschränkt steuerpflichtige, unter § 7 Abs 3 KStG fallende Kapitalgesellschaft Gruppenträgerin sein. Als Gruppenmitglied kommen gem § 9 Abs 2 TS 1 KStG die Gesellschaften Iota GmbH, Kappa GmbH und Lambda GmbH in Betracht, weil diese unbeschränkt körperschaftsteuerpflichtig sind, unter § 7 Abs 3 KStG fallen und eine ausreichende finanzielle Verbindung > 50% gem § 9 Abs 4 KStG besteht. Bei Iota GmbH und Kappa GmbH ist diese Verbindung unmittelbar gem § 9 Abs 4 TS 1 KStG (zu 100% bzw 60%), bei Lambda GmbH mittelbar gem § 9 Abs 4 TS 3 KStG gegeben (wegen anteiliger Zurechnung der von Kappa GmbH gehaltenen 10%-Beteiligung an Iota GmbH und sodann Theta GmbH, in Summe beträgt die multiplikative Gesamtbeteiligung an Lambda GmbH daher 56%, vgl KStR 2013 Rz 1045). Die beschränkt steuerpflichtige My GmbH käme zwar grundsätzlich als ausländisches Gruppenmitglied in Betracht, sie ist aber nicht ausreichend finanziell verbunden. Lösung Aufgabenstellung 2: Der in der Gruppe verwertbare Verlust der Lambda GmbH beträgt EUR -150.000. Er wird zunächst der Iota GmbH zugerechnet. Die Vorgruppenverluste der Lambda GmbH müssen gem § 9 Abs 6 Z 4 KStG mit zukünftigen Gewinnen der Lambda GmbH verrechnet werden. Das steuerliche Ergebnis der Kappa GmbH beträgt EUR +200.000. Dieses wird ebenfalls der Iota GmbH zugerechnet. Das eigene vorläufige steuerliche Ergebnis der Iota GmbH beträgt EUR +100.000. Die Vorgruppenverluste iHv EUR 300.000 können gem § 9 Abs 6 Z 4 KStG bis zur Höhe des eigenen Gewinns gegengerechnet werden, sodass das eigene Ergebnis EUR 0 beträgt. EUR 200.000 bleiben als Vorgruppenverluste bei der Iota GmbH in Evidenz. Die der Iota GmbH zugerechneten Ergebnisse von Kappa und Lambda sind nicht Teil des eigenen Gewinns (siehe KStR 2013 Rz 1071). Zusätzlich werden der Iota GmbH EUR -150.000 der Lambda GmbH und EUR +200.000 der Kappa GmbH zugerechnet, sodass in der Folge EUR +50.000 dem Gruppenträger zugerechnet werden können. Das vorläufige steuerliche Ergebnis der Theta AG beträgt EUR +50.000. Dazu kommen die zugerechneten EUR +50.000 von Iota GmbH. Das sind in Summe EUR +100.000. Die Verluste aus dem Vorjahr können beim Gruppenträger als Sonderausgabe gem § 8 Abs 4 Z 2 KStG in voller Höhe abgezogen werden, weil die 75 % Grenze gem 8 Abs 4 Z 2 lit a KStG nicht überschritten ist. Das Gruppenergebnis beträgt daher EUR 50.000. Lösung Aufgabenstellung 3: My GmbH kann nun ausländisches Gruppenmitglied sein, weil sie mit dem unbeschränkt steuerpflichtigen Gruppenmitglied Lambda GmbH unmittelbar finanziell verbunden ist (§ 9 Abs 2 TS 2 iVm Abs 4 TS 1 KStG; mit Deutschland besteht umfassende Amtshilfe). Gem § 9 Abs 6 Z 6 KStG können nur nach österreichischem Steuerrecht ermittelte Verluste zugerechnet werden und nur insoweit, als die die nach ausländischem Steuerrecht ermittelten Verluste nicht übersteigen. Es ist daher der geringere Verlust nach österreichischem Steuerrecht relevant. Gem § 9 Abs 6 Z 6 KStG können die Verluste können ferner höchstens im Ausmaß der Beteiligung zugerechnet werden (EUR 40.000, 80 % Beteiligung). Darüber hinaus ist zu berücksichtigen, dass diese Auslandsverluste nur iHv 75 % des inländischen Gruppeneinkommens (eigenen Einkommens aller unbeschränkt steuerpflichtigen Gruppenmitglieder und des Gruppenträgers) zugerechnet werden dürfen (§ 9 Abs 6 Z 6 vorletzter Satz KStG). Dieser Höchstbetrag der Auslandsverlustzurechnung ist somit EUR 75.000 (75 % von EUR 100.000), weil der Verlustvortrag des Gruppenträgers für diese Zwecke das inländische Gruppeneinkommen nicht kürzt. Da der Höchstbetrag nicht erreicht wird, kann die My GmbH ihren gesamten (anteiligen) nach österreichischem Recht berechneten Verlust iHv EUR 40.000 in die Gruppe zurechnen. | H235: null | I235: Answer must contain: (1) Theta AG als Gruppenträgerin gem § 9 Abs 3 TS 1 KStG (unbeschränkt steuerpflichtige, unter § 7 Abs 3 KStG fallende Kapitalgesellschaft). (2) Gruppenmitglieder gem § 9 Abs 2 TS 1 KStG: Iota GmbH, Kappa GmbH, Lambda GmbH (unbeschränkt körperschaftsteuerpflichtig, unter § 7 Abs 3 KStG, finanzielle Verbindung > 50% gem § 9 Abs 4 KStG). (3) Finanzielle Verbindung: Iota unmittelbar 100% gem § 9 Abs 4 TS 1 KStG; Kappa unmittelbar 60% gem § 9 Abs 4 TS 1 KStG; Lambda mittelbar gem § 9 Abs 4 TS 3 KStG inkl multiplikative Gesamtbeteiligung 56% (anteilige Zurechnung der 10%-Beteiligung der Kappa GmbH an Iota GmbH und sodann Theta GmbH; Verweis KStR 2013 Rz 1045). (4) My GmbH im Grundfall: grundsätzlich möglich als ausländisches Gruppenmitglied, aber nicht ausreichend finanziell verbunden. (5) Gruppenergebnis: in der Gruppe verwertbarer Verlust Lambda GmbH EUR -150.000 wird zunächst Iota GmbH zugerechnet; Vorgruppenverluste Lambda GmbH gem § 9 Abs 6 Z 4 KStG nur mit zukünftigen Gewinnen der Lambda GmbH verrechenbar. (6) Steuerliches Ergebnis Kappa GmbH EUR +200.000 wird Iota GmbH zugerechnet. (7) Eigenes vorläufiges steuerliches Ergebnis Iota GmbH EUR +100.000; Vorgruppenverluste Iota GmbH iHv EUR 300.000 gem § 9 Abs 6 Z 4 KStG bis zur Höhe des eigenen Gewinns gegenzurechnen → eigenes Ergebnis EUR 0; EUR 200.000 verbleiben als Vorgruppenverluste in Evidenz; zugerechnete Ergebnisse von Kappa und Lambda nicht Teil des eigenen Gewinns (KStR 2013 Rz 1071). (8) Zurechnung an Gruppenträger: Iota nach Zurechnung von -150.000 (Lambda) und +200.000 (Kappa) → EUR +50.000 an Theta AG. (9) Vorläufiges steuerliches Ergebnis Theta AG EUR +50.000 + zugerechnete EUR +50.000 = EUR +100.000. (10) Verlustvortrag Gruppenträger EUR 50.000 als Sonderausgabe gem § 8 Abs 4 Z 2 KStG in voller Höhe abzugsfähig, weil 75 %-Grenze gem 8 Abs 4 Z 2 lit a KStG nicht überschritten → Gruppenergebnis EUR 50.000. (11) Variante Auslandsgesellschaft: My GmbH als ausländisches Gruppenmitglied bei 80 % Beteiligung (finanzielle Verbindung mit unbeschränkt steuerpflichtigem Gruppenmitglied Lambda GmbH unmittelbar gem § 9 Abs 2 TS 2 iVm Abs 4 TS 1 KStG; umfassende Amtshilfe mit Deutschland). (12) § 9 Abs 6 Z 6 KStG: nur nach österreichischem Steuerrecht ermittelte Verluste zurechenbar und nur insoweit, als sie die nach ausländischem Steuerrecht ermittelten Verluste nicht übersteigen → geringerer Verlust maßgeblich. (13) Zurechnungsobergrenze § 9 Abs 6 Z 6 KStG: höchstens im Ausmaß der Beteiligung → EUR 40.000 (80 %). (14) Weitere Begrenzung: Auslandsverluste nur iHv 75 % des inländischen Gruppeneinkommens zurechenbar (§ 9 Abs 6 Z 6 vorletzter Satz KStG) → Höchstbetrag EUR 75.000 (75 % von EUR 100.000), Verlustvortrag des Gruppenträgers kürzt inländisches Gruppeneinkommen hierfür nicht. (15) Ergebnis Variante: Höchstbetrag nicht erreicht → gesamter (anteiliger) nach österreichischem Recht berechneter Verlust der My GmbH iHv EUR 40.000 in die Gruppe zurechenbar. Semantische Übereinstimmung ausreichend. Minor wording deviations allowed. | K235: Aufgabenstellung 1: Anmerkung: Punkte werden auch bei Addition im Sinne der aA, dh 60 %, vergeben. | N235: austrian_tax_law | O235: 2025 | P235: tax | Q235: Ertragsteuern und Abfassung von Abgabenerklärungen | R235: Steuergruppe | S235: professional_examinations | U235: batch_import | V235: batch_admin | W235: 1 | X235: 2026-04-29 18:00:39.315751 | Y235: Manuel Kaburek | Z235: approved
A236: 234 | B236: 11913255_0008 | C236: Die selbständige Ärztin Frau Omikron kauft für ihre Wohnung am 1.12.2024 zwei gebrauchte Kronleuchter auf einem Flohmarkt um je EUR 400. Zuhause stellt sie jedoch fest, dass die Kronleuchter leider zu groß sind. Daher ist sie froh, diese am 16.12.2024 um je EUR 800 an Bekannte weiterverkaufen zu können. Für einen Kronleuchter erhält sie das Geld sofort in bar, das Entgelt für den anderen Kronleuchter wird ihr am 15.1.2025 überwiesen. Im Jahr 2024 tätigt Frau Omikron keine weiteren derartigen Geschäfte. Welche der Aussagen ist/sind richtig? Kreuzen Sie die richtige(n) Antwortmöglichkeit(en) an! | D236: multi_choice | E236: interpretation_of_law | F236: multi_choice | G236: E | H236: {"a": "Die Verk\u00e4ufe der Kronleuchter unterliegen als Eink\u00fcnfte aus selbst\u00e4ndiger Arbeit gem \u00a7 22 Z 1 lit b TS 2 EStG der Einkommensteuer.", "b": "Die \u00dcbersch\u00fcsse aus dem Verkauf der Kronleuchter unterliegen als Spekulationseink\u00fcnfte einem besonderen Steuersatz iHv 27,5 %.", "c": "Frau Omikron erzielt in 2024 sonstige Eink\u00fcnfte iHv EUR 800.", "d": "Frau Omikron erzielt Spekulationseink\u00fcnfte iHv EUR 1.600.", "e": "Die Eink\u00fcnfte des Jahres 2024 aus dem Verkauf der Kronleuchter bleiben einkommensteuerfrei."} | I236: Exact set match required (E). Order irrelevant. Case-insensitive. No additional choices allowed. | L236: Die Verkäufe der Kronleuchter haben keinen Bezug zur selbständigen Tätigkeit als Ärztin und sind daher sonstige Einkünfte. Spekulationseinkünfte werden nach dem Tarif gem § 33 EStG versteuert. Frau Omikron erzielt in 2024 sonstige Einkünfte iHv lediglich EUR 400, weil sie nur das Geld für einem Kronleuchter im Jahr 2024 erhält. Der Verkauf des zweiten Kronleuchters führt zwar ebenfalls zu sonstigen Einkünften, diese fließen aber erst im Jahr 2025 zu. Frau Omikron erzielt zwar insgesamt (verteilt auf 2024 und 2025) Veräußerungserlöse iHv 1.600, die Spekulationseinkünfte sind jedoch eine Nettogröße, sodass von den Veräußerungserlösen die Anschaffungskosten gem § 31 Abs 2 EStG abzuziehen sind. Soweit Frau Omikron im Jahr 2024 Spekulationseinkünfte erzielt, bleiben diese im Ergebnis steuerfrei, weil sie die Grenze von EUR 440 nicht übersteigen (§ 31 Abs 3 EStG). Entsprechendes würde auch für 2025 gelten. | N236: austrian_tax_law | O236: 2025 | P236: tax | Q236: Ertragsteuern und Abfassung von Abgabenerklärungen | R236: Einkommenssteuer | S236: professional_examinations | U236: batch_import | V236: batch_admin | W236: 1 | X236: 2026-04-29 18:02:32.343958 | Y236: Manuel Kaburek | Z236: approved
